Workbook

Sheet README
A1: Minzhong land deeds: OCR tables
A3: Source
A4: OCR_results/ (407 pages, 234 items) in eastd143a-team-Youxiao, joined to the catalogue chinese_land_records_235.csv (jackieldyh branch) by Pitt ID.
A6: Sheets
A7: Documents: one row per OCR page. Catalogue fields (reliable), auto-extracted OCR fields (need checking), 0/1 formula flags, OCR quality counts, cleaned text.
A8: Narrative_moves: the 12-move structure of a private deed, with counts.
A9: Formulae_by_period: private-deed formulae by period.
A10: Official_formulae: bureaucratic formulae by regime (Qing / Republic / PRC).
A11: Deed_types: every 立…契 title found, grouped into stages.
A12: Land_and_money: land-layer and currency vocabulary.
A13: Deed_chains: documents that cite one another.
A14: OCR_issues: known recognition errors and their effect.
... A23: Companion analysis page: https://claude.ai/artifact/XqAXHuUGLNm4J5q7sqxaro

Sheet Documents
A1: Page ID | B1: Item ID | C1: Page | D1: Year (start) | E1: Year (end) | F1: Period | G1: Regime | H1: Catalogue date | I1: County (normalised) | J1: Place (catalogue) | K1: Catalogue nature | L1: Owner (catalogue) | M1: Seller (catalogue) | N1: Buyer (catalogue) | O1: Box / folder | P1: Page type | Q1: Deed title 立…契 | R1: Dates in text | S1: Seller / author (OCR) | T1: Buyer X處 (OCR) | U1: Price phrase (OCR) | V1: Currency | W1: Location 坐落 | X1: Place-name 土名 | Y1: Land terms | Z1: Middleman 中人 | AA1: Scribe 代筆 | AB1: Witnesses 在見 | AC1: Female consent 知契…氏 | AD1: Redemption term (yrs) | AE1: Form headings | AF1: Issuing office | AG1: Holder 業戶/右給 | AH1: Serial 字第…號 | AI1: 今因 motive | AJ1: 自願 voluntary | AK1: 託中 mediated | AL1: 三面言議 | AM1: 即日交足 paid | AN1: 無重典/來歷 warranty | AO1: 出頭承當 seller answers | AP1: 取贖 redemption | AQ1: 永遠 perpetual | AR1: 無反悔/異言 | AS1: 今欲有憑 closing | AT1: 併繳 prior deeds | AU1: 內改 correction | AV1: 吉日 | AW1: 為…事 | AX1: 案奉/等因奉此 | AY1: 須至…者 | AZ1: 右給… | BA1: 罰/逾限 | BB1: 訴訟/憑證 | BC1: Characters | BD1: Seal/image blocks | BE1: Truncated blocks | BF1: English mixed in | BG1: Pitt URL | BH1: OCR text (cleaned, ≤3000 chars)
A2: 31735064607413_001 | B2: 31735064607413 | C2: 1 | D2: 1886 | E2: 1886 | F2: =IF(D2="","?",IF(D2<1796,"pre-1796",IF(D2<1912,"1796-1911",IF(D2<1949,"1912-1948","1949+")))) -> 1796-1911 | G2: =IF(D2="","?",IF(D2<1912,"Qing",IF(D2<1949,"Republic","PRC"))) -> Qing | H2: 1886 | I2: 福清 | J2: 福建省福清縣 | K2: Government | L2: 高恭地 | O2: Box 2, Folder 60 | P2: Other / fragment | AE2: 契 | 尾 | AI2: 0 | AJ2: 0 | AK2: 0 | AL2: 0 | AM2: 0 | AN2: 0 | AO2: 0 | AP2: 0 | AQ2: 0 | AR2: 0 | AS2: 0 | AT2: 0 | AU2: 0 | AV2: 0 | AW2: 0 | AX2: 1 | AY2: 0 | AZ2: 0 | BA2: 0 | BB2: 0 | BC2: 131 | BD2: 1 | BE2: 2 | BF2: 0 | BG2: https://digital.library.pitt.edu/islandora/object/pitt:31735064607413 | BH2: 契尾布九三三雷查該縣於十五年正月二十日奉准部咨開司案所有本縣舊有印信等項應行更換...查該縣於十五年正月二十日奉准部咨開司案所有本縣舊有印信等項應行更換...高恭地聖蓮店一間高山市街致千卷百肆拾肆福清高恭地准此拾捌年捌月三...拾...日陸拾叁捌拾分陸拾叁捌拾分
A3: 31735064607421_001 | B3: 31735064607421 | C3: 1 | D3: 1946 | E3: 1951 | F3: =IF(D3="","?",IF(D3<1796,"pre-1796",IF(D3<1912,"1796-1911",IF(D3<1949,"1912-1948","1949+")))) -> 1912-1948 | G3: =IF(D3="","?",IF(D3<1912,"Qing",IF(D3<1949,"Republic","PRC"))) -> Republic | H3: 1946/1951 | I3: 福清 | J3: 福建省福清縣 | K3: Government | M3: 張學車 | N3: 陳書寶 | 張學車 | O3: Box 4, Folder 173 | P3: Private deed + state certificate | Q3: 立契 | R3: 公元一九四六年; 中華民國三十五年; 民國35年; 民國三十五年 | S3: 日期上手 | U3: 幣壹佰捌拾萬元; 幣壹萬元正 | V3: 人民幣; 國幣 | W3: 福州市五甲街 | Y3: 店屋; 地基; 基地 | AI3: 1 | AJ3: 0 | AK3: 1 | AL3: 0 | AM3: 1 | AN3: 1 | AO3: 1 | AP3: 0 | AQ3: 0 | AR3: 1 | AS3: 0 | AT3: 1 | AU3: 0 | AV3: 0 | AW3: 0 | AX3: 0 | AY3: 0 | AZ3: 0 | BA3: 0 | BB3: 0 | BC3: 571 | BD3: 5 | BE3: 0 | BF3: 0 | BG3: https://digital.library.pitt.edu/islandora/object/pitt:31735064607421 | BH3: 元九月市長日發給收執繳納稅額屋價屋式四至面積坐落不動產種類姓名承受人人民幣壹拾萬捌仟九人民幣壹佰捌拾萬元坐西向東五柱二棚樓屋直進壹欄南至隣屋九九九地號西至隣屋九九九地號北至隣屋九九九地號零畝零分伍厘肆毫五甲街門牌二七號宅陳寶學車附註監證人簽名蓋章立契日期上手原契區段別姓名原所有姓名公元一九四六年六月三區二二段九九八地號(此契人受未權有原請中交聯此)中華民國三十五年六月日賣斷契張學車民國35年9月28日21998219981401立賣斷契張學車民國三十五年五月間買斷王依增店屋(座坐落福州市五甲街地方門牌19號屬3區11段1401地號面積14毫定着物坐西向東五柱直進單欄排上下堵木尺橫澗前後均壹丈長深寸零直深三丈四尺零東至五甲街西至隣屋九九九號南至隣屋九九九號北至隣屋九九七號上至椽瓦天下至礫石地基地六至叙明屋內所有附屬物品一切俱全今因別置托中將上列店屋連同基地賣斷與陳書寶處為業議定斷國幣壹萬元正其款即日收足其屋即聽陳家移轉登記享受所有權收益使用自由處分串自賣斷之後價定終休永不敢別生枝節有言借湊畫牘之理但此店屋係車自置與房族上下人等無干亦無重疊典押來歷各等情如有發生意外轉輾均由車得欺人處理負責不涉買主之事彼此兩願各無反悔恐口易翻特立賣斷契壹紙並繳王依增斷契壹紙樊汝濟斷契壹紙楊生春斷契稅証各壹紙鄔細細佛斷契壹紙稅証式紙共成捌紙付執為据
A4: 31735064607439_001 | B4: 31735064607439 | C4: 1 | D4: 1929 | E4: 1929 | F4: =IF(D4="","?",IF(D4<1796,"pre-1796",IF(D4<1912,"1796-1911",IF(D4<1949,"1912-1948","1949+")))) -> 1912-1948 | G4: =IF(D4="","?",IF(D4<1912,"Qing",IF(D4<1949,"Republic","PRC"))) -> Republic | H4: 1929 | I4: 古田 | J4: 福建省古田縣 | K4: Government | L4: 林枝貴 | O4: Box 3, Folder 139 | P4: Official form | Q4: 立之不動產舊契 | R4: 中華民國十年 | U4: 價壹萬零九百零四元 | W4: 四至原契已載明白遵章呈驗應納紙價 | AE4: 驗 稅 契 證 | 福建財政廳 | AF4: 福建財政廳 | AG4: 林枝秀 | AH4: 契證新字第 306 號 | AI4: 0 | AJ4: 0 | AK4: 0 | AL4: 0 | AM4: 0 | AN4: 0 | AO4: 0 | AP4: 0 | AQ4: 0 | AR4: 0 | AS4: 1 | AT4: 1 | AU4: 0 | AV4: 0 | AW4: 1 | AX4: 1 | AY4: 1 | AZ4: 1 | BA4: 1 | BB4: 1 | BC4: 318 | BD4: 2 | BE4: 2 | BF4: 0 | BG4: https://digital.library.pitt.edu/islandora/object/pitt:31735064607439 | BH4: 驗稅契證福建財政廳為給發驗稅契證事案奉國民政府財政部訓令頒發驗契暫行條例及各省驗契章程凡在此次開辦驗契以前成立之不動產舊契無已稅未稅均應一律限期呈驗換發新契紙倘逾限不呈驗遇有訴訟不能作為憑證如經人告發或官廳查出者並加以處罰業由財政部咨行司法部通飭遵辦以為匿驗者等因奉此當經擬具徵收方法電奉財政部核准照辦並已訂定本堂驗契補充辦法分別通令布告遵照在案茲據業戶林枝秀呈繳已稅田契壹張產價壹萬零九百零四元坐落四至原契已載明白遵章呈驗應納紙價壹元八角分註冊費五角附加教育費貳角業已如數收訖除註冊外合填驗稅契證粘連原契給收執管業須至契證者奉財政廳令定逾限按屆遞加紙價十分之二右給業戶林枝秀准此中華民國十年八月日給小契證新字第306號系所......
A5: 31735064607447_001 | B5: 31735064607447 | C5: 1 | D5: 1866 | E5: 1866 | F5: =IF(D5="","?",IF(D5<1796,"pre-1796",IF(D5<1912,"1796-1911",IF(D5<1949,"1912-1948","1949+")))) -> 1796-1911 | G5: =IF(D5="","?",IF(D5<1912,"Qing",IF(D5<1949,"Republic","PRC"))) -> Qing | H5: 1866 | I5: 閩侯（閩縣・侯官・林森） | J5: 福建省閩邑 | K5: Personal | M5: 林春源 | O5: Box 1, Folder 41 | P5: Private deed | Q5: 立賣斷契 | R5: 同治伍年 | S5: 林春源 | U5: 銀庫砵壹拾貳兩正 | W5: 閩邑嘉崇里秋龍巷 | Z5: 將此地屋賣斷; 陳友梅 | AA5: 張秉中 | AB5: 堂弟 | AI5: 1 | AJ5: 1 | AK5: 1 | AL5: 0 | AM5: 1 | AN5: 1 | AO5: 1 | AP5: 1 | AQ5: 1 | AR5: 0 | AS5: 1 | AT5: 0 | AU5: 1 | AV5: 1 | AW5: 0 | AX5: 0 | AY5: 0 | AZ5: 0 | BA5: 0 | BB5: 0 | BC5: 339 | BD5: 0 | BE5: 0 | BF5: 0 | BG5: https://digital.library.pitt.edu/islandora/object/pitt:31735064607447 | BH5: 立賣斷契林春源承父遺下有式柱破屋壹直參堵右邊更有殘地壹塊在王家店後坐落閩邑嘉崇里秋龍巷地方其屋前至王家店後至王家屋左至李家屋右至翰家屋其地前至翰家屋後至王家屋肆至載明今因乏用托中友將此地屋賣斷王處為業參面言議本日賣斷得地屋價足色鏡銀庫砵壹拾貳兩正其銀即日隨券收清其地屋俱聽王家掌管永遠為世業價足心愿永斷葛藤不敢別生枝節異說翻言以至後日亦不敢言取贖湊盡之事但此地屋係源遺父遺已業歷掌無異與親疏房份伯叔兄弟侄等無干並未曾重張曲當他人財物如有來歷不明承葛各等情弊源自愿出頭承當與王家毫無干涉其原契夾連別業不得繳賣今欲有憑立賣斷契壹紙付執永遠為照內塗遺壹字標照陸王姓在店後居住者出入皆由王家店內而行標照壹同治伍年參月吉日立賣斷契林春源謹堂叔長發在見堂弟春榮樓中友陳友梅樓地保代筆張秉中謹
A6: 31735064607454_001 | B6: 31735064607454 | C6: 1 | D6: 1862 | E6: 1862 | F6: =IF(D6="","?",IF(D6<1796,"pre-1796",IF(D6<1912,"1796-1911",IF(D6<1949,"1912-1948","1949+")))) -> 1796-1911 | G6: =IF(D6="","?",IF(D6<1912,"Qing",IF(D6<1949,"Republic","PRC"))) -> Qing | H6: 1862 | K6: Personal | M6: 张华富 | O6: Box 1, Folder 36 | P6: Private deed + state certificate | Q6: 立賣斷山契 | S6: 張華富 | U6: 價銅錢捌仟五百文正; 價銅錢捌仟伍百文正 | W6: 田里南坑上名鳳坑仔即目上至崗頂下 | Y6: 皮骨; 茶山; 山場 | Z6: 張華春 | AA6: 詹王佐鑾 | AI6: 0 | AJ6: 1 | AK6: 1 | AL6: 1 | AM6: 1 | AN6: 1 | AO6: 0 | AP6: 0 | AQ6: 1 | AR6: 0 | AS6: 1 | AT6: 0 | AU6: 0 | AV6: 0 | AW6: 0 | AX6: 0 | AY6: 0 | AZ6: 0 | BA6: 0 | BB6: 0 | BC6: 308 | BD6: 0 | BE6: 0 | BF6: 0 | BG6: https://digital.library.pitt.edu/islandora/object/pitt:31735064607454 | BH6: 立賣斷山契人張華富承祖遺下置有皮骨茶山壹片坐落田里南坑上名鳳坑仔即目上至崗頂下至日榜左至本張宅分水為界右至亦本張分水為界今來俱出四至明白茲因缺錢應用情愿託中說諭甘將榕桐竹茶雜木皮骨山場盡立契出賣斷與程金寶名下邊為業當日三面言議時值價銅錢捌仟五百文正成契之日一頓交足不少分文並無債化員準折之類亦無重典復賣之理所賣斷其山的係自己股內物業與親房伯叔兄弟侄人等各不相干自賣斷之後任從買者永遠管業收租不敢阻執此係兩家甘允各無異說今欲有憑故立賣斷契為照當日實交得賣斷價銅錢捌仟伍百文正足訖所有上手契卷一時不及尋出日後尋出不堪行用執照同治壬戌元年柒月日立賣斷契人張華富張說諭人張喜孫張為中人張華春在見人張華應張代筆人詹王佐鑾張華富
A7: 31735064607462_001 | B7: 31735064607462 | C7: 1 | D7: 1931 | E7: 1931 | F7: =IF(D7="","?",IF(D7<1796,"pre-1796",IF(D7<1912,"1796-1911",IF(D7<1949,"1912-1948","1949+")))) -> 1912-1948 | G7: =IF(D7="","?",IF(D7<1912,"Qing",IF(D7<1949,"Republic","PRC"))) -> Republic | H7: 1931 | K7: Personal | M7: 高天钏 | N7: 郑祚龙 | O7: Box 3, Folder 142 | P7: Private deed | Q7: 立送字 | R7: 民國貳拾年 | S7: 高天釗 | X7: 過洋 | Y7: 墳 | AA7: 經手人族 | AB7: 兄居碑誌 | AI7: 1 | AJ7: 0 | AK7: 0 | AL7: 0 | AM7: 0 | AN7: 1 | AO7: 1 | AP7: 0 | AQ7: 1 | AR7: 1 | AS7: 1 | AT7: 0 | AU7: 0 | AV7: 0 | AW7: 0 | AX7: 0 | AY7: 0 | AZ7: 0 | BA7: 0 | BB7: 0 | BC7: 255 | BD7: 0 | BE7: 0 | BF7: 0 | BG7: https://digital.library.pitt.edu/islandora/object/pitt:31735064607462 | BH7: 立送字永遠山地契高天釗承祖純剛公派下有壙穴坐產土名過洋山北山墓埕下大坪園下有吉穴上至大坪園下至山坡左至居耐墓右至居炉墓親歷四至明白今因要用將此山地送友鄭祚龍處造墳葬親即听鄭家破土興工造墳葬親面約前無遮蔽後無開鑿金至於鄭家高者鋪平低者補滿堆疊圓山嶺仍憑順處一派路徑通行通用開門放水听從其便係天釗但此山地承祖物業前別房伯叔兄弟姪無干並未曾重張曲當情弊如有來歷不明係天釗出頭承當鄭家無涉到後帮葬花紅一概全免兩相允諾各毋反悔今啟有憑立送字永遠墳地契壙帛為據民國貳拾年春初立送字高天釗在見兄居碑誌代筆經手人族姪信釗代筆人
A8: 31735064607470_001 | B8: 31735064607470 | C8: 1 | D8: 1887 | E8: 1887 | F8: =IF(D8="","?",IF(D8<1796,"pre-1796",IF(D8<1912,"1796-1911",IF(D8<1949,"1912-1948","1949+")))) -> 1796-1911 | G8: =IF(D8="","?",IF(D8<1912,"Qing",IF(D8<1949,"Republic","PRC"))) -> Qing | H8: 1887 | I8: 閩侯（閩縣・侯官・林森） | J8: 福建省閩縣 | K8: Personal | M8: 王錦發 | N8: 王錦枝 | O8: Box 2, Folder 63 | P8: Private deed | Q8: 立賣斷契 | R8: 光緒拾叁年 | S8: 王錦發 | U8: 價錠銀柒拾伍兩正 | W8: 閩邑橫山鋪秋龍社 | Y8: 地基; 店屋 | Z8: 賣斷與堂兄; 林細弟 | AA8: 李逢銓 | AB8: 堂兄 | AC8: 母 林氏 | AI8: 1 | AJ8: 1 | AK8: 1 | AL8: 1 | AM8: 1 | AN8: 1 | AO8: 1 | AP8: 0 | AQ8: 1 | AR8: 1 | AS8: 1 | AT8: 0 | AU8: 0 | AV8: 0 | AW8: 0 | AX8: 0 | AY8: 0 | AZ8: 0 | BA8: 0 | BB8: 0 | BC8: 394 | BD8: 0 | BE8: 0 | BF8: 0 | BG8: https://digital.library.pitt.edu/islandora/object/pitt:31735064607470 | BH8: 立賣斷契王錦發原祖遺闔分份下有肆柱店面右半半內門窓戶榻前榻板地棚一切俱全坐產閩邑橫山鋪秋龍社地方前至官街後王清官屋在左邊錦枝半內店右至何家店上至掾桁磚瓦下至廊石礫石地基地陸至俱載明白今因要用情願將此右邊店面半內託中友賣斷與堂兄錦枝處永遠為業三面言議本日賣斷得店屋價錠銀柒拾伍兩正庫砵大錠白足色足兌其銀即日隨契親手收足其右邊半內店屋即所堂兄錦枝永遠管業千秋或自己居住或召租他人或折毀改式起蓋聽從其便係錦發自斷之後價足心願永斷葛藤向後永不敢言贖言湊言盡亦不敢別生枝節索取花紅之理但此店屋右半內係錦發祖遺闔分份下物業與親疎房份伯叔兄弟侄等無干亦未曾重張典當他人財物以及來歷不明各等情如有此情係錦發出頭抵當不涉堂兄之事兩相允愿各無翻悔今欲有憑立賣斷契事紙付執永遠為憑內併綴林春源典斷契司單下半屯相連標以知契母林氏光緒拾叁年冬月拾捌日立賣斷契王錦發胞弟森發在見堂兄俊發永發中友林細弟代筆李逢銓林春源
A9: 31735064607488_001 | B9: 31735064607488 | C9: 1 | D9: 1890 | E9: 1890 | F9: =IF(D9="","?",IF(D9<1796,"pre-1796",IF(D9<1912,"1796-1911",IF(D9<1949,"1912-1948","1949+")))) -> 1796-1911 | G9: =IF(D9="","?",IF(D9<1912,"Qing",IF(D9<1949,"Republic","PRC"))) -> Qing | H9: 1890 | I9: 閩侯（閩縣・侯官・林森） | J9: 福建省閩邑縣 | K9: Government | M9: 吳開成 | N9: 陳氏 | O9: Box 2, Folder 71 | P9: Private deed + state certificate | Q9: 立賣斷契 | R9: 同治玖年 | S9: 吳開成 | U9: 價銀陸拾捌兩正 | Y9: 厝屋 | Z9: 其屋式瑞數陸至俱; 李懷鏡 | AA9: 林枝三 | AB9: 親友陳清霖 | AC9: 嫂 洪氏 | AI9: 1 | AJ9: 0 | AK9: 1 | AL9: 0 | AM9: 1 | AN9: 1 | AO9: 1 | AP9: 0 | AQ9: 1 | AR9: 1 | AS9: 1 | AT9: 1 | AU9: 0 | AV9: 1 | AW9: 0 | AX9: 0 | AY9: 0 | AZ9: 0 | BA9: 0 | BB9: 0 | BC9: 551 | BD9: 0 | BE9: 0 | BF9: 0 | BG9: https://digital.library.pitt.edu/islandora/object/pitt:31735064607488 | BH9: 立賣斷契吳開成全姓瑞枝長庚原承祖遺下有厝屋肆在式欄相手座生產閩邑橫街舖地方前叁在門樓後引道至橫墻牆內左邊肆在屋後又有土庫肆在壹欄右邊肆在後又有拔水壹欄於道光貳拾叁年肆柒等年間經兄開揚在日憑中立典契先後曲在陳前魏各姓處為業緣年限已滿今因宗房別置全姪枝等向陳鄭魏邀往現繳典主劉李鄭各姓贖回隨托中友其屋式瑞數陸至俱載在贖回契內明白憑中統賣斷契陳處永遠為業三言議賣斷出屋價銀陸拾捌兩正庫大銀四其銀即日經成等隨契收足其厝屋即聽陳家永為子孫世業掌管收租或自己居住悉從其便成與枝等原價收足時價過浮自賣之後價足心願永斷萬無嗣後不得言贖言奉言盡之理以及別生枝等此屋緣因年久損壞倘陳家所毀改式起蓋聽從其便亦不敢啓齒索取花紅等情如有此情係成與枝等事但此厝屋係承祖遺下物業與親疎房份伯叔兄弟姪無亦未曾重張典當他人財物以及來歷不明各等情如有此情係成與枝等出頭承當不涉陳家之事兩相允願各無反悔今欲有過立賣斷契壹紙併繳陳家贖回契壹紙目壹紙鄭家贖回契壹紙魏家贖回契壹紙向陳家借字壹紙陳世旺繳典契壹紙鄭茂城繳典契壹紙魏振發繳典契壹紙劉嘉茂繳典契壹紙吳標標典契壹紙上年原曲斷契併司單執照老契壹拾肆紙共成貳拾伍紙統付永遠為憑知契嫂洪氏陳氏同治玖年十二月吉日賣斷契吳開成全姓瑞枝長庚全姪瑞枝長庚左見親友陳清霖中友李懷鏡代筆林枝三該契已協之永遠
A10: 31735064607496_001 | B10: 31735064607496 | C10: 1 | D10: 1900 | E10: 1900 | F10: =IF(D10="","?",IF(D10<1796,"pre-1796",IF(D10<1912,"1796-1911",IF(D10<1949,"1912-1948","1949+")))) -> 1796-1911 | G10: =IF(D10="","?",IF(D10<1912,"Qing",IF(D10<1949,"Republic","PRC"))) -> Qing | H10: 1900 | I10: 閩侯（閩縣・侯官・林森） | J10: 福建省閩邑縣 | K10: Government | M10: 鄒允春 | N10: 和意軒老人會 | O10: Box 2, Folder 82 | P10: Private deed | Q10: 立賣斷契 | R10: 光緒貳拾陸年 | S10: 鄒允春 | T10: 和意軒老人會 | U10: 價庫平銀肆拾肆兩正 | V10: 庫平 | Y10: 厝屋; 地基 | Z10: 王伊細 | AA10: 李松軒謹 | AB10: 表弟黃公弼 | AI10: 1 | AJ10: 0 | AK10: 1 | AL10: 1 | AM10: 1 | AN10: 1 | AO10: 1 | AP10: 0 | AQ10: 1 | AR10: 1 | AS10: 1 | AT10: 0 | AU10: 0 | AV10: 1 | AW10: 0 | AX10: 0 | AY10: 0 | AZ10: 0 | BA10: 0 | BB10: 0 | BC10: 336 | BD10: 1 | BE10: 0 | BF10: 0 | BG10: https://digital.library.pitt.edu/islandora/object/pitt:31735064607496 | BH10: 立賣斷契鄒允春承父手置原有厝屋叁柱式欄排串座共成式堵上有標椽磚瓦上至天至天下至地基地礫石地地內有門窓戶榻地坪板榻一切俱全橫濶式丈式尺參直深式丈肆尺參左至鄭家屋右至鄭家簷坪後至蘓家墻六至俱俱明白厝角水井通用座產閩邑嘉崇里文山舖秋龍社地方今因要托中賣斷與和意軒老人會處永遠為業本日三面言議賣斷得厝價庫平銀肆拾肆兩正即日隨契收足其屋所憑買主或自己居住或租他人悉從其便春自賣之後價足心願永斷葛藤但此屋係父自己手置與親疎伯叔兄弟侄無干並未曾重張典當他人財物之理以及來歷不明各等情如有此情係春出頭承當與買主無涉之事不得異說各無反悔今欲有憑立賣斷契事紙並張銓銓原契事紙司單事紙共成叁紙付執為憑內標註至用式字為憑在見表弟黃公弼光緒貳拾陸年閏捌月吉日立賣斷契鄒允春中人王伊細代筆李松軒謹卷八
A11: 31735064607504_001 | B11: 31735064607504 | C11: 1 | D11: 1918 | E11: 1918 | F11: =IF(D11="","?",IF(D11<1796,"pre-1796",IF(D11<1912,"1796-1911",IF(D11<1949,"1912-1948","1949+")))) -> 1912-1948 | G11: =IF(D11="","?",IF(D11<1912,"Qing",IF(D11<1949,"Republic","PRC"))) -> Republic | H11: 1918 | I11: 閩侯（閩縣・侯官・林森） | J11: 福建省閩侯縣 | K11: Government | M11: 陳燦祥 | N11: 吳 | O11: Box 2, Folder 108 | P11: Private deed + state certificate | Q11: 立契 | R11: 民國六年; 中華民國七年 | U11: 價柒百元 | V11: 大洋 | W11: 橫街舖茶葉衙面積壹庄一不動產之買 | Z11: 吳維清 | AE11: 典 契 | 例 則 摘 要 | AI11: 0 | AJ11: 0 | AK11: 0 | AL11: 0 | AM11: 0 | AN11: 0 | AO11: 0 | AP11: 0 | AQ11: 0 | AR11: 0 | AS11: 1 | AT11: 1 | AU11: 0 | AV11: 0 | AW11: 0 | AX11: 0 | AY11: 0 | AZ11: 0 | BA11: 1 | BB11: 1 | BC11: 605 | BD11: 0 | BE11: 0 | BF11: 0 | BG11: https://digital.library.pitt.edu/islandora/object/pitt:31735064607504 | BH11: 典契例則摘要承典人姓名吳不動產種類牆屋典價柒百元應納稅額貳拾壹元原契幾張立契年月日民國六年十二月四至北至西至南至東至坐落橫街舖茶葉衙面積壹庄一不動產之買主或承典人須於契紙成立後六個月以內赴該管徵收官署投稅一訂立不動產買契或典契時須由賣主或出典人赴該管徵收官署填具申請書請領契紙繳納契紙費大洋五角前項之契紙費五角由賣主與買主或出典人與承典人分擔一不動產之賣主或出典人請領契紙後已逾兩月其契約尚未成立者原領契紙失其効力但因有障礙致契約不能成立時得於限內赴徵收官署申明事由酌予寬限一原領契紙因遺失及其他事由須補領或更換時仍依第四條第一項之規定繳納契紙費一不動產之買主或承典人逾契約成立後六個月之期限不依本條例繳納契稅者除約定稅之稅額外並處以應納稅額之十倍罰金一繳納契稅時匿稅契價者除另換契紙改正契約繳納稅額外並處以左列之罰金一匿報契價十分之二以上未滿十分之三者短納稅額之二倍一匿報契價十分之三以上未滿十分之四者短納稅額之四倍一匿報契價十分之四以上未滿十分之五者短納稅額之八倍一匿報契價十分之五以上者短納稅額之十六倍或由徵稅官署依所報契價收買之一契約成立後六個月之納稅期間限於遵領官契紙者適用之其私紙所書之契約若事後不換寫契紙以逾限論一賣主或出典人以私紙訂立契約者得由徵稅官署處以五元以上五十元以下之罰金一逾限未稅之契訴訟時無憑證之效力中華民國七年四月廿六日出典人陳燦祥中人吳維清繕契核對陶筱泉縣給留字第虎完兌限合壹元
A12: 31735064607512_001 | B12: 31735064607512 | C12: 1 | D12: 1924 | E12: 1924 | F12: =IF(D12="","?",IF(D12<1796,"pre-1796",IF(D12<1912,"1796-1911",IF(D12<1949,"1912-1948","1949+")))) -> 1912-1948 | G12: =IF(D12="","?",IF(D12<1912,"Qing",IF(D12<1949,"Republic","PRC"))) -> Republic | H12: 1924 | I12: 閩侯（閩縣・侯官・林森） | J12: 福建省閩侯縣 | K12: Government | M12: 王三妹 | N12: 陳軍漢 | O12: Box 3, Folder 119 | P12: Private deed | Q12: 立典屋契 | S12: 約王三妹 | T12: 陳軍漢 | U12: 伏壹佰式拾伍元正; 銀台伏壹佰叁拾伍元 | V12: 台伏 | W12: 福州閩侯縣轄內文山鋪秋龍社下底埕 | Y12: 地基 | Z12: 林武欽 | AD12: 五 | AI12: 1 | AJ12: 0 | AK12: 0 | AL12: 1 | AM12: 1 | AN12: 1 | AO12: 1 | AP12: 1 | AQ12: 0 | AR12: 1 | AS12: 1 | AT12: 1 | AU12: 0 | AV12: 0 | AW12: 0 | AX12: 0 | AY12: 0 | AZ12: 0 | BA12: 0 | BB12: 0 | BC12: 356 | BD12: 0 | BE12: 0 | BF12: 0 | BG12: https://digital.library.pitt.edu/islandora/object/pitt:31735064607512 | BH12: 立典屋契約王三妹承繼父遺下有民屋一所坐產福州閩侯縣轄內文山鋪秋龍社下底埕地方坐北向南其屋式柱一欄前至天井後至牆左至廊墘右至王家上至椽瓦天下至地基地左邊房屋一堵右邊廊墘一堵共成參堵門牌戶嫡及椽極地秤破舊畧全今因要需於中將該屋典與陳軍漢處為業三面議定典價銀台伏壹佰式拾伍元正又貼修理費壹拾元合共貳大壹佰叁拾伍元正其銀即日經中收足其屋即聽陳處掌管或已居住或租他人均從其便約定五年為限期滿之日聽妹籌備原典銀台伏壹佰叁拾伍元取贖不得半途言贖及別生枝節但此屋係妹繼父遺產與親疏所伯叔兄弟姪等無關亦未曾重張典當他人財物如有來應不明係妹出頭承當不涉與之事若遇天災時變兩家均分各半雙方允諾各無反悔今設有憑蓋屋契約一紙並繳王齊發契一紙共應式紙統付為據此照標明郭宗付老原契遺失中人林武欽王斌斌知契生父王繼保立典屋契約卷之二文山鋪秋龍巷
A13: 31735064607512_002 | B13: 31735064607512 | C13: 2 | D13: 1924 | E13: 1924 | F13: =IF(D13="","?",IF(D13<1796,"pre-1796",IF(D13<1912,"1796-1911",IF(D13<1949,"1912-1948","1949+")))) -> 1912-1948 | G13: =IF(D13="","?",IF(D13<1912,"Qing",IF(D13<1949,"Republic","PRC"))) -> Republic | H13: 1924 | I13: 閩侯（閩縣・侯官・林森） | J13: 福建省閩侯縣 | K13: Government | M13: 王三妹 | N13: 陳軍漢 | O13: Box 3, Folder 119 | P13: Official form | Q13: 立契 | R13: 民國十三年 | U13: 價壹百貳拾伍元 | Y13: 厝屋 | AE13: 典 | AI13: 0 | AJ13: 0 | AK13: 0 | AL13: 0 | AM13: 0 | AN13: 0 | AO13: 0 | AP13: 0 | AQ13: 0 | AR13: 0 | AS13: 0 | AT13: 1 | AU13: 0 | AV13: 0 | AW13: 0 | AX13: 0 | AY13: 0 | AZ13: 0 | BA13: 0 | BB13: 1 | BC13: 171 | BD13: 0 | BE13: 0 | BF13: 0 | BG13: https://digital.library.pitt.edu/islandora/object/pitt:31735064607512 | BH13: 第典李契銀每張收善附捐壹元相第張卷承典人姓名陳軍漢不動產種類厝屋典價壹百貳拾伍元應納稅額叁元柒角伍占原契幾張立契年月日民國十三年二月到坐面落文山鋪秋龍巷積貳拾壹元四至東至南至西至北至清查一不動產之買主或承典人須於契紙成立後六個月以內赴該管徵收官署投稅二出典人赴該管徵收官署填具申請書請領契紙三立者原領契紙失其效力但寬限四繳納契紙費五首余酌定稅
A14: 31735064607520_001 | B14: 31735064607520 | C14: 1 | D14: 1876 | E14: 1876 | F14: =IF(D14="","?",IF(D14<1796,"pre-1796",IF(D14<1912,"1796-1911",IF(D14<1949,"1912-1948","1949+")))) -> 1796-1911 | G14: =IF(D14="","?",IF(D14<1912,"Qing",IF(D14<1949,"Republic","PRC"))) -> Qing | H14: 1876 | I14: 永安 | J14: 福建省永安縣 | K14: Government | M14: 祿中 | O14: Box 2, Folder 55 | P14: Private deed | Q14: 立杜賣田皮骨契 | R14: 光緒二年 | S14: 祿中客 | U14: 價銀壹拾柒員正 | Y14: 田皮 | AA14: 海中客 | AB14: 見代筆人海中客 | AI14: 1 | AJ14: 0 | AK14: 1 | AL14: 1 | AM14: 1 | AN14: 0 | AO14: 0 | AP14: 0 | AQ14: 1 | AR14: 0 | AS14: 1 | AT14: 0 | AU14: 0 | AV14: 0 | AW14: 0 | AX14: 0 | AY14: 0 | AZ14: 0 | BA14: 0 | BB14: 0 | BC14: 246 | BD14: 1 | BE14: 0 | BF14: 0 | BG14: https://digital.library.pitt.edu/islandora/object/pitt:31735064607520 | BH14: 立杜賣田皮骨契字人祿中今因少銀使用即將父分閩下禾田土名下屋仔虎形地堂下塘仔禾田一坵欲行出賣前來向到本家吉昌兄出首承買即日憑中三面時值盡骨併帶飯糧花押酒席一應在內共成六兌價銀壹拾柒員正其係隨字交付足額載今邑民未陸合其田自賣之後任憑賣主過手會業耕作其糧米任憑過割入冊有賣人叔侄兄弟不得添事等情此係正行交易不是負債準折之故價盡未足永無後贖恐口無憑立杜賣田皮骨契字一紙付與買主收執永遠為據即日收到字內畫骨田價銀壹拾柒員正俱收足記在場見代筆人海中客在堂母氏蘇光緒二年丙子歲十月廿七日立杜賣畫田字人祿中客
A15: 31735064607538_001 | B15: 31735064607538 | C15: 1 | D15: 1761 | E15: 1762 | F15: =IF(D15="","?",IF(D15<1796,"pre-1796",IF(D15<1912,"1796-1911",IF(D15<1949,"1912-1948","1949+")))) -> pre-1796 | G15: =IF(D15="","?",IF(D15<1912,"Qing",IF(D15<1949,"Republic","PRC"))) -> Qing | H15: 1761/1762 | I15: 永定 | J15: 福建省永定縣 | K15: Government | M15: 許瓊栢 | N15: 吳省忠 | O15: Box 1, Folder 5 | P15: Other / fragment | Q15: 立賣買山埔土審契 | R15: 乾隆貳拾六年 | S15: 許瓊相 | U15: 銀九四星色叁拾兩正; 價銀叁拾兩正 | W15: 大溪邊礫下崗上原有土審貳穴上至許 | Y15: 山埔; 墳 | AI15: 0 | AJ15: 0 | AK15: 1 | AL15: 0 | AM15: 1 | AN15: 0 | AO15: 0 | AP15: 0 | AQ15: 1 | AR15: 1 | AS15: 1 | AT15: 0 | AU15: 0 | AV15: 0 | AW15: 0 | AX15: 0 | AY15: 0 | AZ15: 0 | BA15: 0 | BB15: 0 | BC15: 335 | BD15: 3 | BE15: 0 | BF15: 0 | BG15: https://digital.library.pitt.edu/islandora/object/pitt:31735064607538 | BH15: 立賣買山埔土審契人許瓊相學明利錫今有祖父遺下山埔壹所坐落大溪邊礫下崗上原有土審貳穴上至許家墳下為界下至圳面為界左右並無土審相連其山埔內上下左右并土審貳穴欲行出賣前來托中送與吳省忠叔姪等出首承買當日憑中三向言斷時值山埔土審價銀九四星色叁拾兩正其銀即日隨契交訖不欠分文自的筆之日其大溪邊礫下崗上埔壹所共土審貳穴從吳省忠叔姪等前去堆砌土築板安置遷上遷下遷左遷右有許瓊相兄弟叔姪貳房等不得異言阻當等情其山埔土審與房族叔伯兄弟人等並無寸土干涉亦不會重複典當他人財物委係正行交易不是負債推折之故今欲有憑立賣買山埔土審契永遠為照即日得收山埔土審契內價銀叁拾兩正足訖說命人官盛清務房戶許芳相等乾隆貳拾六年辛巳歲拾月初二日立賣買山埔土審契人許瓊相北相瓊相或相字全姪信上利盛與平明聯上兩北上
A16: 31735064607538_002 | B16: 31735064607538 | C16: 2 | D16: 1761 | E16: 1762 | F16: =IF(D16="","?",IF(D16<1796,"pre-1796",IF(D16<1912,"1796-1911",IF(D16<1949,"1912-1948","1949+")))) -> pre-1796 | G16: =IF(D16="","?",IF(D16<1912,"Qing",IF(D16<1949,"Republic","PRC"))) -> Qing | H16: 1761/1762 | I16: 永定 | J16: 福建省永定縣 | K16: Government | M16: 許瓊栢 | N16: 吳省忠 | O16: Box 1, Folder 5 | P16: Official form | R16: 乾隆十五年; 乾隆貳拾柒年 | AE16: 欽 | AF16: 福建等處承宣布政使司 | AI16: 0 | AJ16: 0 | AK16: 0 | AL16: 0 | AM16: 0 | AN16: 0 | AO16: 0 | AP16: 0 | AQ16: 0 | AR16: 0 | AS16: 0 | AT16: 0 | AU16: 0 | AV16: 0 | AW16: 1 | AX16: 1 | AY16: 0 | AZ16: 0 | BA16: 0 | BB16: 0 | BC16: 742 | BD16: 3 | BE16: 0 | BF16: 0 | BG16: https://digital.library.pitt.edu/islandora/object/pitt:31735064607538 | BH16: 欽永字一千四百十三號福建等處承宣布政使司為查據奏事乾隆十五年正月二十四日奉准戶部咨開司案呈所有奉部議覆河南布政使高爾隆奏買賣田產將契尾精連用印存貯申送府州藩司查驗等因一摺于本年十一月二十二日奉本日來查依議欽此相應抄錄原奏并頒發格式行文福憲照欽遵辦理可也計前單一紙格式一張內開該府等查得該布政使高爾隆奏稱部議多頒契尾以後巧取病民緣象勢難免例不與照根契中上已查驗不自備其與給民契尾則按數登與而于存官照根或將價銀刪改請照後州縣于票之納照時符即將應給集戶之契尾并州縣備案之照根等項從未議將花戶收執票與申繳上司收執等項與照根并送查發是難項更難于正賦稅與照根且當緣為奸情勒索查以致難戶經年累月求其難望其掛圖匿白契而不解不目誤費集照根而直隸州照州縣例例送照用之處均毋庸議至請嗣後布政司頒發給民契尾格式編列號數前中印鈐司印以備投稅時將契價稅銀數目太字與票和政司查核此係一行筆跡平分為二大小數目妥離子虞而契價無參差之契于民無累于稅無虧侵舒杜爭訟可息矣如蒙照其契尾一項經二衙門即多一衙門之停關由吏胥即多一吏胥之索索甚亦以憑票請州縣經收稅銀將契尾粘連存貯一單中送府州官照根而直隸吏以大細小奸民爭執訂訟定緣法久弊生不可不事為變通自應將照常細畫業戶等姓名買賣田房數目價銀稅銀若干後半幅下空白處印之處令業戶看明當面騎字截開將幅將業戶及執後幅司印冊景換其稅前州縣布政司銷送各契尾應將停止以省繁文庶契尾無停爭訟可息矣如蒙命下之日部頒發格式通行無有督撫一體欽遵謹此等因咨院行司奉此納稅銀玖錢五納稅銀玖錢五納稅銀玖錢五納稅銀玖錢五納稅銀玖錢五納稅銀玖錢五納稅銀玖錢五納稅銀玖錢五納稅銀玖錢五納稅銀玖錢五納稅銀玖錢五納稅銀玖錢五納稅銀玖錢五納稅銀玖錢五納稅銀玖錢五乾隆貳拾柒年捌月永字壹千肆百八拾號白給永茂縣葉口吳有德佳此
A17: 31735064607546_001 | B17: 31735064607546 | C17: 1 | D17: 1760 | E17: 1767 | F17: =IF(D17="","?",IF(D17<1796,"pre-1796",IF(D17<1912,"1796-1911",IF(D17<1949,"1912-1948","1949+")))) -> pre-1796 | G17: =IF(D17="","?",IF(D17<1912,"Qing",IF(D17<1949,"Republic","PRC"))) -> Qing | H17: 1760/1767 | I17: 閩清 | J17: 福建省閩清縣 | K17: Government | L17: 黃毓扆 | O17: Box 1, Folder 4 | P17: Private deed | Q17: 立典契 | R17: 乾隆貳拾伍年 | S17: 黃毓辰 | T17: 葉 | U17: 價銀陸拾叁兩正 | W17: 檢壹都 | Y17: 民田 | Z17: 薛宜章 | AB17: 劉有臺 | AI17: 1 | AJ17: 0 | AK17: 1 | AL17: 0 | AM17: 1 | AN17: 1 | AO17: 0 | AP17: 1 | AQ17: 0 | AR17: 0 | AS17: 1 | AT17: 0 | AU17: 0 | AV17: 0 | AW17: 0 | AX17: 0 | AY17: 0 | AZ17: 0 | BA17: 0 | BB17: 0 | BC17: 341 | BD17: 1 | BE17: 0 | BF17: 0 | BG17: https://digital.library.pitt.edu/islandora/object/pitt:31735064607546 | BH17: 立典契黃毓辰承祖有民田數號坐產檢壹都地方土名和尚壠長壠平水潭台尾上下大坵尾園前後埭埭利吳晉洋上中假桑園二小坵等處受種伍斗陸升伍合年載租米伍碩陸伍升伍合斗陸升伍合立在昇平文親孝仁戶下今因乏用托中典與葉處為葉三向言議得訖田價銀陸拾叁兩正紋廣其銀即日收足其田轉銀主前去會佃收租自是身苗糧聽從葉過割入戶西約伍年限滿之日借銀以契面銀兩定期取贖葉不得自留此田係自己物業與別房佃叔兄等無干上上本自重張典當他人財物如有未磨不明係辰出欵抵當不得借銀主事今欲有洗立典契為憑此為計開一個陳朝彩出名和尚壠載租米壹石捌斗官姓李長一個許維實出名長壠平水潭台尾抽出租米壹石捌斗官一個林子為土名上下大坵尾園前徐假埭利吳晉洋上中假桑園二小坵載租米貳石柒斗官乾隆貳拾伍年伍月立典契黃毓辰中人薛宜章左見劉有臺謝朝尊謹大壠
A18: 31735064607546_002 | B18: 31735064607546 | C18: 2 | D18: 1760 | E18: 1767 | F18: =IF(D18="","?",IF(D18<1796,"pre-1796",IF(D18<1912,"1796-1911",IF(D18<1949,"1912-1948","1949+")))) -> pre-1796 | G18: =IF(D18="","?",IF(D18<1912,"Qing",IF(D18<1949,"Republic","PRC"))) -> Qing | H18: 1760/1767 | I18: 閩清 | J18: 福建省閩清縣 | K18: Government | L18: 黃毓扆 | O18: Box 1, Folder 4 | P18: Private deed | Q18: 立湊字 | R18: 乾隆叁拾貳年 | S18: 黃毓辰原 | Y18: 民田; 苗米; 田面 | Z18: 列有炳燧 | AI18: 0 | AJ18: 0 | AK18: 1 | AL18: 0 | AM18: 1 | AN18: 0 | AO18: 0 | AP18: 0 | AQ18: 0 | AR18: 0 | AS18: 0 | AT18: 0 | AU18: 0 | AV18: 0 | AW18: 0 | AX18: 0 | AY18: 0 | AZ18: 0 | BA18: 0 | BB18: 0 | BC18: 127 | BD18: 0 | BE18: 0 | BF18: 0 | BG18: https://digital.library.pitt.edu/islandora/object/pitt:31735064607546 | BH18: 立湊字黃毓辰子前耳向有民田數號其理名銀西土名苗米俱載草契內明白若因立用托中向立葉表伯處湊出制鈔書拉子又石其鈔即日收其其田面約再限出仁耳備年之日以原湊專銀西取燒如未取燒契聽從以四收葉立湊字葉弟併原契其成或命助乃乾隆叁拾貳年伍月日立湊字黃毓辰原契中見列有炳燧
A19: 31735064607553_001 | B19: 31735064607553 | C19: 1 | D19: 1940 | E19: 1940 | F19: =IF(D19="","?",IF(D19<1796,"pre-1796",IF(D19<1912,"1796-1911",IF(D19<1949,"1912-1948","1949+")))) -> 1912-1948 | G19: =IF(D19="","?",IF(D19<1912,"Qing",IF(D19<1949,"Republic","PRC"))) -> Republic | H19: 1940 | K19: Personal | M19: 藍維乾 | 藍維坤 | N19: 吳淮棉 | O19: Box 3, Folder 162 | P19: Private deed | Q19: 立令賣契 | S19: 要藍維坤 | U19: 幣銀書佰壹拾員正 | V19: 國幣 | Z19: 抵當不涉銀主之事; 吳淮西 | AA19: 陳鳳英 | AB19: 龍叔世錄 | AI19: 0 | AJ19: 0 | AK19: 1 | AL19: 1 | AM19: 1 | AN19: 0 | AO19: 1 | AP19: 1 | AQ19: 1 | AR19: 1 | AS19: 1 | AT19: 0 | AU19: 0 | AV19: 1 | AW19: 0 | AX19: 0 | AY19: 0 | AZ19: 0 | BA19: 0 | BB19: 0 | BC19: 297 | BD19: 1 | BE19: 0 | BF19: 1 | BG19: https://digital.library.pitt.edu/islandora/object/pitt:31735064607553 | BH19: 立令賣契藍維坤原史手闕於下有山國書號坐地本山土名定下坑大小坑近載藤書千伍佰餘根東至淮球國為界西至立善園為界南至淮元田為界北至土墓為界於立以少令因要用托中引引吳淮棉處三面言說賣契以示國所國幣銀書佰壹拾員正其銀即日親手收足其山國即付銀主壹壹名佃他人耕作栽種地依此山國係坤原史手闕於下有立業為本房內諸人等於子並未重此典當他人財物中有不以唯坤原史手已出頭令中見抵當不涉銀主之事自賣契以後永為銀主久遠實業與坤原史手孫半點無干園內有吉穴聽從銀主擇吉這並不敢言說取贖說契契膠貼易生枝節之理此乃係足心願各勿反悔今致有憑立賣契契書序為據在見龍叔世錄中華民國庚辰年拾月吉日立賣契要藍維坤坤原史手中人吳淮西代筆陳鳳英
A20: 31735064607561_001 | B20: 31735064607561 | C20: 1 | D20: 1917 | E20: 1917 | F20: =IF(D20="","?",IF(D20<1796,"pre-1796",IF(D20<1912,"1796-1911",IF(D20<1949,"1912-1948","1949+")))) -> 1912-1948 | G20: =IF(D20="","?",IF(D20<1912,"Qing",IF(D20<1949,"Republic","PRC"))) -> Republic | H20: 1917 | K20: Personal | M20: 維衜 | O20: Box 2, Folder 105 | P20: Private deed | Q20: 立賣斷契 | S20: 贈侄孫維 | U20: 價番銀貳拾柒員正 | V20: 番銀 | W20: 本增墾頭 | AA20: 中陳端率 | AB20: 胞弟 | AI20: 1 | AJ20: 0 | AK20: 1 | AL20: 0 | AM20: 1 | AN20: 1 | AO20: 1 | AP20: 1 | AQ20: 1 | AR20: 1 | AS20: 1 | AT20: 0 | AU20: 0 | AV20: 0 | AW20: 0 | AX20: 0 | AY20: 0 | AZ20: 0 | BA20: 0 | BB20: 0 | BC20: 295 | BD20: 0 | BE20: 0 | BF20: 0 | BG20: https://digital.library.pitt.edu/islandora/object/pitt:31735064607561 | BH20: 立賣斷契贈侄孫維衡原祖上遺下有茄種園雲驛坐址本增墾頭土名竹籃下雲坵載籐書千伍百餘根西至路為界東至青元茄種園為界南至良良園為界北至現為界肆至明白今因要用托中引到贈叔祖公勳懷諸面議賣斷得出價番銀貳拾柒員正每員陸份捌分重其銀即日親手收足其茄種園聽從贈叔祖管業召佃耕作栽種地瓜此茄種園係原祖上遺下實業由本房內諸人無干並未重張典當他人財中有不明係自行抵當不涉贈叔祖之事自賣斷以後永為贈叔祖久遠實業由半點絲毫無干如有因內吉穴聽從贈叔祖擇吉起蓋並不敢言說取贖贖貼另生枝節之理此乃價足心愿各無反悔今故有憑立賣斷契書紙為據在見胞弟維壽維炎從命男長善中華民國丁巳陸年拾月廿日立賣斷契贈侄孫維衡代筆中陳端率禮大和
A21: 31735064607579_001 | B21: 31735064607579 | C21: 1 | D21: 1805 | E21: 1816 | F21: =IF(D21="","?",IF(D21<1796,"pre-1796",IF(D21<1912,"1796-1911",IF(D21<1949,"1912-1948","1949+")))) -> 1796-1911 | G21: =IF(D21="","?",IF(D21<1912,"Qing",IF(D21<1949,"Republic","PRC"))) -> Qing | H21: 1805/1816 | I21: 閩侯（閩縣・侯官・林森） | J21: 福建省閩縣 | K21: Government | L21: 吳秉鑒 | M21: 吳秉鑒 | N21: 謝先經 | O21: Box 1, Folder 16 | P21: Private deed | Q21: 立轉典契 | R21: 嘉慶十年 | S21: 吳秉鑄 | Z21: 鄭長梅 | AC21: 王氏 | AI21: 0 | AJ21: 0 | AK21: 0 | AL21: 0 | AM21: 0 | AN21: 0 | AO21: 0 | AP21: 0 | AQ21: 0 | AR21: 0 | AS21: 0 | AT21: 0 | AU21: 0 | AV21: 0 | AW21: 0 | AX21: 0 | AY21: 0 | AZ21: 0 | BA21: 0 | BB21: 0 | BC21: 46 | BD21: 2 | BE21: 0 | BF21: 0 | BG21: https://digital.library.pitt.edu/islandora/object/pitt:31735064607579 | BH21: 嘉慶十年六月吉大見卷知契王氏日立轉典契吳秉鑄胞弟秉鈞中見鄭長梅金存國鄭捷登秉筆林學經鄭保涂正
A22: 31735064607579_002 | B22: 31735064607579 | C22: 2 | D22: 1805 | E22: 1816 | F22: =IF(D22="","?",IF(D22<1796,"pre-1796",IF(D22<1912,"1796-1911",IF(D22<1949,"1912-1948","1949+")))) -> 1796-1911 | G22: =IF(D22="","?",IF(D22<1912,"Qing",IF(D22<1949,"Republic","PRC"))) -> Qing | H22: 1805/1816 | I22: 閩侯（閩縣・侯官・林森） | J22: 福建省閩縣 | K22: Government | L22: 吳秉鑒 | M22: 吳秉鑒 | N22: 謝先經 | O22: Box 1, Folder 16 | P22: Other / fragment | AI22: 0 | AJ22: 0 | AK22: 0 | AL22: 0 | AM22: 0 | AN22: 0 | AO22: 0 | AP22: 0 | AQ22: 0 | AR22: 0 | AS22: 0 | AT22: 0 | AU22: 0 | AV22: 0 | AW22: 0 | AX22: 0 | AY22: 0 | AZ22: 0 | BA22: 0 | BB22: 0 | BC22: 1 | BD22: 1 | BE22: 0 | BF22: 0 | BG22: https://digital.library.pitt.edu/islandora/object/pitt:31735064607579 | BH22: 契
A23: 31735064607587_001 | B23: 31735064607587 | C23: 1 | D23: 1871 | E23: 1913 | F23: =IF(D23="","?",IF(D23<1796,"pre-1796",IF(D23<1912,"1796-1911",IF(D23<1949,"1912-1948","1949+")))) -> 1796-1911 | G23: =IF(D23="","?",IF(D23<1912,"Qing",IF(D23<1949,"Republic","PRC"))) -> Qing | H23: 1871/1913 | I23: 閩侯（閩縣・侯官・林森） | J23: 福建省閩侯縣 | K23: Government | M23: 方元慈 | N23: 方潮濤 | O23: Box 1, Folder 50 | P23: Private deed + state certificate | Q23: 立賣斷根面全田契 | R23: 中華民國 年; 中華民國 11 年; 同治拾年 | S23: 第方元慈 | U23: 價一千五百元; 價銀壹百壹拾元正 | W23: 二號不動產面積二畝四至東至南至西 | Y23: 根面全田 | Z23: 族叔 | AA23: 魏佳 | AB23: 母親 | AC23: 嫂 趙氏 | AE23: 單 契 斷 賣 | 福建省政府財政廳頒發閩侯縣已稅契驗契證 | AF23: 福建省政府財政廳 | AG23: 業戶; 住址 | AI23: 1 | AJ23: 0 | AK23: 1 | AL23: 0 | AM23: 1 | AN23: 1 | AO23: 0 | AP23: 0 | AQ23: 1 | AR23: 1 | AS23: 1 | AT23: 0 | AU23: 0 | AV23: 1 | AW23: 0 | AX23: 0 | AY23: 0 | AZ23: 1 | BA23: 0 | BB23: 0 | BC23: 676 | BD23: 2 | BE23: 0 | BF23: 1 | BG23: https://digital.library.pitt.edu/islandora/object/pitt:31735064607587 | BH23: 單契斷賣中華民國年拾壹月卷拾日拾證方濃官原價銀紙價實銀兩共已如數收訖西至北至坐向橫丈尺直丈尺中東水湯北督催處右給業戶潮青准此福建省政府財政廳頒發閩侯縣已稅契驗契證茲為整理契稅，體卹人民，保障產權起見，特定驗契辦法，凡屬田園屋地各類不動產，已稅未稅契據，均應一律投驗，填給驗契證，已稅之紅契，不收驗費，未稅之白契，無論典賣及產價多寡，每張祇收驗契費銀壹元，短此驗契，粘有驗契證者，方為有效。非經買賣轉移，不再徵稅。業主姓名潮青業主住址閩侯不動產種類田不動產坐落二號不動產面積二畝四至東至南至西至北至畝分契分契等則賦額地丁糧米產價一百一十五千六業主姓名潮青中人姓名潮青契價一千五百元其他此契係1917年11月11日人此處蓋財政廳驗契證開份此處蓋財政廳驗契證開份此處蓋財政廳驗契證開份中華民國11年11月11日第41740號此種已稅契驗契證收驗費閩侯縣三此張填給業主粘連原契合業同治拾年拾壹月吉日立賣斷根面全田契第方元慈鑒代筆魏佳謹啟在見母親許氏嫂趙氏中人族叔濃官立賣斷根面全田契第方元慈原承父閩書份下有根面全田委原糧銀三十九部壹甲方道戶下又掛三十八部四圍八甲方福昌戶下又掛三十八部壹圍六甲方永平戶下銀照票例科繳應掌無異今因別置托中將此田統斷與兄潮青處永遠為業云云言議本日賣斷出田價銀壹百壹拾元正其錢即日全中收足其田即聽兄掌管新作定納糧色弟自賣斷之後價足心慰永斷萬無向後永不得用生枝即以此田係弟承父閩書份下為業與本別居親族人等無干亦未曾重張回當他人財物如有來應不係弟祇當與兄無干兩相允應各無反悔今欲有憑立賣斷根面全田契壹紙付現為照其憑契因洪水陸等朽腐無可徵付
A24: 31735064607587_002 | B24: 31735064607587 | C24: 2 | D24: 1871 | E24: 1913 | F24: =IF(D24="","?",IF(D24<1796,"pre-1796",IF(D24<1912,"1796-1911",IF(D24<1949,"1912-1948","1949+")))) -> 1796-1911 | G24: =IF(D24="","?",IF(D24<1912,"Qing",IF(D24<1949,"Republic","PRC"))) -> Qing | H24: 1871/1913 | I24: 閩侯（閩縣・侯官・林森） | J24: 福建省閩侯縣 | K24: Government | M24: 方元慈 | N24: 方潮濤 | O24: Box 1, Folder 50 | P24: Private deed | Q24: 立賣斷根面全田契 | R24: 同治拾年 | S24: 弟方元慈 | U24: 價錢壹百壹拾伍千文正 | W24: 侯邑三十九都 | X24: 圳仔墘 | Y24: 根面全田 | Z24: 族叔濃官 | AA24: 孫佳亨 | AB24: 母親許氏 | AC24: 母親許氏; 嫂趙氏 | AI24: 1 | AJ24: 0 | AK24: 1 | AL24: 1 | AM24: 1 | AN24: 1 | AO24: 0 | AP24: 0 | AQ24: 1 | AR24: 1 | AS24: 1 | AT24: 0 | AU24: 0 | AV24: 1 | AW24: 0 | AX24: 0 | AY24: 0 | AZ24: 0 | BA24: 0 | BB24: 0 | BC24: 346 | BD24: 3 | BE24: 0 | BF24: 0 | BG24: https://digital.library.pitt.edu/islandora/object/pitt:31735064607587 | BH24: 此立賣斷根面全田契弟方元慈原承父閭書份下有根面全田坐落侯邑三十九都地方土名圳仔墘田大小丞坊官犬式畝式分零糧掛三十九都壹甲方道戶下又掛三十八都四圖八甲方福昌戶下又掛三十八都壹圖六甲方永平戶下銀米照縣例科派應掌無異今因別置托中將此田統斷與兄潮壽處永遠為業三面言議本月賣斷出田價錢壹百壹拾伍千文正其錢即日全中收足其田即聽兄掌管耕作完納糧色弟自賣斷之後價足心慈永斷葛藤自後永不得別生枝節但此田係弟承父閭書份下物業與本別房親疎人等無干亦未曾重張曲當他人財物如有來應不係弟抵當與兄無干兩相允慈各無反悔今欲有憑立賣斷根面全田契壹紙付執為照其愿契因洪水陵厝朽腐無可徵付中人族叔濃官在見母親許氏嫂趙氏Handwrittensignatureormark.同治拾年拾壹月吉日立賣斷根面全田契弟方元慈代筆孫佳亨承林
A25: 31735064607587_003 | B25: 31735064607587 | C25: 3 | D25: 1871 | E25: 1913 | F25: =IF(D25="","?",IF(D25<1796,"pre-1796",IF(D25<1912,"1796-1911",IF(D25<1949,"1912-1948","1949+")))) -> 1796-1911 | G25: =IF(D25="","?",IF(D25<1912,"Qing",IF(D25<1949,"Republic","PRC"))) -> Qing | H25: 1871/1913 | I25: 閩侯（閩縣・侯官・林森） | J25: 福建省閩侯縣 | K25: Government | M25: 方元慈 | N25: 方潮濤 | O25: Box 1, Folder 50 | P25: Official form | Q25: 立之不動產舊契 | R25: 同治拾年; 中華民國 貳年 | U25: 價銀兩申銀壹百壹拾伍元 | V25: 銀元 | W25: 閩侯縣三九都圳仔地 | AE25: 賣 斷 契 單 | 福建國稅廳籌備處 | AF25: 福建國稅廳籌備處 | AG25: 方潮清 | AH25: 驗字第萬二千四百六十八號 | AI25: 0 | AJ25: 0 | AK25: 0 | AL25: 0 | AM25: 0 | AN25: 0 | AO25: 0 | AP25: 0 | AQ25: 0 | AR25: 0 | AS25: 1 | AT25: 0 | AU25: 0 | AV25: 0 | AW25: 0 | AX25: 1 | AY25: 1 | AZ25: 1 | BA25: 1 | BB25: 1 | BC25: 352 | BD25: 0 | BE25: 0 | BF25: 0 | BG25: https://digital.library.pitt.edu/islandora/object/pitt:31735064607587 | BH25: 賣斷契單福建國稅廳籌備處給發契單十案奉財政部電劃一契紙章程內開本章程施行以前成立之不動產舊契無論已稅契未稅契均一律限期呈驗逾限不呈驗者於訴訟時不能作為憑據一併函知司法機關認真理以為匿驗者或等因奉此當經擬定分別徵收方法已稅之舊契每張收紙價壹元未稅之舊契每產價百元收紙價壹元其光復後新契已稅者不收紙價酌定正限三個月餘限兩個月逾期呈驗者分別加徵嚴罰經已電奉財政部核辦並通飭遵照在案今據閩侯縣業戶方潮清於清同治拾年拾二月日買受先慈田地貳畝分界坐落閩侯縣三九都圳仔地地方東至西至北至坐落坐向橫丈尺直丈尺中證方濃官原價銀兩申銀壹百壹拾伍元原契未稅遵章依限呈驗應納紙價壹元貳角半已如數收訖合填契單粘連原契印給收執管業須至契單者東水湯井銀元北督催處馬官右給業戶方潮清准此中華民國貳年拾壹月叁拾日給驗字第萬二千四百六十八號
A26: 31735064607587_004 | B26: 31735064607587 | C26: 4 | D26: 1871 | E26: 1913 | F26: =IF(D26="","?",IF(D26<1796,"pre-1796",IF(D26<1912,"1796-1911",IF(D26<1949,"1912-1948","1949+")))) -> 1796-1911 | G26: =IF(D26="","?",IF(D26<1912,"Qing",IF(D26<1949,"Republic","PRC"))) -> Qing | H26: 1871/1913 | I26: 閩侯（閩縣・侯官・林森） | J26: 福建省閩侯縣 | K26: Government | M26: 方元慈 | N26: 方潮濤 | O26: Box 1, Folder 50 | P26: Official form | R26: 中華民國 41 年 | W26: ...係...東...者...博 | AI26: 0 | AJ26: 0 | AK26: 0 | AL26: 0 | AM26: 0 | AN26: 0 | AO26: 0 | AP26: 0 | AQ26: 0 | AR26: 0 | AS26: 0 | AT26: 0 | AU26: 0 | AV26: 0 | AW26: 0 | AX26: 0 | AY26: 0 | AZ26: 0 | BA26: 0 | BB26: 0 | BC26: 144 | BD26: 4 | BE26: 1 | BF26: 0 | BG26: https://digital.library.pitt.edu/islandora/object/pitt:31735064607587 | BH26: 此處粘連原契騎縫加蓋驗契鈐記此處蓋財政廳驗契證關防此處蓋縣府印第區區長簽名蓋章中華民國41年6月11日第49740號第保保長或鄉長簽名蓋章此種已稅契驗契證收驗費閩侯縣三此張填給業主粘連原契管業日買...慈田...畝分...坐落...係...東...者...博...北...身...至...
A27: 31735064607595_001 | B27: 31735064607595 | C27: 1 | D27: 1932 | E27: 1932 | F27: =IF(D27="","?",IF(D27<1796,"pre-1796",IF(D27<1912,"1796-1911",IF(D27<1949,"1912-1948","1949+")))) -> 1912-1948 | G27: =IF(D27="","?",IF(D27<1912,"Qing",IF(D27<1949,"Republic","PRC"))) -> Republic | H27: 1932 | I27: 閩清 | J27: 福建省閩清縣 | K27: Government | M27: 劉振萬 | N27: 劉紀臣 | O27: Box 3, Folder 145 | P27: Private deed + state certificate | Q27: 立賣新契 | R27: 中華民國二十一年 | S27: 劉振萬劉 | U27: 價大洋律拾肆員正 | V27: 大洋 | Y27: 民田 | Z27: 叔培貴鑒 | AB27: 姪維興叩 | AI27: 0 | AJ27: 0 | AK27: 0 | AL27: 1 | AM27: 1 | AN27: 1 | AO27: 0 | AP27: 0 | AQ27: 1 | AR27: 1 | AS27: 1 | AT27: 0 | AU27: 0 | AV27: 0 | AW27: 0 | AX27: 0 | AY27: 0 | AZ27: 0 | BA27: 0 | BB27: 0 | BC27: 244 | BD27: 1 | BE27: 0 | BF27: 0 | BG27: https://digital.library.pitt.edu/islandora/object/pitt:31735064607595 | BH27: 立賣新契劉振萬自已手置有民田報面全壺號坐地本鄉地方去名東埔頭並舊園厝迹田式均受種棟外其私照縣例斜派立立劉汝俊不台因要用稅中將此田賣斷契劉紀臣處永遠為業三面言改即日約記田斷價大洋律拾肆員正其銀隨契交足其田下聽臣維佃永遠耕作業理納租差但此田係萬自已物業與別契于並若重張與賣他人財物以及來歷不同皆情若有些情萬出拆不清臣之事自賣斷之後李筆千秋各彬欣喜不得異言亦不得別生枝節之理沿口若遇言教有過立賣斷契壹紙永作為照中華民國二十一年十一月日立賣新契劉振萬劉左見姪維興叩中人叔培貴鑒秉筆中弟振財劉劉振萬
A28: 31735064607595_002 | B28: 31735064607595 | C28: 2 | D28: 1932 | E28: 1932 | F28: =IF(D28="","?",IF(D28<1796,"pre-1796",IF(D28<1912,"1796-1911",IF(D28<1949,"1912-1948","1949+")))) -> 1912-1948 | G28: =IF(D28="","?",IF(D28<1912,"Qing",IF(D28<1949,"Republic","PRC"))) -> Republic | H28: 1932 | I28: 閩清 | J28: 福建省閩清縣 | K28: Government | M28: 劉振萬 | N28: 劉紀臣 | O28: Box 3, Folder 145 | P28: Official form | V28: 國幣 | AE28: 契稅暫行條例摘 | 要： | 財政部福建省 縣(市)田賦管理處賣契本契 | AI28: 0 | AJ28: 0 | AK28: 0 | AL28: 0 | AM28: 0 | AN28: 0 | AO28: 0 | AP28: 0 | AQ28: 0 | AR28: 0 | AS28: 0 | AT28: 1 | AU28: 0 | AV28: 0 | AW28: 0 | AX28: 0 | AY28: 0 | AZ28: 0 | BA28: 1 | BB28: 0 | BC28: 297 | BD28: 0 | BE28: 0 | BF28: 0 | BG28: https://digital.library.pitt.edu/islandora/object/pitt:31735064607595 | BH28: 契稅暫行條例摘要：一、契稅稅率規定如左：一、賣契稅為其契價百分之十二、典契稅為其契價百分之六三、交換契稅為其契價百分之四四、贈與契稅為其契價百分之十二、契紙工本費每張納國幣二元三、完納契稅應于契約成立後三個月內為之逾限不納者應責令補納并科以應納契稅百分之十之罰鍰其後每再逾期二個月遞加百分之十至達納稅額之同數為止四、繳納契稅時如遇匿報或低估契價應令另換契紙按實改正補繳短納稅額並科以左例之罰鍰甲、匿報或低估契價未滿百分之二十者其短納稅額之半數乙、匿報或低估契價百分之二十以上未滿百分之五十者其短納稅額之同數丙、匿報或低估契價百分之五十以上者其短納稅額之二倍財政部福建省縣(市)田賦管理處賣契本契
A29: 31735064607603_001 | B29: 31735064607603 | C29: 1 | F29: =IF(D29="","?",IF(D29<1796,"pre-1796",IF(D29<1912,"1796-1911",IF(D29<1949,"1912-1948","1949+")))) -> ? | G29: =IF(D29="","?",IF(D29<1912,"Qing",IF(D29<1949,"Republic","PRC"))) -> ? | J29: 福建省 | K29: Government | O29: Box 4, Folder 211 | P29: Official form | R29: 中華民國 年 | AF29: 福建省人民政府 | AH29: 權狀禮字第三三號 | AI29: 0 | AJ29: 0 | AK29: 0 | AL29: 0 | AM29: 0 | AN29: 0 | AO29: 0 | AP29: 0 | AQ29: 0 | AR29: 0 | AS29: 0 | AT29: 0 | AU29: 0 | AV29: 0 | AW29: 0 | AX29: 0 | AY29: 0 | AZ29: 0 | BA29: 0 | BB29: 0 | BC29: 96 | BD29: 0 | BE29: 0 | BF29: 0 | BG29: https://digital.library.pitt.edu/islandora/object/pitt:31735064607603 | BH29: 省-III-20-366實測戶地圖租經國家福建省人民政府委員會福建省會第二區第二十四段第三四號宅地面積。畝口分八厘一毫。然所有權狀禮字第三三號[]中華民國年月日福建省政府民政廳發一比五尺百分之
A30: 31735064607611_001 | B30: 31735064607611 | C30: 1 | D30: 1925 | E30: 1925 | F30: =IF(D30="","?",IF(D30<1796,"pre-1796",IF(D30<1912,"1796-1911",IF(D30<1949,"1912-1948","1949+")))) -> 1912-1948 | G30: =IF(D30="","?",IF(D30<1912,"Qing",IF(D30<1949,"Republic","PRC"))) -> Republic | H30: 1925 | I30: 閩侯（閩縣・侯官・林森） | J30: 福建省閩侯縣 | K30: Government | M30: 張銓銓 | N30: 鄒道明 | O30: Box 3, Folder 123 | P30: Private deed | Q30: 立賣與契 | S30: 張銓銓 | T30: 鄒道明 | U30: 價銀肆拾兩正 | Y30: 厝屋; 地基 | AI30: 1 | AJ30: 0 | AK30: 1 | AL30: 1 | AM30: 1 | AN30: 1 | AO30: 0 | AP30: 0 | AQ30: 1 | AR30: 1 | AS30: 1 | AT30: 0 | AU30: 0 | AV30: 0 | AW30: 0 | AX30: 0 | AY30: 0 | AZ30: 0 | BA30: 0 | BB30: 0 | BC30: 317 | BD30: 0 | BE30: 0 | BF30: 0 | BG30: https://digital.library.pitt.edu/islandora/object/pitt:31735064607611 | BH30: 立賣與契張銓銓承嗣父遺下閩分份下原有厝屋三柱式棚排重座共成式堵上有樑椽磚瓦天天下有地基石地地內有門懸戶棚地棚板粒一切具全橫濶至我丈式尺深至重丈四尺東才至前家屋右至游家路前至鄭家簷坪後至蘇家墻坪六至其俱明白厝角水井通用甲座產閩邑嘉崇里文山鋪秋龍社地方其屋歷掌無異今因別用將此厝屋托中向賣與鄒道明處永遠為業三面言議即日得訖賣與王之重價銀肆拾兩正紋廣其銀即日收足其屋即聽買主掌管前去從便做作聽從買主之事與銓本點無干但此屋係銓承嗣父遺下閩分份下已業與房內親疎伯叔兄弟侄輩本點無干亦未曾重張典掛他人財物以及未歷不明各等情如有此情係銓承嗣父當與買主無涉之事賣與之後價足心愿不得別生製節求斷其永不得異言兩相心愿各無反悔今欵有憑立主斷契委低付此永為憑
A31: 31735064607611_002 | B31: 31735064607611 | C31: 2 | D31: 1925 | E31: 1925 | F31: =IF(D31="","?",IF(D31<1796,"pre-1796",IF(D31<1912,"1796-1911",IF(D31<1949,"1912-1948","1949+")))) -> 1912-1948 | G31: =IF(D31="","?",IF(D31<1912,"Qing",IF(D31<1949,"Republic","PRC"))) -> Republic | H31: 1925 | I31: 閩侯（閩縣・侯官・林森） | J31: 福建省閩侯縣 | K31: Government | M31: 張銓銓 | N31: 鄒道明 | O31: Box 3, Folder 123 | P31: Official form | Q31: 立契 | R31: 民國二十三年 | AE31: 賣 | 新頒契紙 | 吳 | 列則摘要 | AI31: 0 | AJ31: 0 | AK31: 0 | AL31: 0 | AM31: 0 | AN31: 0 | AO31: 0 | AP31: 0 | AQ31: 0 | AR31: 0 | AS31: 0 | AT31: 0 | AU31: 0 | AV31: 0 | AW31: 0 | AX31: 0 | AY31: 0 | AZ31: 0 | BA31: 0 | BB31: 0 | BC31: 50 | BD31: 0 | BE31: 0 | BF31: 0 | BG31: https://digital.library.pitt.edu/islandora/object/pitt:31735064607611 | BH31: 號賣新頒契紙吳買王姓名儲商百壽協廣軒大種類牆屋價壹千應納稅額原契幾張立契年月日民國二十三年拾列則摘要
A32: 31735064607629_001 | B32: 31735064607629 | C32: 1 | D32: 1898 | E32: 1898 | F32: =IF(D32="","?",IF(D32<1796,"pre-1796",IF(D32<1912,"1796-1911",IF(D32<1949,"1912-1948","1949+")))) -> 1796-1911 | G32: =IF(D32="","?",IF(D32<1912,"Qing",IF(D32<1949,"Republic","PRC"))) -> Qing | H32: 1898 | K32: Personal | M32: 蘇章林 | N32: 劉仕懋 | O32: Box 2, Folder 80 | P32: Private deed | Q32: 立賣契 | R32: 光緒貳拾肆年 | S32: 蘇章林 | U32: 價紋銀叁拾貳兩正 | V32: 紋銀; 洋銀 | W32: 濠墩門前 | Y32: 皮骨 | Z32: 前來說諭即將其田 | AA32: 邱宗海 | AI32: 0 | AJ32: 1 | AK32: 0 | AL32: 1 | AM32: 0 | AN32: 0 | AO32: 0 | AP32: 1 | AQ32: 0 | AR32: 0 | AS32: 1 | AT32: 0 | AU32: 0 | AV32: 0 | AW32: 0 | AX32: 0 | AY32: 0 | AZ32: 0 | BA32: 0 | BB32: 0 | BC32: 383 | BD32: 0 | BE32: 0 | BF32: 0 | BG32: https://digital.library.pitt.edu/islandora/object/pitt:31735064607629 | BH32: 立賣契人蘇章林承祖遺下置有皮骨分定晚田坐落濠墩門前土名溪壁洲確下外郎目上至陳宅田下至楊宅田右至陳宅田右至本宅田為界原計大苗糙米壹籮七斛六管正該載民產壹畝零今來俱出四至產畝明白茲因缺少銀兩應用情愿托得中人前來說諭即將其田盡底立契出賣與長布村劉仕懋名下邊為業當日三面議土風時值契價紋銀叁拾貳兩正足成契之日一頓現交未欠分厘並非準折債貨之類及無重復興賣之理所賣其田的係自己分定物業與親房伯叔兄弟侄人等各無相涉自賣之後其田言議叁冬取贖办得原價即便退還如無原價任從買主營業收租賣者不敢阻攔此係前言後定兩家甘允各無後悔再無異說恐口無憑今欲有憑敬立賣契為照當日計批上手契卷與網房相共不便照後日尋出不堪行用一存太里之番五甲蘇廷林戶名當官完糧不得丟累存據當日實得契價紋銀叁拾貳兩正足訖另批中書洋銀壹兩伍錢貳分正光緒貳拾肆年十一月廿三賣契人蘇章林見銀人蘇章林說諭人劉仕德代筆人邱宗海蘇章林
A33: 31735064607637_001 | B33: 31735064607637 | C33: 1 | D33: 1945 | E33: 1945 | F33: =IF(D33="","?",IF(D33<1796,"pre-1796",IF(D33<1912,"1796-1911",IF(D33<1949,"1912-1948","1949+")))) -> 1912-1948 | G33: =IF(D33="","?",IF(D33<1912,"Qing",IF(D33<1949,"Republic","PRC"))) -> Republic | H33: 1945 | I33: 永泰（永福） | J33: 福建省永泰縣 | K33: Government | L33: 葉文怡 | O33: Box 3, Folder 167 | P33: Other / fragment | AE33: 支款凭证(代支出传票) | AI33: 0 | AJ33: 0 | AK33: 0 | AL33: 0 | AM33: 0 | AN33: 0 | AO33: 0 | AP33: 0 | AQ33: 0 | AR33: 0 | AS33: 0 | AT33: 0 | AU33: 0 | AV33: 0 | AW33: 0 | AX33: 0 | AY33: 0 | AZ33: 0 | BA33: 0 | BB33: 0 | BC33: 140 | BD33: 0 | BE33: 0 | BF33: 0 | BG33: https://digital.library.pitt.edu/islandora/object/pitt:31735064607637 | BH33: 支款凭证(代支出传票)总第号填发日期196年月日分第号借方科目农业收入转帐日期1963年2月18日对方科目支款单位名称项目内支款人姓名盖章帐号摘要付由62年收入转入分配金類万千百十元角分金額(大写)一万肆仟叁百壹拾元玖角貳分正631092第一联出納存根付款单位主管会计出納記帳制表
A34: 31735064607637_002 | B34: 31735064607637 | C34: 2 | D34: 1945 | E34: 1945 | F34: =IF(D34="","?",IF(D34<1796,"pre-1796",IF(D34<1912,"1796-1911",IF(D34<1949,"1912-1948","1949+")))) -> 1912-1948 | G34: =IF(D34="","?",IF(D34<1912,"Qing",IF(D34<1949,"Republic","PRC"))) -> Republic | H34: 1945 | I34: 永泰（永福） | J34: 福建省永泰縣 | K34: Government | L34: 葉文怡 | O34: Box 3, Folder 167 | P34: Official form | AI34: 0 | AJ34: 0 | AK34: 0 | AL34: 0 | AM34: 0 | AN34: 0 | AO34: 0 | AP34: 0 | AQ34: 0 | AR34: 0 | AS34: 0 | AT34: 0 | AU34: 0 | AV34: 0 | AW34: 0 | AX34: 0 | AY34: 0 | AZ34: 0 | BA34: 0 | BB34: 0 | BC34: 9 | BD34: 0 | BE34: 0 | BF34: 0 | BG34: https://digital.library.pitt.edu/islandora/object/pitt:31735064607637 | BH34: 月縣長兼處長副處長
A35: 31735064607637_003 | B35: 31735064607637 | C35: 3 | D35: 1945 | E35: 1945 | F35: =IF(D35="","?",IF(D35<1796,"pre-1796",IF(D35<1912,"1796-1911",IF(D35<1949,"1912-1948","1949+")))) -> 1912-1948 | G35: =IF(D35="","?",IF(D35<1912,"Qing",IF(D35<1949,"Republic","PRC"))) -> Republic | H35: 1945 | I35: 永泰（永福） | J35: 福建省永泰縣 | K35: Government | L35: 葉文怡 | O35: Box 3, Folder 167 | P35: Official form | R35: 中華民國三十四年 | Y35: 基地 | AE35: 梧 字 第 3994 號 | 福建省永泰縣 土地管業執照 | AF35: 照永泰縣政府 | AG35: 葉文怡 | AH35: 梧字第 105 號 | AI35: 0 | AJ35: 0 | AK35: 0 | AL35: 0 | AM35: 0 | AN35: 0 | AO35: 0 | AP35: 0 | AQ35: 0 | AR35: 0 | AS35: 0 | AT35: 0 | AU35: 0 | AV35: 0 | AW35: 1 | AX35: 1 | AY35: 1 | AZ35: 1 | BA35: 0 | BB35: 0 | BC35: 294 | BD35: 0 | BE35: 0 | BF35: 0 | BG35: https://digital.library.pitt.edu/islandora/object/pitt:31735064607637 | BH35: 梧字第3994號福建省永泰縣土地管業執照永泰縣政府為發給土地管業執照事查本縣奉令舉辦土地陳報右記業主地畝業經審核無訛合行填發管業執照以憑管業嗣後如有買賣典當繼承分割合併贈與交換或其他產權移轉時一除典權外一務須持照遵章向本縣田賦機關聲請推收過戶換領新照倘有偽造或私擅塗改按律治罪須至執照者地主姓名土地座落地目等則面積賦額全年收益地價葉文怡梧桐鄉鎮土名橫樓梧字第105號基地式下340畝九分捌厘0元壹角叁分元斤分附記[35(top),34(right),17(bottom),and10(北)南)東)西)totheleft.]比例尺1:2000中華民國三十四年右給葉文怡收執縣長兼處長副處長日
A36: 31735064607645_001 | B36: 31735064607645 | C36: 1 | D36: 1891 | E36: 1891 | F36: =IF(D36="","?",IF(D36<1796,"pre-1796",IF(D36<1912,"1796-1911",IF(D36<1949,"1912-1948","1949+")))) -> 1796-1911 | G36: =IF(D36="","?",IF(D36<1912,"Qing",IF(D36<1949,"Republic","PRC"))) -> Qing | H36: 1891 | K36: Personal | L36: 林萬開 | O36: Box 2, Folder 74 | P36: Other / fragment | Q36: 立閭書 | S36: 林萬開偕 | Y36: 屋宇; 山場 | AI36: 0 | AJ36: 0 | AK36: 0 | AL36: 0 | AM36: 0 | AN36: 0 | AO36: 0 | AP36: 0 | AQ36: 0 | AR36: 0 | AS36: 0 | AT36: 0 | AU36: 0 | AV36: 0 | AW36: 0 | AX36: 0 | AY36: 0 | AZ36: 0 | BA36: 0 | BB36: 0 | BC36: 283 | BD36: 0 | BE36: 0 | BF36: 0 | BG36: https://digital.library.pitt.edu/islandora/object/pitt:31735064607645 | BH36: 立閭書林萬開偕弟萬拱等蓋聞棣華競秀四玉相輝荆樹交柯三珠並耀誠盛事也我儀圖之顧藉式好而臚歡自叶雁行之美亦因分勞而折箸尤徵燕翼之周斯一家各凜肩承辛勤共喻即百產亦知掌管子姓長綿矣茲者兄弟商議敬擇良月邀請親友將承父遺物業及手置田園屋宇山場樹木等項除撥長子長孫份外其餘高低相搭肥瘦相兼在祖宗堂前按照福祿壽三房勻作三股均分拈閭為定各掌各業向後不得爭長競短庶幾無負前人貽謀之計抑且以杜後來攘奪之端其宗族之幸多矣伏願自閭分之後各自摒擋須半粟一絲常思儉約五風十雨勿廢勤勞同胞貴有同心還期臂助分產當知分任莫懈躬親兄宜弟弟亦宜兄聯枝衍慶子生孫孫復生子奕葉流馨長發其祥克昌厥後有厚望焉是為序
A37: 31735064607645_002 | B37: 31735064607645 | C37: 2 | D37: 1891 | E37: 1891 | F37: =IF(D37="","?",IF(D37<1796,"pre-1796",IF(D37<1912,"1796-1911",IF(D37<1949,"1912-1948","1949+")))) -> 1796-1911 | G37: =IF(D37="","?",IF(D37<1912,"Qing",IF(D37<1949,"Republic","PRC"))) -> Qing | H37: 1891 | K37: Personal | L37: 林萬開 | O37: Box 2, Folder 74 | P37: Other / fragment | U37: 錢伍拾文 | Y37: 厝屋 | AI37: 0 | AJ37: 0 | AK37: 0 | AL37: 0 | AM37: 0 | AN37: 0 | AO37: 0 | AP37: 0 | AQ37: 0 | AR37: 0 | AS37: 0 | AT37: 0 | AU37: 0 | AV37: 0 | AW37: 0 | AX37: 0 | AY37: 0 | AZ37: 0 | BA37: 0 | BB37: 0 | BC37: 167 | BD37: 2 | BE37: 0 | BF37: 0 | BG37: https://digital.library.pitt.edu/islandora/object/pitt:31735064607645 | BH37: 計開長子長孫份下一田土名井嘴根面全壺畝叁分水壑壺口一田土名馬路下根面全壺畝式分水壑壺口此二號糧色均立在草市都五甲林鎮戶下一田土名坑裡根面全壺畝水壑壺口此項田貼與福房年例三年施食一年上厝西澗出海各用耗其糧色附在草市都五甲林鎮戶下其田尾所栽松栢楸係為祖墓風水不得砍伐福房份下一厝屋前進二欄年貼納完糧錢伍拾文一厝邊牛欄一堵一典楊定亨厝屋壺欄
A38: 31735064607645_003 | B38: 31735064607645 | C38: 3 | D38: 1891 | E38: 1891 | F38: =IF(D38="","?",IF(D38<1796,"pre-1796",IF(D38<1912,"1796-1911",IF(D38<1949,"1912-1948","1949+")))) -> 1796-1911 | G38: =IF(D38="","?",IF(D38<1912,"Qing",IF(D38<1949,"Republic","PRC"))) -> Qing | H38: 1891 | K38: Personal | L38: 林萬開 | O38: Box 2, Folder 74 | P38: Other / fragment | X38: 壇路根; 長坵根 | AI38: 0 | AJ38: 0 | AK38: 0 | AL38: 0 | AM38: 0 | AN38: 0 | AO38: 0 | AP38: 0 | AQ38: 0 | AR38: 0 | AS38: 0 | AT38: 0 | AU38: 0 | AV38: 0 | AW38: 0 | AX38: 0 | AY38: 0 | AZ38: 0 | BA38: 0 | BB38: 0 | BC38: 179 | BD38: 0 | BE38: 0 | BF38: 0 | BG38: https://digital.library.pitt.edu/islandora/object/pitt:31735064607645 | BH38: 一草倉馬路松楸下壺欄一田白龍土名根面全式畝壺分零糧色立在三十六都六甲林溥戶下一田白龍土名圓坵根面全捌分零糧色立在三十六都十甲林維豪戶下一田湖尾土名長坵根面全式畝式分零糧色立在三十六都七甲林昌元戶下一田后圳土名四角橫坵根面全捌分零典久溜夾片壑應半壑水用糧色立在三十六都四甲林均戶下一田白龍土名壇路根田式畝伍分年納本鄉王處面租穀叁百伍拾斤一田白龍土名長坵根田壺畝
A39: 31735064607645_004 | B39: 31735064607645 | C39: 4 | D39: 1891 | E39: 1891 | F39: =IF(D39="","?",IF(D39<1796,"pre-1796",IF(D39<1912,"1796-1911",IF(D39<1949,"1912-1948","1949+")))) -> 1796-1911 | G39: =IF(D39="","?",IF(D39<1912,"Qing",IF(D39<1949,"Republic","PRC"))) -> Qing | H39: 1891 | K39: Personal | L39: 林萬開 | O39: Box 2, Folder 74 | P39: Other / fragment | U39: 價陸拾兩 | Y39: 田面 | AI39: 0 | AJ39: 0 | AK39: 0 | AL39: 0 | AM39: 0 | AN39: 0 | AO39: 0 | AP39: 0 | AQ39: 0 | AR39: 0 | AS39: 0 | AT39: 0 | AU39: 0 | AV39: 0 | AW39: 0 | AX39: 0 | AY39: 0 | AZ39: 0 | BA39: 0 | BB39: 0 | BC39: 146 | BD39: 0 | BE39: 0 | BF39: 0 | BG39: https://digital.library.pitt.edu/islandora/object/pitt:31735064607645 | BH39: 年儀納福城林家面租穀壹百叁拾陸斤一田面租年共叁百柒拾捌斤糧色附在草市都五甲林鎮戶下一田林克江年應各壹百伍拾肆斤現耕林可廷一佃王聯環王聯豪林昌興昌國年應柒拾斤現耕林克品王鳳灼林可廷一田北馬鞍用價陸拾兩年應乾淨穀陸百斤現耕蘇長育此項王梅出閣貼用一糞池馬路厝仔邊壹口一糞池臺前大路邊壹口又糞池地壹塊
A40: 31735064607645_005 | B40: 31735064607645 | C40: 5 | D40: 1891 | E40: 1891 | F40: =IF(D40="","?",IF(D40<1796,"pre-1796",IF(D40<1912,"1796-1911",IF(D40<1949,"1912-1948","1949+")))) -> 1796-1911 | G40: =IF(D40="","?",IF(D40<1912,"Qing",IF(D40<1949,"Republic","PRC"))) -> Qing | H40: 1891 | K40: Personal | L40: 林萬開 | O40: Box 2, Folder 74 | P40: Other / fragment | U40: 錢肆百文 | Y40: 厝屋 | AE40: 祿房份下 | AI40: 0 | AJ40: 0 | AK40: 0 | AL40: 0 | AM40: 0 | AN40: 0 | AO40: 0 | AP40: 0 | AQ40: 0 | AR40: 0 | AS40: 0 | AT40: 0 | AU40: 0 | AV40: 0 | AW40: 0 | AX40: 0 | AY40: 0 | AZ40: 0 | BA40: 0 | BB40: 0 | BC40: 196 | BD40: 1 | BE40: 0 | BF40: 0 | BG40: https://digital.library.pitt.edu/islandora/object/pitt:31735064607645 | BH40: 祿房份下一厝屋第三進二櫚披水壺櫚其門路由二進出入喜喪事二進大廳通用年納楊家地租伍拾文一厝屋楊家隔壁壺櫚一草倉祠堂下壺櫚一田湖尾土名水流路根面全叁畝叁分糧色立在三十六都二圖二甲林開戶下又納倪家禾租肆拾斤折錢肆百文一田湖尾土名流道應半根面全壺畝壹分糧色立在三十六都二圖二甲林春戶下又買斷可真典與白龍張家應半田底一田湖尾土名豬蹄坵根面全壺畝叁分典契價壺百兩又借式拾兩糧色立在三十六都二圖四甲林均戶下
A41: 31735064607645_006 | B41: 31735064607645 | C41: 6 | D41: 1891 | E41: 1891 | F41: =IF(D41="","?",IF(D41<1796,"pre-1796",IF(D41<1912,"1796-1911",IF(D41<1949,"1912-1948","1949+")))) -> 1796-1911 | G41: =IF(D41="","?",IF(D41<1912,"Qing",IF(D41<1949,"Republic","PRC"))) -> Qing | H41: 1891 | K41: Personal | L41: 林萬開 | O41: Box 2, Folder 74 | P41: Other / fragment | Y41: 田面 | AI41: 0 | AJ41: 0 | AK41: 0 | AL41: 0 | AM41: 0 | AN41: 0 | AO41: 0 | AP41: 0 | AQ41: 0 | AR41: 0 | AS41: 0 | AT41: 0 | AU41: 0 | AV41: 0 | AW41: 0 | AX41: 0 | AY41: 0 | AZ41: 0 | BA41: 0 | BB41: 0 | BC41: 141 | BD41: 0 | BE41: 0 | BF41: 0 | BG41: https://digital.library.pitt.edu/islandora/object/pitt:31735064607645 | BH41: 一田后圳土名五二坵根面全壺畝捌分水壑壺口糧色立在三十八都二圖十甲林盛熾戶下一田后圳土名橄欖坵根面全式畝式分零糧色附在林均戶下又納本鄉陳家面租叁百壺拾伍斤一田后圳土名根田陸分年納李家面租壺百斤一田面租年應式百斤糧色附在三十八都林溥戶下一糞池下底園上邊壺口又臺前大路邊壺口又蛇山山頂壺口
A42: 31735064607645_007 | B42: 31735064607645 | C42: 7 | D42: 1891 | E42: 1891 | F42: =IF(D42="","?",IF(D42<1796,"pre-1796",IF(D42<1912,"1796-1911",IF(D42<1949,"1912-1948","1949+")))) -> 1796-1911 | G42: =IF(D42="","?",IF(D42<1912,"Qing",IF(D42<1949,"Republic","PRC"))) -> Qing | H42: 1891 | K42: Personal | L42: 林萬開 | O42: Box 2, Folder 74 | P42: Other / fragment | X42: 洋中根 | Y42: 厝屋 | AE42: 壽房份下 | AI42: 0 | AJ42: 0 | AK42: 0 | AL42: 0 | AM42: 0 | AN42: 0 | AO42: 0 | AP42: 0 | AQ42: 0 | AR42: 0 | AS42: 0 | AT42: 0 | AU42: 0 | AV42: 0 | AW42: 0 | AX42: 0 | AY42: 0 | AZ42: 0 | BA42: 0 | BB42: 0 | BC42: 175 | BD42: 1 | BE42: 0 | BF42: 0 | BG42: https://digital.library.pitt.edu/islandora/object/pitt:31735064607645 | BH42: 壽房份下一厝屋第二進壺櫚直透後滴水止年納楊家地租伍拾文其第三進門路聽其出入大廳祿房喜喪事通用一厝屋二進前照壺堵一厝屋祠堂邊壺櫚一田白龍后圳土名燈籠坵根面全叁畝叁分糧色立在三十六都二圖三甲林茂戶下一田白龍壇路土名磨盤根面全式畝糧色立在三十六都二圖四甲林潤之戶下一田湖尾土名長坵頭根面全式畝式分糧色立在三十六都二圖四甲林棟戶下一田湖尾土名洋中根田壺畝捌分
A43: 31735064607645_008 | B43: 31735064607645 | C43: 8 | D43: 1891 | E43: 1891 | F43: =IF(D43="","?",IF(D43<1796,"pre-1796",IF(D43<1912,"1796-1911",IF(D43<1949,"1912-1948","1949+")))) -> 1796-1911 | G43: =IF(D43="","?",IF(D43<1912,"Qing",IF(D43<1949,"Republic","PRC"))) -> Qing | H43: 1891 | K43: Personal | L43: 林萬開 | O43: Box 2, Folder 74 | P43: Other / fragment | U43: 錢陸拾文 | Y43: 田面 | AI43: 0 | AJ43: 0 | AK43: 0 | AL43: 0 | AM43: 0 | AN43: 0 | AO43: 0 | AP43: 0 | AQ43: 0 | AR43: 0 | AS43: 0 | AT43: 0 | AU43: 0 | AV43: 0 | AW43: 0 | AX43: 0 | AY43: 0 | AZ43: 0 | BA43: 0 | BB43: 0 | BC43: 187 | BD43: 0 | BE43: 0 | BF43: 0 | BG43: https://digital.library.pitt.edu/islandora/object/pitt:31735064607645 | BH43: 年納井片亭李家面租式百貳拾肆斤一田面租年應式百肆拾斤糧邑附在平都林灣戶下佃李木韶現耕張慶壽一糞池下底園下邊壺口又白龍張家厝邊壺口又大路邊坊裡壺口又湖尾壺口福祿壽三房公衆份下一祠堂邊厝地三欄各應壺欄左邊撥與壽房如各房先後起蓋其墻准後起架析一園下底園壺坪一園對面園壺坪內所有樹木籽粒柴草三房照輪一園坑口園壺坪內橄欖欖壺株應貼納糧錢陸拾文一園桃棗坪壺坪內橄欖欖式株應貼納糧錢陸拾文
A44: 31735064607645_009 | B44: 31735064607645 | C44: 9 | D44: 1891 | E44: 1891 | F44: =IF(D44="","?",IF(D44<1796,"pre-1796",IF(D44<1912,"1796-1911",IF(D44<1949,"1912-1948","1949+")))) -> 1796-1911 | G44: =IF(D44="","?",IF(D44<1912,"Qing",IF(D44<1949,"Republic","PRC"))) -> Qing | H44: 1891 | K44: Personal | L44: 林萬開 | O44: Box 2, Folder 74 | P44: Other / fragment | U44: 錢叁拾文; 錢伍拾文 | X44: 王豹四 | Y44: 墳 | AI44: 0 | AJ44: 0 | AK44: 0 | AL44: 0 | AM44: 0 | AN44: 0 | AO44: 0 | AP44: 0 | AQ44: 0 | AR44: 0 | AS44: 0 | AT44: 0 | AU44: 0 | AV44: 0 | AW44: 0 | AX44: 0 | AY44: 0 | AZ44: 0 | BA44: 0 | BB44: 0 | BC44: 238 | BD44: 1 | BE44: 0 | BF44: 0 | BG44: https://digital.library.pitt.edu/islandora/object/pitt:31735064607645 | BH44: 一園坑裡厝仔前壺坪年納糧錢叁拾文一坑裡田仔壺坵年貼納糧錢叁拾文此四號糧色均立在草市都林鎮戶下三房公納一山坑裡山壺崙內沈家契買土名王豹四田仔壺塊年應貼納糧錢伍拾文三房公納一山坑裡對面山壺崙檳欖檳壺株山園內所有松栢檳除沈家墓邊左右陸株外又自己祖墓邊留作風水不得砍伐其餘大株各作記號聽各房自行砍伐小株未號者以及隨後長大者亦照株勻分不得私自砍伐山內如有新理造墳以及補墓年礼花紅一切均照三股勻分不得爭執所有柴草三房照輪週而復始又坑裡山壺塊係與堂叔昌意堂兄萬進夾買所有山內籽粒亦照三房公分
A45: 31735064607645_010 | B45: 31735064607645 | C45: 10 | D45: 1891 | E45: 1891 | F45: =IF(D45="","?",IF(D45<1796,"pre-1796",IF(D45<1912,"1796-1911",IF(D45<1949,"1912-1948","1949+")))) -> 1796-1911 | G45: =IF(D45="","?",IF(D45<1912,"Qing",IF(D45<1949,"Republic","PRC"))) -> Qing | H45: 1891 | K45: Personal | L45: 林萬開 | O45: Box 2, Folder 74 | P45: Other / fragment | Q45: 立閨書 | R45: 光緒拾柒年 | S45: 林萬開 | AB45: 族長昌意 | AI45: 0 | AJ45: 0 | AK45: 0 | AL45: 0 | AM45: 0 | AN45: 0 | AO45: 0 | AP45: 0 | AQ45: 0 | AR45: 0 | AS45: 0 | AT45: 0 | AU45: 0 | AV45: 1 | AW45: 0 | AX45: 0 | AY45: 0 | AZ45: 0 | BA45: 0 | BB45: 0 | BC45: 61 | BD45: 2 | BE45: 0 | BF45: 0 | BG45: https://digital.library.pitt.edu/islandora/object/pitt:31735064607645 | BH45: 光緒拾柒年八月吉日立閨書林萬開德全弟萬拱萬欽德在見族長昌意堂弟萬順德堂姪可娘德外甥塗振海德姪婿蕭慶金德李茂炳德秉筆姪可舉德
A46: 31735064607652_001 | B46: 31735064607652 | C46: 1 | D46: 1798 | E46: 1798 | F46: =IF(D46="","?",IF(D46<1796,"pre-1796",IF(D46<1912,"1796-1911",IF(D46<1949,"1912-1948","1949+")))) -> 1796-1911 | G46: =IF(D46="","?",IF(D46<1912,"Qing",IF(D46<1949,"Republic","PRC"))) -> Qing | H46: 1798 | I46: 建陽 | J46: 福建省建陽縣 | K46: Government | M46: 劉盛章 | N46: 劉咸安 | 劉道建 | O46: Box 1, Folder 11 | P46: Private deed | Q46: 立增找杜斷朽房屋基契 | R46: 嘉慶叁年 | S46: 劉盛章 | V46: 紋銀 | W46: 水北永興社賣主房屋后四至銀兩前契 | Y46: 地基 | AA46: 劉如萬 | AI46: 1 | AJ46: 1 | AK46: 0 | AL46: 0 | AM46: 1 | AN46: 0 | AO46: 0 | AP46: 0 | AQ46: 1 | AR46: 0 | AS46: 1 | AT46: 0 | AU46: 0 | AV46: 0 | AW46: 0 | AX46: 0 | AY46: 0 | AZ46: 0 | BA46: 0 | BB46: 0 | BC46: 250 | BD46: 2 | BE46: 0 | BF46: 0 | BG46: https://digital.library.pitt.edu/islandora/object/pitt:31735064607652 | BH46: 立增找離業杜斷朽房屋地基契人劉盛章緣因旧年冬賣斷有朽房屋地基共計叁欄坐落水北永興社賣主房屋后四至銀兩前契載明今因缺少銀應用自己托得原中向買主本族道成安名下增找得杜斷朽房屋基價白系紋銀捌兩正成增契之日壹併交足不少分厘自增找斷之后仍憑買者永遠營業修整架造開門出入賣者不敢阻佔此係賣斷增找物業日久不再得另生枝節言增言找之理情愿甘允各無後悔生端異說今欲有憑立增找杜斷朽房屋地基契字為照本日寔收得增找杜斷契價紋銀捌兩正足訖再照外用中銀貳錢津分正嘉慶叁年貳月日立增找杜斷朽房屋基契人劉盛章原中代字人劉如萬增找斷契
A47: 31735064607660_001 | B47: 31735064607660 | C47: 1 | D47: 1805 | E47: 1805 | F47: =IF(D47="","?",IF(D47<1796,"pre-1796",IF(D47<1912,"1796-1911",IF(D47<1949,"1912-1948","1949+")))) -> 1796-1911 | G47: =IF(D47="","?",IF(D47<1912,"Qing",IF(D47<1949,"Republic","PRC"))) -> Qing | H47: 1805 | I47: 建陽 | J47: 福建省建陽縣 | K47: Government | L47: 劉咸安 | O47: Box 1, Folder 13 | P47: Other / fragment | AE47: 勅 | AI47: 0 | AJ47: 0 | AK47: 0 | AL47: 0 | AM47: 0 | AN47: 0 | AO47: 0 | AP47: 0 | AQ47: 0 | AR47: 0 | AS47: 0 | AT47: 0 | AU47: 0 | AV47: 0 | AW47: 1 | AX47: 0 | AY47: 0 | AZ47: 0 | BA47: 0 | BB47: 0 | BC47: 121 | BD47: 3 | BE47: 1 | BF47: 0 | BG47: https://digital.library.pitt.edu/islandora/object/pitt:31735064607660 | BH47: 勅微卷九三福建等處督撫使司為查請奏事於嘉靖十五年正月二十四日...福建等處督撫使司為...查請奏事於嘉靖十五年正月二十四日...福建等處督撫使司為...查請奏事於嘉靖十五年正月二十四日...嘉靖十年五月劉成資劉盛平建陽縣...劉成安貳拾肆兩日
A48: 31735064607678_001 | B48: 31735064607678 | C48: 1 | D48: 1782 | E48: 1782 | F48: =IF(D48="","?",IF(D48<1796,"pre-1796",IF(D48<1912,"1796-1911",IF(D48<1949,"1912-1948","1949+")))) -> pre-1796 | G48: =IF(D48="","?",IF(D48<1912,"Qing",IF(D48<1949,"Republic","PRC"))) -> Qing | H48: 1782 | I48: 建陽 | J48: 福建省建陽縣 | K48: Government | M48: 應梓龍 | N48: 劉繼伍 | O48: Box 1, Folder 9 | P48: Private deed | Q48: 立增我杜新契 | R48: 乾隆肆拾柒年 | U48: 價紋銀壹拾柒兩; 價紋銀壹拾柒兩正 | V48: 紋銀 | Y48: 田皮 | Z48: 札銀伍錢壹分正; 劉禮雲 | AA48: 徐遇萬 | AI48: 0 | AJ48: 0 | AK48: 0 | AL48: 0 | AM48: 0 | AN48: 0 | AO48: 0 | AP48: 0 | AQ48: 1 | AR48: 1 | AS48: 1 | AT48: 0 | AU48: 0 | AV48: 0 | AW48: 0 | AX48: 0 | AY48: 0 | AZ48: 0 | BA48: 0 | BB48: 0 | BC48: 246 | BD48: 2 | BE48: 0 | BF48: 0 | BG48: https://digital.library.pitt.edu/islandora/object/pitt:31735064607678 | BH48: 立增我杜新契字人應梓龍本年賣新有田皮骨未染羅涼餅伍管止坐春筵上橫寮游嶺黃厝墘銀面前契載明今日無銀完編托得原中勸諭原買主劉維伍名下增我杜新價紋銀壹拾柒兩立成契之日一併文足不欠分厘自增我新之後仍准買主永遠晉業交租收割過戶當差完糧其田實係增我新根物業嗣后永無言增言我之理此際兩下甘允再無反悔生端異說今故有現立增我杜新契字人應梓龍為照本日寔收得增我杜新契內價紋銀壹拾柒兩正再照。外用中見札銀伍錢壹分正乾隆肆拾柒年玖月日立增我杜新契字人應梓龍。知契人應梓明唐中人劉禮雲勸諭人劉兆華代字人徐遇萬增我杜新契
A49: 31735064607686_001 | B49: 31735064607686 | C49: 1 | D49: 1910 | E49: 1910 | F49: =IF(D49="","?",IF(D49<1796,"pre-1796",IF(D49<1912,"1796-1911",IF(D49<1949,"1912-1948","1949+")))) -> 1796-1911 | G49: =IF(D49="","?",IF(D49<1912,"Qing",IF(D49<1949,"Republic","PRC"))) -> Qing | H49: 1910 | K49: Government | M49: 開保 | O49: Box 2, Folder 91 | P49: Private deed | Q49: 立典契 | R49: 宣統貳年 | S49: 堂侄孫開 | V49: 番銀 | Y49: 民田 | Z49: 族叔端率極 | AB49: 知契父端理 | AI49: 1 | AJ49: 0 | AK49: 1 | AL49: 0 | AM49: 1 | AN49: 1 | AO49: 1 | AP49: 1 | AQ49: 0 | AR49: 1 | AS49: 1 | AT49: 0 | AU49: 0 | AV49: 1 | AW49: 0 | AX49: 0 | AY49: 0 | AZ49: 0 | BA49: 0 | BB49: 0 | BC49: 253 | BD49: 0 | BE49: 0 | BF49: 0 | BG49: https://digital.library.pitt.edu/islandora/object/pitt:31735064607686 | BH49: 姓立典契堂侄孫開保原父手圖分份下有民田陸其糧米掛在保我面前甲陳元華干下糧應壹錢伍分正米應我升陸合正今因要用托中引到叔祖朝朋慶諸面議典得出價番銀拾員正每員陸錢叁分重其銀即日親手收足其田即付叔祖受業召佃他人耕作收租完課皆係原父手圖分份下物業與房內諸人無干並未重張典當他人財物中有不明係作自己出頭抵當不涉叔祖之事其年面約致年限滿備銀照舊契面量數取贖外加銀水茶占伍厘正銀到契還叔祖不得阻留支理此乃兩家允愿各無反悔今啟有舊立典契壹份為據在見知契父端理宣統貳年拾壹月吉日立典契堂侄孫開保中人族叔端率極族弟開次不1612
A50: 31735064607694_001 | B50: 31735064607694 | C50: 1 | D50: 1913 | E50: 1913 | F50: =IF(D50="","?",IF(D50<1796,"pre-1796",IF(D50<1912,"1796-1911",IF(D50<1949,"1912-1948","1949+")))) -> 1912-1948 | G50: =IF(D50="","?",IF(D50<1912,"Qing",IF(D50<1949,"Republic","PRC"))) -> Republic | H50: 1913 | I50: 閩侯（閩縣・侯官・林森） | J50: 福建省閩侯縣 | K50: Government | M50: 林應香 | N50: 林萬開 | O50: Box 2, Folder 97 | P50: Official form | R50: 中華民國貳 年 | AE50: 斷賣契單 | AG50: 林萬開 | AH50: 驗字第三萬七千六百六十九號 | AI50: 0 | AJ50: 0 | AK50: 0 | AL50: 0 | AM50: 0 | AN50: 0 | AO50: 0 | AP50: 0 | AQ50: 0 | AR50: 0 | AS50: 0 | AT50: 0 | AU50: 0 | AV50: 0 | AW50: 1 | AX50: 0 | AY50: 0 | AZ50: 1 | BA50: 0 | BB50: 0 | BC50: 152 | BD50: 0 | BE50: 0 | BF50: 0 | BG50: https://digital.library.pitt.edu/islandora/object/pitt:31735064607694 | BH50: 斷賣契單福建田賦心籌備處為給發契單事示奉財政部電行劃一契未稅契均應一併限收紙價壹元未稅之酌定正限三個月餘財政部核准照辦並通飭遵照在案日買受林應者田地貳畝西至原西北至坐向橫丈尺直丈尺中證陳春雷紙價壹元已以填契占重原契一稅遵章依限呈驗應納右給業戶林萬開准此中華民國貳年拾貳月拾柒日給驗字第三萬七千六百六十九號
A51: 31735064607702_001 | B51: 31735064607702 | C51: 1 | D51: 1906 | E51: 1906 | F51: =IF(D51="","?",IF(D51<1796,"pre-1796",IF(D51<1912,"1796-1911",IF(D51<1949,"1912-1948","1949+")))) -> 1796-1911 | G51: =IF(D51="","?",IF(D51<1912,"Qing",IF(D51<1949,"Republic","PRC"))) -> Qing | H51: 1906 | I51: 閩侯（閩縣・侯官・林森） | J51: 福建省閩侯縣 | K51: Government | M51: 林為良 | N51: 林可瓊 | O51: Box 2, Folder 87 | P51: Official form | R51: 光緒叁拾貳年; 光緒 叁拾貳 年 | U51: 價銀壹百叁拾兩 | W51: 十市都黃道 | Y51: 民田 | Z51: 劉興國 | AA51: 王清泉 | AB51: 叔維屏心 | AI51: 0 | AJ51: 0 | AK51: 1 | AL51: 0 | AM51: 1 | AN51: 1 | AO51: 1 | AP51: 0 | AQ51: 1 | AR51: 0 | AS51: 0 | AT51: 0 | AU51: 1 | AV51: 0 | AW51: 0 | AX51: 0 | AY51: 0 | AZ51: 0 | BA51: 0 | BB51: 0 | BC51: 268 | BD51: 0 | BE51: 0 | BF51: 0 | BG51: https://digital.library.pitt.edu/islandora/object/pitt:31735064607702 | BH51: 置根面令民田壹號坐落十市都黃道地方冊載地字式百號地中則民田池應半計官丈壹畝伍分二二五五忽根掛本都七甲林福戶下完糧銀壹錢式分式七毫色米壹升柒合五口應享無異公為要用托中復還賣斷上目抄此族弟可瓊永遠向業一面議定賣斷田價銀壹百叁拾兩每兩一捌百文即日收足其田聽業完課良之後永斷萬以勝不敢割枝節此輩與人之子亦未重張由當與承當與瓊令子兩出契壹紙亦緣楊鵬超幾曲出契林可鐫湊斷壹紙共成叁納統付為內註壹紙二十標光緒叁拾貳年拾壹月日賣斷根面會契林為良憑在見叔維屏心中人劉興國代筆王清泉光緒叁拾貳年拾壹月閩侯縣西門區稅契分局清光緒叁拾貳年永遠向業西湖區稅契分局
A52: 31735064607710_001 | B52: 31735064607710 | C52: 1 | D52: 1932 | E52: 1932 | F52: =IF(D52="","?",IF(D52<1796,"pre-1796",IF(D52<1912,"1796-1911",IF(D52<1949,"1912-1948","1949+")))) -> 1912-1948 | G52: =IF(D52="","?",IF(D52<1912,"Qing",IF(D52<1949,"Republic","PRC"))) -> Republic | H52: 1932 | K52: Personal | L52: 林可昌 | 林可淦 | O52: Box 3, Folder 146 | P52: Other / fragment | Q52: 立聲昭遺失契 | R52: 民國二十一年 | S52: 林可 | Y52: 田根 | AA52: 王幼卿 | AI52: 1 | AJ52: 0 | AK52: 0 | AL52: 0 | AM52: 0 | AN52: 0 | AO52: 0 | AP52: 0 | AQ52: 1 | AR52: 0 | AS52: 1 | AT52: 0 | AU52: 0 | AV52: 1 | AW52: 0 | AX52: 0 | AY52: 0 | AZ52: 0 | BA52: 0 | BB52: 0 | BC52: 238 | BD52: 0 | BE52: 0 | BF52: 0 | BG52: https://digital.library.pitt.edu/islandora/object/pitt:31735064607710 | BH52: 立聲昭遺失契字林可昌可金今因有祖遺閩書分長子長孫份下田根壟號土名坑裏計大小五坵厝丈壹畝畧田頭水壟壟口田尾松柏五株上輩字置原盡斷各契共七紙計產價式拾捌而四因前久謝年幼契箱寄存別處各項契據不知遺失何方茲經公親檢閱閩書所載證明係福房管業以作施食上座及西間出海各用耗嗣後無論內外親屬人等務出此項遺失契據永遠作為廢紙此係由公親議定恐後日舊生枝弟以杜絕爭執情事特立此紙付久謝執掌永遠為據民國二十一年五月吉日立聲昭字林可昌繼弟洽落公陳其清孫經見王兆鋒孫王光森孫親林可泉孫林久機孫代筆王幼卿啓
A53: 31735064607728_001 | B53: 31735064607728 | C53: 1 | D53: 1862 | E53: 1862 | F53: =IF(D53="","?",IF(D53<1796,"pre-1796",IF(D53<1912,"1796-1911",IF(D53<1949,"1912-1948","1949+")))) -> 1796-1911 | G53: =IF(D53="","?",IF(D53<1912,"Qing",IF(D53<1949,"Republic","PRC"))) -> Qing | H53: 1862 | K53: Personal | M53: 楊兆通 | N53: 林 | O53: Box 1, Folder 37 | P53: Private deed | Q53: 立典田根契 | S53: 楊允通 | T53: 林 | U53: 價銀貳百捌拾叁兩; 銀折銅錢柒百伍拾文 | W53: 候邑三十八都白龍嶺路 | Y53: 田根; 民田 | Z53: 蔡書波 | AB53: 胞弟允如 | AD53: 叁 | AI53: 0 | AJ53: 0 | AK53: 1 | AL53: 1 | AM53: 1 | AN53: 1 | AO53: 1 | AP53: 1 | AQ53: 0 | AR53: 1 | AS53: 1 | AT53: 1 | AU53: 1 | AV53: 1 | AW53: 0 | AX53: 0 | AY53: 0 | AZ53: 0 | BA53: 0 | BB53: 0 | BC53: 373 | BD53: 0 | BE53: 0 | BF53: 0 | BG53: https://digital.library.pitt.edu/islandora/object/pitt:31735064607728 | BH53: 立典田根契楊允通承父閻分份入有民田根壺號坐產候邑三十八都白龍嶺路地方土名鯽魚坵計寬丈貳畝伍分大小三坵池壺口共拜坵年納向主王家早晚租谷叁百伍拾劬平秤厯掌互易今日要用托中將此田根典與林處為業三面言议本日以訖田根價銀貳百捌拾叁兩伍錢正其銀即日收足其田根听從買主前去翻犁耕作了納向租向約叁年為限俟限滿之日听備價照契向銀兩取贖每兩銀折銅錢柒百伍拾文算如未取贖仍听照舊管業但此田係通承父閻分已份入與別房親疎伯叔兄弟侄妾干亦未曾重張典當他人物以及未厯不明各等情如有此情係通出以承當不得銀主之子兩相允厚各共翻悔今欲有憑立典田根契壹紙併繳楊昌箴典契壹紙邦銘尽契壹紙海武斷契壹紙共成律紙統付為照向約贖田之日叁至前為期併東壩壹起統贖不得抽贖內註物業財共三字統標照舊同治元年八月吉日立典田根契楊允通謹在見胞弟允如堂侄能波傳中友蔡書波傳劉朝達傳李兆相傳花筆李肇松謹Y李兆相
A54: 31735064607736_001 | B54: 31735064607736 | C54: 1 | D54: 1913 | E54: 1913 | F54: =IF(D54="","?",IF(D54<1796,"pre-1796",IF(D54<1912,"1796-1911",IF(D54<1949,"1912-1948","1949+")))) -> 1912-1948 | G54: =IF(D54="","?",IF(D54<1912,"Qing",IF(D54<1949,"Republic","PRC"))) -> Republic | H54: 1913 | I54: 閩侯（閩縣・侯官・林森） | J54: 福建省閩侯縣 | K54: Government | M54: 林可瓊 | N54: 劉興國 | O54: Box 2, Folder 94 | P54: Official form | Q54: 立之不動產舊契 | R54: 光緒叁拾貳年; 中華民國 貳年 | U54: 價銀壹百叁拾兩; 銀壹百八肆元 | AE54: 建國稅廳籌 | AG54: 林可瓊 | AI54: 0 | AJ54: 0 | AK54: 0 | AL54: 0 | AM54: 0 | AN54: 0 | AO54: 0 | AP54: 0 | AQ54: 0 | AR54: 0 | AS54: 1 | AT54: 0 | AU54: 0 | AV54: 0 | AW54: 0 | AX54: 1 | AY54: 0 | AZ54: 0 | BA54: 1 | BB54: 1 | BC54: 327 | BD54: 0 | BE54: 0 | BF54: 0 | BG54: https://digital.library.pitt.edu/islandora/object/pitt:31735064607736 | BH54: 建國稅廳籌給契單事案奉為斷賣財政部電行劃一契紙章程內開本章程施行以前成立之不動產舊契無論已稅契未稅契均應一律限期呈驗逾限不呈驗者於訴訟時不能作為憑據一併函知司法機關認真辦理以為置驗方成等因奉此旨經提定分別徵收方法已稅之舊契每張收紙價壹元未稅之舊契每產價百元收紙價壹元其光復後新契已稅者不收紙價酌定正限三個月餘限兩個月逾期呈驗者分別加徵嚴罰經已電奉財政部核准照辦並通飭遵照在案今蒙閩縣業戶林可瓊於清光緒叁拾貳年拾壹月日買受林為良四壹畝作八零三落閩縣業戶林可瓊於清光緒叁拾貳年拾壹月西至北至坐向橫丈尺直丈尺中證劉興國原價銀壹百叁拾兩中銀壹百八肆元原未稅遵章依限呈驗應納紙價壹元業已如數收訖合填契單未連原契給收管業須至契單才給業戶林可瓊准此中華民國貳年拾壹月叁
A55: 31735064607744_001 | B55: 31735064607744 | C55: 1 | D55: 1913 | E55: 1913 | F55: =IF(D55="","?",IF(D55<1796,"pre-1796",IF(D55<1912,"1796-1911",IF(D55<1949,"1912-1948","1949+")))) -> 1912-1948 | G55: =IF(D55="","?",IF(D55<1912,"Qing",IF(D55<1949,"Republic","PRC"))) -> Republic | H55: 1913 | I55: 閩侯（閩縣・侯官・林森） | J55: 福建省閩侯縣 | K55: Government | M55: 王聯鄧 | N55: 林萬開 | O55: Box 2, Folder 95 | P55: Official form | Q55: 立之不動產舊契 | R55: 光緒貳拾年; 中華民國 貳年 | U55: 價銀兩中銀壹百叁拾捌元 | W55: 閩侯縣三十八都白龍坑 | AE55: 斷賣契單 | 福建國稅廳籌備處 | AF55: 福建國稅廳籌備處 | AG55: 林萬開 | AH55: 驗字第三千七百九號 | AI55: 0 | AJ55: 0 | AK55: 0 | AL55: 0 | AM55: 0 | AN55: 0 | AO55: 0 | AP55: 0 | AQ55: 0 | AR55: 0 | AS55: 1 | AT55: 0 | AU55: 0 | AV55: 0 | AW55: 0 | AX55: 1 | AY55: 1 | AZ55: 0 | BA55: 1 | BB55: 1 | BC55: 334 | BD55: 0 | BE55: 0 | BF55: 0 | BG55: https://digital.library.pitt.edu/islandora/object/pitt:31735064607744 | BH55: 斷賣契單福建國稅廳籌備處給發契單事案奉財政部電行劃一紙書程內開本章程施行以前成立之不動產舊契無論已稅契未稅契均應一律限期呈驗逾限不呈驗者於訴訟時不能作為憑據一併函知司法機關認真辦理以為憑驗者戒等因奉此當經擬定分函徵收方法已稅之舊契每張收紙價壹元未稅之舊契每張收紙價壹元其先後新契已稅者不收紙價酌定正限三個月餘限兩個月逾期呈驗者分別加徵嚴罰經已電奉財政部核准照辦並通飭遵照在案今據閩侯縣業戶林萬開於清光緒貳拾年拾月日買受王兆熙田畝壹畝坐落閩侯縣三十八都白龍坑地方東至西至北至坐落向黃大尺直丈尺中證王聯登店價銀兩中銀壹百叁拾捌元原契未稅連章依限呈驗應納紙價壹元肆角業已收訖合填契單粘連原契印給收執管業須至契單者石給業戶林萬開准此中華民國貳年拾壹月叁拾日給驗字第三千七百九號
A56: 31735064607751_001 | B56: 31735064607751 | C56: 1 | D56: 1884 | E56: 1884 | F56: =IF(D56="","?",IF(D56<1796,"pre-1796",IF(D56<1912,"1796-1911",IF(D56<1949,"1912-1948","1949+")))) -> 1796-1911 | G56: =IF(D56="","?",IF(D56<1912,"Qing",IF(D56<1949,"Republic","PRC"))) -> Qing | H56: 1884 | I56: 閩侯（閩縣・侯官・林森） | J56: 福建省侯官縣 | K56: Government | M56: 林秋溥 | N56: 林萬開 | O56: Box 2, Folder 58 | P56: Private deed | Q56: 立撥典契 | R56: 光緒拾年 | S56: 林秋溥 | T56: 堂兄萬開 | U56: 價銀肆拾肆兩正 | W56: 侯邑西關外三十八都馬坑白龍 | X56: 白龍水流坵圓坵; 大堦邊上; 白龍上; 水流坵上; 園坵上 | Y56: 民田; 田面 | Z56: 王有才 | AA56: 侄榮陽 | AB56: 弟萬 | AI56: 0 | AJ56: 0 | AK56: 1 | AL56: 1 | AM56: 1 | AN56: 1 | AO56: 0 | AP56: 1 | AQ56: 0 | AR56: 1 | AS56: 1 | AT56: 0 | AU56: 0 | AV56: 0 | AW56: 0 | AX56: 0 | AY56: 0 | AZ56: 0 | BA56: 0 | BB56: 0 | BC56: 511 | BD56: 0 | BE56: 0 | BF56: 0 | BG56: https://digital.library.pitt.edu/islandora/object/pitt:31735064607751 | BH56: 立撥典契林秋溥原自己典得何德興民田面數號坐產侯邑西關外三十八都馬坑白龍地方土名白龍東洋大堦邊水流坵圓坵等處內撥出伍號土名白龍水流坵圓坵等處上中下則田計官犬肆畝捌分畧其糧色立在本都二圖六甲何德興戶下年載租穀捌百陸拾捌歷掌收租完課無異茲因別置託中撥典與堂兄萬開處為業三面言議本日得訖田面價銀肆拾肆兩正大錠庫錫其銀即日收足其田面聽官業收租其糧色照憑縣例科派過甲易戶完納撥典後與無干倘原主取贖不拘年限照憑契面銀兩取贖買主亦不得執留但此田面係自己手置物業與本別房伯叔兄弟侄無干亦未曾重張典掛他人財物如有朱歷不明各等情出頭抵當與買主無涉兩相允願各勿反悔今欲有憑立撥典田面契畫紙為照計向區號畝數租額日字由區畫百式拾玖號土名大堦邊上田畝分叁厘貳毫九絲貳忽貳式百斤佃林萬裔又叁百零貳式土名白龍上田畝分六厘捌毫柒絲伍忽貳式百斤佃李捷崇又貳百柒拾捌號土名水流坵上田畝分叁厘捌毫叁絲叁忽貳式百斤佃林萬裔又叁百捌拾貳號土名白龍上田畝分伍厘柒毫貳絲租共叁百陸拾斤佃林萬裔日字十區肆百壹拾號土名園坵上田畝分陸厘柒毫伍忽何家原契與別業相連未便繳付標照標照光緒拾年貳月吉明並日立撥典田面契林秋溥非賣與外人如違擅擅擅擅在見弟萬拱拱拱拱中友王有才大熟代筆侄榮陽
A57: 31735064607769_001 | B57: 31735064607769 | C57: 1 | D57: 1884 | E57: 1884 | F57: =IF(D57="","?",IF(D57<1796,"pre-1796",IF(D57<1912,"1796-1911",IF(D57<1949,"1912-1948","1949+")))) -> 1796-1911 | G57: =IF(D57="","?",IF(D57<1912,"Qing",IF(D57<1949,"Republic","PRC"))) -> Qing | H57: 1884 | I57: 閩侯（閩縣・侯官・林森） | J57: 福建省侯官縣 | K57: Government | M57: 林萬利 | N57: 官方政府 | O57: Box 2, Folder 59 | P57: Private deed + state certificate | Q57: 立典田面契 | R57: 光緒拾年 | S57: 林萬利 | U57: 銀折銅錢票捌百伍拾文 | W57: 侯邑西關外草市都井邊亭 | X57: 大狹地中則 | Y57: 田面; 民田 | Z57: 將此應半民田面半; 陳金槐 | AB57: 胞叔昌意 | AD57: 肆 | AI57: 1 | AJ57: 0 | AK57: 1 | AL57: 0 | AM57: 1 | AN57: 1 | AO57: 1 | AP57: 1 | AQ57: 0 | AR57: 0 | AS57: 1 | AT57: 1 | AU57: 1 | AV57: 1 | AW57: 0 | AX57: 0 | AY57: 0 | AZ57: 0 | BA57: 0 | BB57: 0 | BC57: 500 | BD57: 0 | BE57: 0 | BF57: 0 | BG57: https://digital.library.pitt.edu/islandora/object/pitt:31735064607769 | BH57: 立典田面契林萬利原承父在日閩分已份下民田面壺號坐產侯邑西關外草市都井邊亭地方冊載地字式百號土名大狹地中則田民地計官丈叁畝陸厘壺毫壺絲年共再面租穀捌百伍拾畝利父份下應分壺半該應田壺畝伍分叁厘伍絲伍忽應面租穀肆百式拾伍畝納在面主官祿下其糧色立在草市都井甲林志戶下年應完糧銀壺錢式分或厘柒毫迄壺升等合伍勺厯掌收租完課無異今因要用托中友將此應半民田面半號典與官慶為業三議言議本日典出田面價銀壺拾兩正紋廣其銀即日收足其田面所從買主前去完課收租管業面納肆年為限俟至限滿之日听備價照契面銀兩每兩銀折銅錢票捌百伍拾文算贖回如未取贖仍听照舊管業倘有奉官役稅應用費銀若干利贖回之日起認還贖田日期定冬至內向贖冬至外不得言說但此田面係利承父閩分份下物業與別房伯叔兄弟侄無干亦未曾重張典當他人財物以及未歷不明各等情如有此情係利自出頭承當不涉買主之事兩相允愿各無及悔今欲有憑立典田面契已紙併繳楊鵬超撥繳典契壺紙稅司單壺紙共成契紙統付為憑外再蔡世端盡契壺紙再者其上手原契並此契經已半號別業相連及若未便繳付內塗講字字註面字二字共成式字壺統標光緒拾年拾月吉日立典田契林萬利啓在見胞叔昌意堂兄萬斌大張堂兄萬順堂侄可良中人陳金槐自筆萬利啓
A58: 31735064607777_001 | B58: 31735064607777 | C58: 1 | D58: 1924 | E58: 1924 | F58: =IF(D58="","?",IF(D58<1796,"pre-1796",IF(D58<1912,"1796-1911",IF(D58<1949,"1912-1948","1949+")))) -> 1912-1948 | G58: =IF(D58="","?",IF(D58<1912,"Qing",IF(D58<1949,"Republic","PRC"))) -> Republic | H58: 1924 | K58: Personal | M58: 林久興 | 林可鑒 | 林久澍 | O58: Box 3, Folder 120 | P58: Private deed | Q58: 立合約 | R58: 光緒十 七年; 光緒十七年; 民國拾叁年 | U58: 伏伍拾元 | V58: 台伏 | AA58: 王子文 | AC58: 母 楊氏; 祖母楊氏; 母楊氏 | AI58: 0 | AJ58: 0 | AK58: 0 | AL58: 0 | AM58: 0 | AN58: 0 | AO58: 0 | AP58: 0 | AQ58: 0 | AR58: 1 | AS58: 1 | AT58: 0 | AU58: 1 | AV58: 0 | AW58: 0 | AX58: 0 | AY58: 0 | AZ58: 0 | BA58: 0 | BB58: 0 | BC58: 401 | BD58: 0 | BE58: 0 | BF58: 0 | BG58: https://digital.library.pitt.edu/islandora/object/pitt:31735064607777 | BH58: 立合約字林可鑑久興諱萬開公興諱萬拱公鑑父諱萬欽公三人同胞兄弟所有產業於光緒十七年閏八月分為福祿壽三房各執閩書一本為据謝生父可瓊係祖父萬開公長子謝係庶出彼時父納謝生母時另居別處謝生週歲謝生母出經謝祖母謝父可瓊及親族伯叔兄弟等力劝謝嫡母楊氏將謝領回由祖母楊氏暨嫡母楊氏躬親撫養謝已十有六歲行將完娶族戚等又以興年已成人理宜娶室劝謝認助台伏厝百或拾元次房可昌另認台伏伍拾元三房可鑑另認台伏伍拾元以為興完娶之用約定謝認助之款俟本年舊曆十二月底合清付興收至所有各房產業暨光緒十七年八月間閩書閩分份下各管各業所憑自由買賣不得別生枝節兩相允愿各勿反悔今欵有憑立約字畫紙為照內塗銷合字(字又添註憑字)字標照謝長房謝嫡母楊氏久謝厝次房可昌可第厝久興厝久年厝三房可鑑厝鄉族長萬順厝族人萬棋可杯厝可為厝可建可泉懿戚王友增厝李茂炳厝厝公親劉慶雲厝陳仲良厝經陳其清厝厝陳依銘厝族鄰可釵厝久信厝民國拾叁年叁月初日立公約字代筆王子文厝
A59: 31735064607785_001 | B59: 31735064607785 | C59: 1 | D59: 1875 | E59: 1875 | F59: =IF(D59="","?",IF(D59<1796,"pre-1796",IF(D59<1912,"1796-1911",IF(D59<1949,"1912-1948","1949+")))) -> 1796-1911 | G59: =IF(D59="","?",IF(D59<1912,"Qing",IF(D59<1949,"Republic","PRC"))) -> Qing | H59: 1875 | I59: 閩侯（閩縣・侯官・林森） | J59: 福建省閩侯縣 | K59: Government | M59: 林應香 | N59: 林萬開 | O59: Box 2, Folder 54 | P59: Other / fragment | Y59: 民田; 田面 | Z59: 陳香雪 | AA59: 方零捌千; 吳祥麟 | AI59: 1 | AJ59: 0 | AK59: 1 | AL59: 0 | AM59: 0 | AN59: 0 | AO59: 1 | AP59: 0 | AQ59: 1 | AR59: 0 | AS59: 1 | AT59: 0 | AU59: 0 | AV59: 0 | AW59: 0 | AX59: 0 | AY59: 0 | AZ59: 0 | BA59: 0 | BB59: 0 | BC59: 370 | BD59: 0 | BE59: 0 | BF59: 0 | BG59: https://digital.library.pitt.edu/islandora/object/pitt:31735064607785 | BH59: 四版五卷斷奏林應香有手印根面全民田穀雙游侯邑西閣外草市都馬坑地方王名馬路下冊載地字四區卷百貳拾捌號官文隆分式屋又卷百叁拾捌號官文卷分案屋八毛此物鋪大小式拉田頭鹽仔畫口園仔畫塊又畫拉土名井嘴冊載地字四區卷百肆拾柒號官文重啟卷分貳屋八忽以上三號共計官文貳啟卷分貳屋五毛八忽其糧色立立草市都中甲巡和例科此免納應官各具今因要用托中將此招面全民田實彭典族名萬開承道為案三而議定實彭田實代書方零捌千文即收之其田輕永遠實業完課自實彭之源永萬能不敢別生枝節以此田係香手置其人各平六各重持也當倘有香歷不所均香承當典各涉物愿各悔今欲有見香彭英承派並微楊能慶原曲為強根英承紙彭英承陳朝科原典井嘴根英承派畫彭英承派德鉉原彭田面德英承派共成承派統付為憑光緒元年拾月五卷斷奏林應香五卷斷奏林應香五卷斷奏林應香中人陳香雪代筆吳祥麟書彭英承派增廿九西湖區802401404
A60: 31735064607793_001 | B60: 31735064607793 | C60: 1 | D60: 1893 | E60: 1893 | F60: =IF(D60="","?",IF(D60<1796,"pre-1796",IF(D60<1912,"1796-1911",IF(D60<1949,"1912-1948","1949+")))) -> 1796-1911 | G60: =IF(D60="","?",IF(D60<1912,"Qing",IF(D60<1949,"Republic","PRC"))) -> Qing | H60: 1893 | I60: 閩侯（閩縣・侯官・林森） | J60: 福建省閩侯縣 | K60: Government | M60: 王兆熙出租 | N60: 林 | O60: Box 2, Folder 76 | P60: Private deed + state certificate | Q60: 立典田面契 | R60: 光緒拾玖年 | S60: 王兆熙 | U60: 錢捌百五十文 | W60: 侯邑西關外叁十方 | Y60: 田面 | Z60: 堂弟兆熙 | AA60: 王兆裕 | AB60: 胞兄兆 | AC60: 母黃氏 | AI60: 0 | AJ60: 0 | AK60: 0 | AL60: 0 | AM60: 1 | AN60: 0 | AO60: 0 | AP60: 1 | AQ60: 0 | AR60: 0 | AS60: 1 | AT60: 0 | AU60: 0 | AV60: 1 | AW60: 0 | AX60: 0 | AY60: 0 | AZ60: 0 | BA60: 0 | BB60: 0 | BC60: 335 | BD60: 0 | BE60: 0 | BF60: 0 | BG60: https://digital.library.pitt.edu/islandora/object/pitt:31735064607793 | BH60: 立典田面契分下田面八都白龍計則田面區號年其糧色立享貞戶下因要用自林處為業銀叁拾壹田面所從其糧色照面約原主面銀兩每取贖如未田面係照與視疎伯當他人財照自己出愿各無翻低為照大王兆熙承祖遺分自己坐落侯邑西關外叁十方土名鯽魚坵等坵分零冊載字三番五甲王租穀叁百伍拾斤出田面價其銀即日足其會田日租壹派過甲入戶完納不拘年限所憑照契本錢捌百五十文其照舊業但此自已份下物業無干亦未曾典買主無涉一而和允知契母黃氏再上手原契別業相連未便做付倘奉官投稅贖契言所有稅耗若干一起算還重統標整改大壹字光緒拾玖年四月吉日立典契王兆熙在見胞兄兆榮啓中見堂弟兆熙代筆王兆裕大清光緒拾玖年四月吉日立典契王兆熙大清光緒拾玖年四月吉日立典契王兆熙大清光緒拾玖年四月吉日立典契王兆熙大清光緒拾玖年四月吉日立典契王兆熙
A61: 31735064607801_001 | B61: 31735064607801 | C61: 1 | D61: 1881 | E61: 1881 | F61: =IF(D61="","?",IF(D61<1796,"pre-1796",IF(D61<1912,"1796-1911",IF(D61<1949,"1912-1948","1949+")))) -> 1796-1911 | G61: =IF(D61="","?",IF(D61<1912,"Qing",IF(D61<1949,"Republic","PRC"))) -> Qing | H61: 1881 | I61: 閩侯（閩縣・侯官・林森） | J61: 福建省閩侯縣 | K61: Government | M61: 林春發 | N61: 林萬開 | O61: Box 2, Folder 57 | P61: Private deed | Q61: 立賣斷契 | S61: 林春發 | U61: 價錢壹百壹拾千文 | W61: 侯邑西關外白龍壇路 | X61: 鰐魚坵牛頭長坵等大 | Y61: 民田; 田根 | Z61: 楊宗盛 | AB61: 弟春輝 | AI61: 1 | AJ61: 0 | AK61: 1 | AL61: 1 | AM61: 1 | AN61: 1 | AO61: 1 | AP61: 0 | AQ61: 1 | AR61: 1 | AS61: 1 | AT61: 1 | AU61: 1 | AV61: 0 | AW61: 0 | AX61: 0 | AY61: 0 | AZ61: 0 | BA61: 0 | BB61: 0 | BC61: 278 | BD61: 0 | BE61: 0 | BF61: 0 | BG61: https://digital.library.pitt.edu/islandora/object/pitt:31735064607801 | BH61: 立賣斷林春發有手置民田根數號坐落侯邑西關外白龍壇路地方土名鰐魚坵牛頭長坵等大山三坵池壹口共四坵計官丈式畝五分零年納面主王家早晚租谷叁百五十觔平秤歷中無異今因要用托中將此田根一統賣斷與族叔萬開承遠為業三面言議賣斷田根價錢壹百壹拾千文即日收足其田根聽叔永遠為業發自賣斷之後永斷萬籐不敢別生枝節但此田根係發手置與親疎房伯叔兄弟侄無干亦無重張與當他人財物如有來歷不明均發承當與叔無涉而相允愿各無反悔今欲有憑立賣斷契壹紙並繳楊必通原由根契壹紙楊能鋒畫斷契三紙統付為憑內註契字一字標照楊立賣斷契尤儲系平拾貳月日立賣斷根契林春發楊在見弟春輝中人楊宗盛楊日立賣斷楊立賣斷契
A62: 31735064607819_001 | B62: 31735064607819 | C62: 1 | D62: 1894 | E62: 1894 | F62: =IF(D62="","?",IF(D62<1796,"pre-1796",IF(D62<1912,"1796-1911",IF(D62<1949,"1912-1948","1949+")))) -> 1796-1911 | G62: =IF(D62="","?",IF(D62<1912,"Qing",IF(D62<1949,"Republic","PRC"))) -> Qing | H62: 1894 | I62: 閩侯（閩縣・侯官・林森） | J62: 福建省閩侯縣 | K62: Government | M62: 王兆熙 | N62: 林 | O62: Box 2, Folder 78 | P62: Other / fragment | Q62: 立約 | R62: 光緒貳拾年 | S62: 王兆熙 | T62: 本鄉林 | Y62: 田面 | AA62: 王瑞臣 | AI62: 0 | AJ62: 0 | AK62: 0 | AL62: 0 | AM62: 0 | AN62: 0 | AO62: 0 | AP62: 0 | AQ62: 0 | AR62: 0 | AS62: 1 | AT62: 0 | AU62: 0 | AV62: 1 | AW62: 0 | AX62: 0 | AY62: 0 | AZ62: 0 | BA62: 0 | BB62: 0 | BC62: 172 | BD62: 0 | BE62: 0 | BF62: 0 | BG62: https://digital.library.pitt.edu/islandora/object/pitt:31735064607819 | BH62: 此內字王兆熙緣有承祖青圖分自己份下田面教歸生首侯邑三十，都白龍坑地方士名鄭真伍甘故年內祖及卷百伍拾斤加，鄭平祥熙因別置將此田面賣與與本鄉林處為業其區歸糧邑祖手多業相連未曾分別清楚而得通年林家貼納照完糧餉伍百文俟照查明直歸耕邑與林家概回完納不得推諉今數有憑立約字垂納付收為憑立約人光緒貳拾年十二月吉日立約字王兆熙在兒胞兄兆清中兄叔祖醉登代筆王瑞臣
A63: 31735064607827_001 | B63: 31735064607827 | C63: 1 | D63: 1894 | E63: 1894 | F63: =IF(D63="","?",IF(D63<1796,"pre-1796",IF(D63<1912,"1796-1911",IF(D63<1949,"1912-1948","1949+")))) -> 1796-1911 | G63: =IF(D63="","?",IF(D63<1912,"Qing",IF(D63<1949,"Republic","PRC"))) -> Qing | H63: 1894 | I63: 閩侯（閩縣・侯官・林森） | J63: 福建省閩侯縣 | K63: Government | M63: 王兆熙 | N63: 林 | O63: Box 2, Folder 77 | P63: Private deed + state certificate | Q63: 立湊斷契 | R63: 光緒二十年 | S63: 王兆熙 | Y63: 田面 | Z63: 叔祖附登簿 | AA63: 王瑞臣 | AB63: 胞兄兆榮 | AC63: 母黃氏 | AI63: 1 | AJ63: 1 | AK63: 1 | AL63: 1 | AM63: 1 | AN63: 0 | AO63: 0 | AP63: 0 | AQ63: 1 | AR63: 1 | AS63: 1 | AT63: 0 | AU63: 0 | AV63: 1 | AW63: 0 | AX63: 0 | AY63: 0 | AZ63: 0 | BA63: 0 | BB63: 0 | BC63: 229 | BD63: 0 | BE63: 0 | BF63: 0 | BG63: https://digital.library.pitt.edu/islandora/object/pitt:31735064607827 | BH63: 立湊斷契王兆熙原有承祖遺圖自己佔下田面數驛生落侯邑西周外三十八都白龍垌路地方土名鯽魚坵昔計官丈少畝伍分零其糧色租款俱係在原典內明白今因乏用自情愿托中湊斷與本鄉林處永遠為業三面言據本日湊斷出田面價錢式千文公其錢即日收足其田面所湊林家永遠營業但照自湊斷之後價只心願永斷葛藤永不得別生枝節兩相允應各勿反悔今款有憑立湊斷契壹紙付執永遠為憑關侯縣西門區稅局清查驗記知契母黃氏光緒二十年十二月吉日立湊斷契王兆熙清在見胞兄兆榮中見叔祖附登簿代筆王瑞臣等光緒關侯縣西門區稅局
A64: 31735064607835_001 | B64: 31735064607835 | C64: 1 | D64: 1866 | E64: 1871 | F64: =IF(D64="","?",IF(D64<1796,"pre-1796",IF(D64<1912,"1796-1911",IF(D64<1949,"1912-1948","1949+")))) -> 1796-1911 | G64: =IF(D64="","?",IF(D64<1912,"Qing",IF(D64<1949,"Republic","PRC"))) -> Qing | H64: 1866/1871 | I64: 閩侯（閩縣・侯官・林森） | J64: 福建省侯官縣 | K64: Government | M64: 楊鵬超出租 | N64: 林 | O64: Box 1, Folder 42 | P64: Official form | Q64: 立撥繳曲郭壺為照面約 | R64: 同治伍年 | T64: 林 | U64: 價銀貳拾玖兩; 銀折錢壹伍拾文 | W64: 候邑西閭外草上市都井邊亭 | X64: 大秧地中則 | Y64: 民田; 田面 | Z64: 林萬開 | AA64: 堂伯敦 | AB64: 胞伯敦志 | AC64: 母郭氏 | AD64: 陸 | AI64: 1 | AJ64: 0 | AK64: 0 | AL64: 1 | AM64: 1 | AN64: 1 | AO64: 1 | AP64: 1 | AQ64: 0 | AR64: 1 | AS64: 1 | AT64: 0 | AU64: 0 | AV64: 1 | AW64: 0 | AX64: 0 | AY64: 0 | AZ64: 0 | BA64: 0 | BB64: 0 | BC64: 461 | BD64: 0 | BE64: 0 | BF64: 0 | BG64: https://digital.library.pitt.edu/islandora/object/pitt:31735064607835 | BH64: 立撥繳曲郭楊鵬超承祖在日手置閭分嗣父份下有民田面壺號坐產候邑西閭外草上市都井邊亭地方冊再地字戈百號土名大秧地中則田民池計官丈叁畝陸重壺壹壺系年共再面租穀捌百伍拾畝內將撥出壺半嗣父份下應田壺畝伍分叁厘零伍系伍忽應面租穀肆百貳拾伍畝佃林昌志其糧邑立在草市都柴申楊紹標戶下年應完糧銀壺貳分貳厘柒毫色米壺升柒合伍勺歷掌收租完課無異今因乏用愿將撥出閭分嗣父份下此半號民田面繳曲與林處為業三面言議本日得訖田價銀貳拾玖兩柒錢伍分正紋廣其銀即日收足其田面即聽林家前去會佃收租管業其糧邑聽信照縣例科派過甲入戶完佃面約陸年為限俟至限滿之日聽超備價照契面銀兩取贖如未取贖仍聽照舊掌業倘原主取贖不拘年限但此田係超承祖手置閭分嗣父份下物業與別房親疎伯叔兄弟侄無干亦未嘗重張曲掛他人財物如有來磨不明等情係超出須抵當不涉林家之事兩家允愿各無翻悔今欵有憑立撥繳曲郭壺為照面約贖田之日每兩銀折錢壹伍拾文再傳道例收稅其稅銀若干贖田一起還還其原界更利半號交半難以繳付統標照知郭祖妣薛氏嗣母郭氏同治伍年肆月吉日立撥繳曲郭楊鵬超在見胞伯敦志中友林萬開代筆堂伯敦大龍
A65: 31735064607835_002 | B65: 31735064607835 | C65: 2 | D65: 1866 | E65: 1871 | F65: =IF(D65="","?",IF(D65<1796,"pre-1796",IF(D65<1912,"1796-1911",IF(D65<1949,"1912-1948","1949+")))) -> 1796-1911 | G65: =IF(D65="","?",IF(D65<1912,"Qing",IF(D65<1949,"Republic","PRC"))) -> Qing | H65: 1866/1871 | I65: 閩侯（閩縣・侯官・林森） | J65: 福建省侯官縣 | K65: Government | M65: 楊鵬超出租 | N65: 林 | O65: Box 1, Folder 42 | P65: Other / fragment | AI65: 0 | AJ65: 0 | AK65: 0 | AL65: 0 | AM65: 0 | AN65: 0 | AO65: 0 | AP65: 0 | AQ65: 0 | AR65: 0 | AS65: 0 | AT65: 0 | AU65: 0 | AV65: 0 | AW65: 0 | AX65: 0 | AY65: 0 | AZ65: 0 | BA65: 0 | BB65: 0 | BC65: 58 | BD65: 0 | BE65: 0 | BF65: 0 | BG65: https://digital.library.pitt.edu/islandora/object/pitt:31735064607835 | BH65: 勢福建等處官布收買市場時吉吉吉吉吉吉吉吉吉吉吉吉吉吉吉吉吉吉吉吉吉吉吉吉吉吉吉吉吉吉吉吉吉吉吉吉吉吉吉吉吉吉吉吉吉吉
A66: 31735064607843_001 | B66: 31735064607843 | C66: 1 | D66: 1805 | E66: 1805 | F66: =IF(D66="","?",IF(D66<1796,"pre-1796",IF(D66<1912,"1796-1911",IF(D66<1949,"1912-1948","1949+")))) -> 1796-1911 | G66: =IF(D66="","?",IF(D66<1912,"Qing",IF(D66<1949,"Republic","PRC"))) -> Qing | H66: 1805 | I66: 閩侯（閩縣・侯官・林森） | J66: 福建省侯官縣 | K66: Government | M66: 趙守藻 | N66: 林 | O66: Box 1, Folder 14 | P66: Private deed + state certificate | Q66: 立轉典契 | R66: 嘉慶拾年; 嘉慶 拾年 | S66: 趙守藻 | U66: 價銀壹拾肆兩 | Y66: 民田 | Z66: 友楊海武 | AA66: 林標人鑒 | AD66: 參 | AF66: 防西湖區驗稅局 | AI66: 1 | AJ66: 0 | AK66: 0 | AL66: 0 | AM66: 1 | AN66: 1 | AO66: 1 | AP66: 1 | AQ66: 0 | AR66: 1 | AS66: 1 | AT66: 1 | AU66: 1 | AV66: 0 | AW66: 0 | AX66: 0 | AY66: 0 | AZ66: 0 | BA66: 0 | BB66: 0 | BC66: 438 | BD66: 0 | BE66: 0 | BF66: 0 | BG66: https://digital.library.pitt.edu/islandora/object/pitt:31735064607843 | BH66: 驗林立轉典契趙守藻于嘉慶拾年肆月向買得陶天翰民田面數號生產侯官縣草市都馬坑地方土名坑口佃林有棟耕作逐年載早晚祖谷壺各給酌乾淨祖孫送家交納其卦色掛在草市都五甲陶孔鑣名下應糧除分伍厘色奉升歷年收租等異今因別用林中結典典處為業三向言議者日得記價銀壹拾肆兩止其銀即日收足其田即聽銀主前去會佃收租其銀色照縣例料派過割入戶了納糧色之約參年為限俟限滿之日聽備價照契面銀兩每兩折鈔捌伍拾文美取贖銀主不得抵買未取贖仍聽管業倘限內原主取贖听其贖回此田係藻手置業典別房伯叔兄弟侄等并未曾重張典當他人財物如有未歷不明係藻出頭承當典銀主等向家允愿各各反悔今欲有舊主轉典契壹紙併繳原典壹紙共貳紙統付為憑併閱君良原契壹紙再為憑計開田號畝數內改藻字壹字再為憑一田第一區地字五萬八十六號土名塔下則國丈捌厘柳家園八箇田五萬八十七號土名塔下則國丈叁分叁毫柒絲伍忽五萬八十八號土名荒地下則地貳分貳厘叁毫柒絲伍忽五萬八十九號土名坑裡下則國丈伍厘防西湖區驗稅局嘉慶拾年伍月紅印去三結典契趙守藻中見友楊海武代筆林標人鑒大道
A67: 31735064607850_001 | B67: 31735064607850 | C67: 1 | D67: 1817 | E67: 1817 | F67: =IF(D67="","?",IF(D67<1796,"pre-1796",IF(D67<1912,"1796-1911",IF(D67<1949,"1912-1948","1949+")))) -> 1796-1911 | G67: =IF(D67="","?",IF(D67<1912,"Qing",IF(D67<1949,"Republic","PRC"))) -> Qing | H67: 1817 | I67: 閩侯（閩縣・侯官・林森） | J67: 福建省侯官縣 | K67: Government | M67: 趙守藻 | N67: 林有柱 | O67: Box 1, Folder 19 | P67: Official form | R67: 乾隆十五年; 嘉慶貳拾貳年 | W67: 布宇員萬樹一樹拾叁號有給侯官縣業 | AG67: 林有柱准 | AI67: 0 | AJ67: 0 | AK67: 0 | AL67: 0 | AM67: 0 | AN67: 0 | AO67: 0 | AP67: 0 | AQ67: 0 | AR67: 0 | AS67: 0 | AT67: 0 | AU67: 0 | AV67: 0 | AW67: 0 | AX67: 1 | AY67: 0 | AZ67: 0 | BA67: 0 | BB67: 0 | BC67: 197 | BD67: 5 | BE67: 2 | BF67: 0 | BG67: https://digital.library.pitt.edu/islandora/object/pitt:31735064607850 | BH67: 久樹尾契存上日議奏事乾隆十五年正月二十四日奉准...旨依議欽此相應抄錄原奏并頒發格式行文...奏稱部議多頒契尾以後仍取病民綠業尾例不與照根同上司查驗不肯有司其與給民契尾則按數登填而于存...府州查發并知府直隸州照例發給...命下之日臣部頒發格式通行各省無一違辦理可也等因咨院行司奉此...計開謹將林有柱實著守遷田書契坐落布宇員萬樹一樹拾叁號有給侯官縣業戶林有柱准嘉慶貳拾貳年貳月嘉慶貳拾貳年貳月
A68: 31735064607868_001 | B68: 31735064607868 | C68: 1 | D68: 1850 | E68: 1850 | F68: =IF(D68="","?",IF(D68<1796,"pre-1796",IF(D68<1912,"1796-1911",IF(D68<1949,"1912-1948","1949+")))) -> 1796-1911 | G68: =IF(D68="","?",IF(D68<1912,"Qing",IF(D68<1949,"Republic","PRC"))) -> Qing | H68: 1850 | I68: 閩侯（閩縣・侯官・林森） | J68: 福建省侯官縣 | K68: Personal | M68: 林世奕 | N68: 林 | O68: Box 1, Folder 33 | P68: Private deed | Q68: 立賣田根契 | R68: 道光叁拾年 | S68: 林世奕 | W68: 候邑三十八都白龍洋 | Y68: 田根; 民田 | Z68: 翁太湖 | AA68: 王鳳鳴 | AB68: 胞兄世 | AC68: 母蕭氏 | AD68: 伍 | AI68: 1 | AJ68: 1 | AK68: 1 | AL68: 1 | AM68: 1 | AN68: 1 | AO68: 1 | AP68: 1 | AQ68: 0 | AR68: 1 | AS68: 1 | AT68: 1 | AU68: 0 | AV68: 1 | AW68: 0 | AX68: 0 | AY68: 0 | AZ68: 0 | BA68: 0 | BB68: 0 | BC68: 347 | BD68: 0 | BE68: 0 | BF68: 0 | BG68: https://digital.library.pitt.edu/islandora/object/pitt:31735064607868 | BH68: 立賣田根契林世奕承父陶分份下有民田根壹號大小伍坵坐產候邑三十八都白龍洋地方土名園坵計官丈式畝零年載租谷叁百式拾肆畝平秤納在周家更有壹號土名深田計官丈壹畝伍分年載禾租谷壹百式拾畝平秤納在面主李家歷年掌管無異今因要用情愿托中將此田統賣與林虜為業三面言議本日賣出田根價銀式百兩正平戥九七色其銀即日收足其田聽從買主前去翻犁耕作了納面租掌管為業奕不得言說但此田根面約伍年為限俟至限滿之日所從奕倍價照契面銀兩取贖賣主不得阻番如未取贖仍聽官業其田係奕承父陶分份下物業與本別房伯叔兄弟侄無干亦未曾重張典當他人財物如有未悉不明等情係奕出頭承當不涉買主之事兩家允愿各無反悔今敢有憑立賣契壹紙為照又繳原契壹紙共成式紙統付再照知契母蕭氏道光叁拾年玖月吉日立賣田根契林世奕德在見胞兄世美商胞弟世廷中人翁太湖代筆王鳳鳴大熟
A69: 31735064607876_001 | B69: 31735064607876 | C69: 1 | D69: 1888 | E69: 1888 | F69: =IF(D69="","?",IF(D69<1796,"pre-1796",IF(D69<1912,"1796-1911",IF(D69<1949,"1912-1948","1949+")))) -> 1796-1911 | G69: =IF(D69="","?",IF(D69<1912,"Qing",IF(D69<1949,"Republic","PRC"))) -> Qing | H69: 1888 | I69: 閩侯（閩縣・侯官・林森） | J69: 福建省侯官縣 | K69: Government | M69: 林萬開 | N69: 林秋溥 | O69: Box 2, Folder 67 | P69: Official form | AI69: 0 | AJ69: 0 | AK69: 0 | AL69: 0 | AM69: 0 | AN69: 0 | AO69: 0 | AP69: 0 | AQ69: 0 | AR69: 0 | AS69: 0 | AT69: 0 | AU69: 0 | AV69: 0 | AW69: 0 | AX69: 0 | AY69: 0 | AZ69: 0 | BA69: 0 | BB69: 0 | BC69: 118 | BD69: 1 | BE69: 1 | BF69: 0 | BG69: https://digital.library.pitt.edu/islandora/object/pitt:31735064607876 | BH69: 契侯官陸萬卷拾陸毛光緒拾叁拾壹月三三二木萬卷木次庫功三三二木萬卷木次庫功陸萬卷拾陸侯官給侯官林萬開准此福建等處廣置布政使司...印行府州送府州清冊...查照...稅務...契稅...銀錢...林萬開...陸萬卷...侯官...光緒...
A70: 31735064607884_001 | B70: 31735064607884 | C70: 1 | D70: 1913 | E70: 1913 | F70: =IF(D70="","?",IF(D70<1796,"pre-1796",IF(D70<1912,"1796-1911",IF(D70<1949,"1912-1948","1949+")))) -> 1912-1948 | G70: =IF(D70="","?",IF(D70<1912,"Qing",IF(D70<1949,"Republic","PRC"))) -> Republic | H70: 1913 | I70: 閩侯（閩縣・侯官・林森） | J70: 福建省侯官縣 | K70: Government | L70: 林有柱 | N70: 趙守藻 | O70: Box 2, Folder 96 | P70: Official form | Q70: 立之不動產舊契 | R70: 嘉慶拾年; 中華民國 拾壹年 | U70: 價銀拾肆兩; 銀貳拾元 | W70: 閩侯縣草市都馬坑 | Y70: 田面 | AE70: 典 按 契 單 | 福建國稅廳籌備處 | AF70: 福建國稅廳籌備處 | AG70: 林有柱 | AH70: 驗字第萬五七五十二號 | AI70: 0 | AJ70: 0 | AK70: 0 | AL70: 0 | AM70: 0 | AN70: 0 | AO70: 0 | AP70: 0 | AQ70: 0 | AR70: 0 | AS70: 1 | AT70: 0 | AU70: 0 | AV70: 0 | AW70: 0 | AX70: 1 | AY70: 1 | AZ70: 1 | BA70: 1 | BB70: 1 | BC70: 340 | BD70: 0 | BE70: 0 | BF70: 0 | BG70: https://digital.library.pitt.edu/islandora/object/pitt:31735064607884 | BH70: 典按契單福建國稅廳籌備處給發契單事案奉財政部電行劃一契紙章程內開本章程施行以前成立之不動產舊契無論已稅契未稅契均應一律限期呈驗逾限不呈驗者於訴訟時不能作為憑據一併函知司法機關認真辦理以為匿驗者戒等因奉此當經擬定分別徵收方法已稅之舊契每張收紙價壹元未稅之舊契每產價百元收紙價壹元其光復後新契已稅者不收紙價酌定正限三個月餘限兩個月逾期呈驗者分別加徵嚴罰經已電奉財政部核准照辦並通飭遵照在案今據閩侯縣業戶林有柱於清嘉慶拾年伍月日典受趙華藻田面租谷壹百柒拾斤坐落閩侯縣草市都馬坑地方東至西至北至坐向橫丈尺直丈尺中證楊海武原價銀拾肆兩中銀貳拾元原契已稅遵章依限呈驗應納紙價業已如數收訖合填契單粘連原契印給收執管業須至契單者右給業戶林有柱准此中華民國拾壹年拾壹月叁拾日給驗字第萬五七五十二號為
A71: 31735066237334_001 | B71: 31735066237334 | C71: 1 | D71: 1784 | E71: 1830 | F71: =IF(D71="","?",IF(D71<1796,"pre-1796",IF(D71<1912,"1796-1911",IF(D71<1949,"1912-1948","1949+")))) -> pre-1796 | G71: =IF(D71="","?",IF(D71<1912,"Qing",IF(D71<1949,"Republic","PRC"))) -> Qing | H71: 1784/1830 | I71: 古田 | J71: 福建省古田縣 | K71: Government | L71: 黃鴻吉 | M71: 熊長生 | N71: 熊亨讀 | O71: Box 1, Folder 8 | P71: Private deed | Q71: 立賣契 | R71: 乾隆肆拾玖年 | S71: 熊長生露 | U71: 價銀壹拾玖兩; 錢捌百文正 | W71: 本處 | Y71: 民田 | Z71: 鄭成富 | AI71: 1 | AJ71: 1 | AK71: 1 | AL71: 1 | AM71: 1 | AN71: 1 | AO71: 1 | AP71: 0 | AQ71: 0 | AR71: 1 | AS71: 1 | AT71: 0 | AU71: 0 | AV71: 0 | AW71: 0 | AX71: 0 | AY71: 0 | AZ71: 0 | BA71: 0 | BB71: 0 | BC71: 295 | BD71: 0 | BE71: 0 | BF71: 0 | BG71: https://digital.library.pitt.edu/islandora/object/pitt:31735066237334 | BH71: 立賣契人熊長生同侄亨倫等鄉今因無錢應用自甘情愿即將已置有民田壹號坐址本處土名俗呼門首亭下大坂受種壹拾伍石正該糧壹畝壹分貳厘伍毫正其田叁年以房肆年當收托中送賣本晉堂侄亨讀處入首承買為業即日同中三面言議時值價銀壹拾玖兩廣正每兩的錢捌百文正即日收訖其田隨手退典讀晉業召佃中間明賣明買並無相貪俾俟等情亦未曾重張典掛外財物倘有未歷不明係是生出頭抵當不涉讀主之事其田自賣之後面約五拾叁年條價贖回不得刁難若是無力之日典買主管耕作其卦俟至大造之年推入讀戶內不必多推少收兩家甘允各無異言今啟有憑敬立契已紙付典讀為昭者乾隆肆拾玖年拾貳月日立賣契人熊長生露同侄人熊亨倫熊亨鄉為中人鄭成富在見人熊元廷嘉七第人張秉禮
A72: 31735066237334_002 | B72: 31735066237334 | C72: 2 | D72: 1784 | E72: 1830 | F72: =IF(D72="","?",IF(D72<1796,"pre-1796",IF(D72<1912,"1796-1911",IF(D72<1949,"1912-1948","1949+")))) -> pre-1796 | G72: =IF(D72="","?",IF(D72<1912,"Qing",IF(D72<1949,"Republic","PRC"))) -> Qing | H72: 1784/1830 | I72: 古田 | J72: 福建省古田縣 | K72: Government | L72: 黃鴻吉 | M72: 熊長生 | N72: 熊亨讀 | O72: Box 1, Folder 8 | P72: Official form | R72: 道光拾年 | AI72: 0 | AJ72: 0 | AK72: 0 | AL72: 0 | AM72: 0 | AN72: 0 | AO72: 0 | AP72: 0 | AQ72: 0 | AR72: 0 | AS72: 0 | AT72: 0 | AU72: 0 | AV72: 0 | AW72: 0 | AX72: 0 | AY72: 0 | AZ72: 0 | BA72: 0 | BB72: 0 | BC72: 162 | BD72: 2 | BE72: 3 | BF72: 0 | BG72: https://digital.library.pitt.edu/islandora/object/pitt:31735066237334 | BH72: 七軍人張秉禮福建督憲咨布政使司旨議奏事...本年十二月十二日奏本日奉旨...印存...奏請...官照...爵印...州經...尾與...之茶...與稅...府州...為...手...收...上...契...部...體...可...此...伍...正...用...正布字貳千玖百貳拾貳號給古臣...黃鴻吉道光拾年拾......
A73: 31735066237342_001 | B73: 31735066237342 | C73: 1 | D73: 1870 | E73: 1907 | F73: =IF(D73="","?",IF(D73<1796,"pre-1796",IF(D73<1912,"1796-1911",IF(D73<1949,"1912-1948","1949+")))) -> 1796-1911 | G73: =IF(D73="","?",IF(D73<1912,"Qing",IF(D73<1949,"Republic","PRC"))) -> Qing | H73: 1870/1907 | I73: 屏南 / 古田 | J73: 福建省屏南縣和古田縣 | K73: Government | L73: 張蘭芬 | M73: 張昌暢 | N73: 張邦昔 | O73: Box 1, Folder 49 | P73: Private deed | Q73: 立典契 | R73: 同治玖年 | S73: 張昌暢 | U73: 價銀貳拾伍兩正 | Y73: 民田 | AI73: 1 | AJ73: 1 | AK73: 1 | AL73: 0 | AM73: 0 | AN73: 0 | AO73: 0 | AP73: 1 | AQ73: 0 | AR73: 1 | AS73: 1 | AT73: 0 | AU73: 0 | AV73: 0 | AW73: 0 | AX73: 0 | AY73: 0 | AZ73: 0 | BA73: 0 | BB73: 0 | BC73: 201 | BD73: 0 | BE73: 0 | BF73: 0 | BG73: https://digital.library.pitt.edu/islandora/object/pitt:31735066237342 | BH73: 立典契張昌暢今因官事無錢使用即將父手闔分已公有民田壹號唯批本處草坂田該糧捌分正其四至上至山下至溪左至大成田右至大成田四至明白歷言無異托中送典邦昔承受為業出價銀貳拾伍兩正契立銀收足訖無掛分厘中間明典明受並無相俾貪等情其田自典之後任昔管業收租其錢糧照契津助完納其年限隨年備價贖回無力者任昔管業收租且暢不敢異言等情中用酒食俱免兩家甘愿各無異言今欲有憑立典契壹紙為照同治玖年五月日吉立典契人張昌暢為中胞孫張大都
A74: 31735066237342_002 | B74: 31735066237342 | C74: 2 | D74: 1870 | E74: 1907 | F74: =IF(D74="","?",IF(D74<1796,"pre-1796",IF(D74<1912,"1796-1911",IF(D74<1949,"1912-1948","1949+")))) -> 1796-1911 | G74: =IF(D74="","?",IF(D74<1912,"Qing",IF(D74<1949,"Republic","PRC"))) -> Qing | H74: 1870/1907 | I74: 屏南 / 古田 | J74: 福建省屏南縣和古田縣 | K74: Government | L74: 張蘭芬 | M74: 張昌暢 | N74: 張邦昔 | O74: Box 1, Folder 49 | P74: Official form | R74: 乾隆一五年 | AF74: 福建等處承宣布政使司 | AG74: 納稅時; 收據後幅 | AI74: 0 | AJ74: 0 | AK74: 0 | AL74: 0 | AM74: 0 | AN74: 0 | AO74: 0 | AP74: 0 | AQ74: 0 | AR74: 0 | AS74: 0 | AT74: 0 | AU74: 0 | AV74: 0 | AW74: 1 | AX74: 1 | AY74: 0 | AZ74: 0 | BA74: 0 | BB74: 0 | BC74: 731 | BD74: 0 | BE74: 0 | BF74: 0 | BG74: https://digital.library.pitt.edu/islandora/object/pitt:31735066237342 | BH74: 為中胞孫張大都福建等處承宣布政使司為選旨議奏事乾隆一五年正月二十四日奉准戶部咨河南司案呈所有本知縣陝西布政使富明條奏買賣田產將契尾備起即行查驗等因一摺下本年十二月十二日奉本日奉旨依議欽此相應抄錄原奏并頒發格式行文福建巡撫欽遵辦理可也其格式一張內開該臣等查得該布政使富明奏稱部議多頒契尾以後巧取病民給業戶契尾例不與照根同申上司查驗不有司其與民契尾則按數登填而于存官照根或將實銀開改請補後州縣於業戶納稅時將契尾粘連用印存貯每遇千號申送知府直隸州查對如姓名銀數相符即將應給業戶之契尾并州縣備案之照根于驗處處裁分列給存其應申藩司照根于季報時府州彙送至知府直隸州經收稅契照州縣之例徑送藩司等語查雜稅與正賦均由州縣造冊該管府州核完納正賦實為縣三司更從未議將契尾由州縣申送府州查驗誠以花戶照票一繳府州則給領無時弊端易起今稅契雜項契尾與照根并送查發是難項吏嚴于止賦殊與政體未協况契尾一項經衙門即多一衙門之停關由一吏胥即多一吏胥之索求甚至查驗為奸徒藉端查以致業戶經年累月求一執照寧家而不可得勢必多方打點需索之費數倍于前將來視稅稅為畏途觀望延緩無庸自製而本縣子國課毫無裨益應將該布政使奏請州縣經收稅銀將契尾粘連存貯十號申送直隸州查驗并知府直隸州照州縣例徑送藩司之處均屬庸妄且以天報小奸民爭執計訟實緣法久弊生不可不量為變通臣等酌議嗣後布政司頒發給民契尾格式編列號及前半幅照常細書業戶等姓名實出房數目價銀稅銀若干後半幅于空白處預鈐司印以備投稅時將契價銀數目大字填寫鈐印之處令業戶看明當面隨字蓋開前幅給業戶收據後幅同季冊彙送布政司查核此係一行筆跡平分為二大小數目委難混換其從前州縣布政司備查各契尾應行停止以省繁文庶契尾無停攔之虞而契價無參差之弊于民無累于稅無虧侵蝕可杜而爭訟可息矣如徐允俊
A75: 31735066237359_001 | B75: 31735066237359 | C75: 1 | D75: 1864 | E75: 1872 | F75: =IF(D75="","?",IF(D75<1796,"pre-1796",IF(D75<1912,"1796-1911",IF(D75<1949,"1912-1948","1949+")))) -> 1796-1911 | G75: =IF(D75="","?",IF(D75<1912,"Qing",IF(D75<1949,"Republic","PRC"))) -> Qing | H75: 1864/1872 | I75: 古田 | J75: 福建省古田縣 | K75: Government | L75: 張利禧 | M75: 鄭嬌姑 | N75: 鄭淳氏 | O75: Box 1, Folder 39 | P75: Private deed | Q75: 立會貽畫契 | R75: 同治伍年; 同治叁年 | S75: 楊門郭嬌 | U75: 價銀伍拾兩正; 銀各兩共銀拾兩文 | Y75: 民田 | AB75: 玄胞弟 | AI75: 0 | AJ75: 0 | AK75: 1 | AL75: 0 | AM75: 0 | AN75: 0 | AO75: 0 | AP75: 1 | AQ75: 0 | AR75: 0 | AS75: 1 | AT75: 0 | AU75: 0 | AV75: 0 | AW75: 0 | AX75: 0 | AY75: 0 | AZ75: 0 | BA75: 0 | BB75: 0 | BC75: 371 | BD75: 0 | BE75: 0 | BF75: 0 | BG75: https://digital.library.pitt.edu/islandora/object/pitt:31735066237359 | BH75: 立會貽畫契楊門郭氏嬌姑認故玄大松有閩分已業民田一號土名東洋及溪井佔所有祖石鐵根供載原典明白不必重叙該田陸氏交出由本族潘士公業潘男大林于下湖林道將該田以契轉售玄胞叔浩士公男大鈞同張氏潘並未張我蔡因大林男成器親親兩鈞互指各在業業潘邑主訊明該田由器點贖世傳謝令氏備價取贖詎器將氏玄手齋案有帶備錢為拾子文呈指追做氏居女流又崇謝氏備做因共指做項仍將該田托中向在夫妻不大鈞靈會貽畫出價銀伍拾兩正其銀各兩共銀拾兩文呈立契之日今中親和足訖不少隻文其田自畫之田便已滿足有贖世貽言同治伍年冬本田仍氏備办原畫價銀一兩取贖限內氏不得取贖限外鈞亦不得做當倘若世贖其田仍鈞以契表覆業耳氏不敢畧言兩允世悔之歎有愧立會貽畫契一帝為照外中用銀壹兩五錢正再照認係謙原契畫畫伍伍帝司伍帝同治叁年叁月日立會貽畫契楊門郭嬌姑知契養仔銀在見玄胞弟大相號為契法功江勸渝中張正平應八字除乾三
A76: 31735066237359_002 | B76: 31735066237359 | C76: 2 | D76: 1864 | E76: 1872 | F76: =IF(D76="","?",IF(D76<1796,"pre-1796",IF(D76<1912,"1796-1911",IF(D76<1949,"1912-1948","1949+")))) -> 1796-1911 | G76: =IF(D76="","?",IF(D76<1912,"Qing",IF(D76<1949,"Republic","PRC"))) -> Qing | H76: 1864/1872 | I76: 古田 | J76: 福建省古田縣 | K76: Government | L76: 張利禧 | M76: 鄭嬌姑 | N76: 鄭淳氏 | O76: Box 1, Folder 39 | P76: Other / fragment | R76: 同治拾壹年 | AG76: 古田縣 | AI76: 0 | AJ76: 0 | AK76: 0 | AL76: 0 | AM76: 0 | AN76: 0 | AO76: 0 | AP76: 0 | AQ76: 0 | AR76: 0 | AS76: 0 | AT76: 0 | AU76: 0 | AV76: 0 | AW76: 0 | AX76: 0 | AY76: 0 | AZ76: 1 | BA76: 0 | BB76: 0 | BC76: 220 | BD76: 3 | BE76: 0 | BF76: 1 | BG76: https://digital.library.pitt.edu/islandora/object/pitt:31735066237359 | BH76: 尾契同治拾壹年冬布字叁千貳百拾肆號右給古田縣朱張利禧捐契'(Verticaltextonthefarrightedge,possiblyadateorasignature.Itreads'乾隆三'(Qianlong3)andothercharacters.Verticaltextontheleftedge,possiblyadateorasignature.Itreads'同治拾壹年冬'(Tongzhi11thyear,Winter).
A77: 31735066237367_001 | B77: 31735066237367 | C77: 1 | D77: 1767 | E77: 1767 | F77: =IF(D77="","?",IF(D77<1796,"pre-1796",IF(D77<1912,"1796-1911",IF(D77<1949,"1912-1948","1949+")))) -> pre-1796 | G77: =IF(D77="","?",IF(D77<1912,"Qing",IF(D77<1949,"Republic","PRC"))) -> Qing | H77: 1767 | I77: 南平 | J77: 福建省南平縣 | K77: Government | M77: 徐幹通 | N77: 熊孫 | O77: Box 1, Folder 6 | P77: Private deed | Q77: 立賣契 | R77: 乾隆叁拾貳年 | S77: 徐幹通 | W77: 土名小溪滌下壠年收畝谷柒羅伍斗實 | AI77: 0 | AJ77: 1 | AK77: 1 | AL77: 1 | AM77: 1 | AN77: 0 | AO77: 0 | AP77: 0 | AQ77: 0 | AR77: 0 | AS77: 1 | AT77: 0 | AU77: 0 | AV77: 0 | AW77: 0 | AX77: 0 | AY77: 0 | AZ77: 0 | BA77: 0 | BB77: 0 | BC77: 314 | BD77: 0 | BE77: 0 | BF77: 0 | BG77: https://digital.library.pitt.edu/islandora/object/pitt:31735066237367 | BH77: 立賣契人徐幹通全侄士厚承祖遺下有畝田一段坐落土名小溪滌下壠年收畝谷柒羅伍斗實載畝柒林伍一于先年文起等共抽出畝谷壹羅捌斗柒林伍一應應孫為業有契存一幹通叔侄自己者一向存畝谷陸斗貳林伍合實載民畝陸合貳自伍抄外有隨田鴨肆隻為因缺少銀物應用情願即將己不畝谷壹鴨托中前去召賣先問房親兄弟人等各不願能已得峽陽應能孫進前承買當日今中三面言議定時值土風案賣得契價收銀貳兩貳錢其銀即日交收足說不欠八厘其畝現存概此二畝三甲徐壬童戶內輸差之情願推出典應完收入峽陽二畝二甲應能茂戶內完糧不得照累其田未之先並不會典掛外人財物亦無准拍之類如作賣者出願底當之事的徐二家元各無收悔之故有憑立賣契為照了乾隆叁拾貳年拾貳月日立賣契人徐幹通+小侄徐士厚啟代字中徐起孫謹
A78: 31735066237375_001 | B78: 31735066237375 | C78: 1 | D78: 1779 | E78: 1779 | F78: =IF(D78="","?",IF(D78<1796,"pre-1796",IF(D78<1912,"1796-1911",IF(D78<1949,"1912-1948","1949+")))) -> pre-1796 | G78: =IF(D78="","?",IF(D78<1912,"Qing",IF(D78<1949,"Republic","PRC"))) -> Qing | H78: 1779 | I78: 閩清 | J78: 福建省閩清縣 | K78: Government | M78: 李有定 | N78: 謝氏 | O78: Box 1, Folder 7 | P78: Private deed | Q78: 立湊字 | R78: 乾隆叁拾壹年; 乾隆四十四年 | W78: 閩清縣陳洋 | Y78: 民田 | AB78: 段章綬 | AI78: 1 | AJ78: 0 | AK78: 0 | AL78: 0 | AM78: 0 | AN78: 0 | AO78: 0 | AP78: 1 | AQ78: 0 | AR78: 0 | AS78: 1 | AT78: 0 | AU78: 0 | AV78: 0 | AW78: 0 | AX78: 0 | AY78: 0 | AZ78: 0 | BA78: 0 | BB78: 0 | BC78: 137 | BD78: 0 | BE78: 0 | BF78: 0 | BG78: https://digital.library.pitt.edu/islandora/object/pitt:31735066237375 | BH78: 立湊字李有定於乾隆叁拾壹年向有民田數號坐落閩清縣陳洋地方祖母手典在謝處其銀兩租額土名俱載在原契內明白今因乏用托友向謝處嗟出價銀貳兩五錢正其田所謝任田管業面約加限叁年俟滿之日所李家備價照原湊契面銀兩贖回謝家不得執留今欲有號立湊字壹字為照乾隆四十四年拾月立湊字李有定在見段章綬簽
A79: 31735066237383_001 | B79: 31735066237383 | C79: 1 | D79: 1872 | E79: 1872 | F79: =IF(D79="","?",IF(D79<1796,"pre-1796",IF(D79<1912,"1796-1911",IF(D79<1949,"1912-1948","1949+")))) -> 1796-1911 | G79: =IF(D79="","?",IF(D79<1912,"Qing",IF(D79<1949,"Republic","PRC"))) -> Qing | H79: 1872 | I79: 古田 | J79: 福建省古田縣 | K79: Government | M79: 陳裔煌 | N79: 鄭璟 | O79: Box 2, Folder 52 | P79: Private deed | Q79: 立典契 | R79: 同治拾壹年 | S79: 陳高煌 | U79: 價銀肆拾柒兩; 銀每兩折錢捌百肆拾文 | W79: 本處 | X79: 俗呼棋盤座談 | Y79: 民田 | Z79: 吳廷接 | AA79: 甘興業 | AB79: 堂兄高森 | AI79: 1 | AJ79: 1 | AK79: 1 | AL79: 1 | AM79: 0 | AN79: 1 | AO79: 1 | AP79: 0 | AQ79: 0 | AR79: 1 | AS79: 1 | AT79: 1 | AU79: 0 | AV79: 0 | AW79: 0 | AX79: 0 | AY79: 0 | AZ79: 0 | BA79: 0 | BB79: 0 | BC79: 317 | BD79: 1 | BE79: 0 | BF79: 0 | BG79: https://digital.library.pitt.edu/islandora/object/pitt:31735066237383 | BH79: 契券立典契陳高煌全弟高輝承祖手有民田壹號坐址本處地方土名俗呼棋盤座談田貳畝伍分正歷年收租管業無異今因無銀應用自情愿托中引在本墩鄭處正璟邊入頭承買收租為業三面言議時值契價銀肆拾柒兩伍錢數廣正其銀立契之日是煌兄弟收訖無少分厘其田隨即退與璟前去收租管業且煌兄弟不敢阻霸異言其田中間並無抑勒亦未曾重掛他財倘有來歷不明是煌出抵不涉璟之事其錢糧逐年照畝津助俟至大造之年推入鄭家戶內歸已完納其限面約伍冬滿足外任煌備办價銀每兩折錢捌百肆拾文算贖回如無力任璟收租管業等情兩兄無悔今欵有憑托立典契壹紙併繳原畫斷契叁紙共肆紙為照今領上項交閱契價銀肆拾柒兩伍錢數廣正同治拾壹年十一月中用酒席俱與再照舊立典契陳高煌全弟全弟高輝在見堂兄高森中人吳廷接代筆甘興業壽
A80: 31735066237391_001 | B80: 31735066237391 | C80: 1 | D80: 1869 | E80: 1869 | F80: =IF(D80="","?",IF(D80<1796,"pre-1796",IF(D80<1912,"1796-1911",IF(D80<1949,"1912-1948","1949+")))) -> 1796-1911 | G80: =IF(D80="","?",IF(D80<1912,"Qing",IF(D80<1949,"Republic","PRC"))) -> Qing | H80: 1869 | I80: 屏南 | J80: 福建省屏南縣 | K80: Government | M80: 輝煌 | N80: 蘇坐標 | O80: Box 1, Folder 46 | P80: Other / fragment | Q80: 立直根批 | R80: 同治八年 | S80: 一紙為照 | U80: 價伐肆拾壺千陸百文正 | Y80: 民田 | Z80: 宗弟士治 | AB80: 出嗣弟輝灼 | AI80: 1 | AJ80: 0 | AK80: 1 | AL80: 0 | AM80: 1 | AN80: 1 | AO80: 1 | AP80: 0 | AQ80: 1 | AR80: 0 | AS80: 1 | AT80: 0 | AU80: 0 | AV80: 0 | AW80: 0 | AX80: 0 | AY80: 0 | AZ80: 0 | BA80: 0 | BB80: 0 | BC80: 242 | BD80: 1 | BE80: 0 | BF80: 0 | BG80: https://digital.library.pitt.edu/islandora/object/pitt:31735066237391 | BH80: 立直根批宗弟輝煌於父手置有民田三號址在本處土名俗叫烏石后半嶺及四旋又及草坵式旋共該祖公石鄉正折實田共式畝四分官止但此田太祖前年間出典在根主蘇作標處今因乏伐應用即將此田又托中向在根主作標送入頭承根為業今中言議時值根價伐肆拾壺千陸百文正其伐親收足訖無少隻文其田自根之后隨手即退與標子孫前去召佃耕作愛業中間授受清楚並無抑勒俸算情由亦未曾重根別人財物倘有未歷不明係煌出抵不涉標之事而尤無悔今欲有憑立直根批一紙為照同治八年十二月日親立直根批宗弟輝煌知根胞弟輝煌在見出嗣弟輝灼中人宗弟士治梅蘇作標
A81: 31735066237391_002 | B81: 31735066237391 | C81: 2 | D81: 1869 | E81: 1869 | F81: =IF(D81="","?",IF(D81<1796,"pre-1796",IF(D81<1912,"1796-1911",IF(D81<1949,"1912-1948","1949+")))) -> 1796-1911 | G81: =IF(D81="","?",IF(D81<1912,"Qing",IF(D81<1949,"Republic","PRC"))) -> Qing | H81: 1869 | I81: 屏南 | J81: 福建省屏南縣 | K81: Government | M81: 輝煌 | N81: 蘇坐標 | O81: Box 1, Folder 46 | P81: Other / fragment | R81: 同治八年 | Z81: ... | AI81: 0 | AJ81: 0 | AK81: 0 | AL81: 0 | AM81: 0 | AN81: 0 | AO81: 0 | AP81: 0 | AQ81: 0 | AR81: 0 | AS81: 0 | AT81: 0 | AU81: 0 | AV81: 0 | AW81: 0 | AX81: 0 | AY81: 0 | AZ81: 0 | BA81: 0 | BB81: 0 | BC81: 54 | BD81: 1 | BE81: 1 | BF81: 0 | BG81: https://digital.library.pitt.edu/islandora/object/pitt:31735066237391 | BH81: 103善作標48忠大花加豐忠大花計加豐中人...忠大花...加豐...忠大花...加豐...同治八年十二月日
A82: 31735066237409_001 | B82: 31735066237409 | C82: 1 | F82: =IF(D82="","?",IF(D82<1796,"pre-1796",IF(D82<1912,"1796-1911",IF(D82<1949,"1912-1948","1949+")))) -> ? | G82: =IF(D82="","?",IF(D82<1912,"Qing",IF(D82<1949,"Republic","PRC"))) -> ? | J82: 安徽省歙縣 | K82: Government | L82: 羅 | O82: Box 1, Folder 17 | P82: Official form | AE82: 契尾 | AG82: 收...; 看... | AI82: 0 | AJ82: 0 | AK82: 0 | AL82: 0 | AM82: 0 | AN82: 0 | AO82: 0 | AP82: 0 | AQ82: 0 | AR82: 0 | AS82: 0 | AT82: 0 | AU82: 0 | AV82: 0 | AW82: 0 | AX82: 0 | AY82: 0 | AZ82: 0 | BA82: 0 | BB82: 0 | BC82: 112 | BD82: 0 | BE82: 2 | BF82: 0 | BG82: https://digital.library.pitt.edu/islandora/object/pitt:31735066237409 | BH82: 契尾江南安徽等處承印布政使司局處吉肅春奉察院牌戶部奏為前次改訂田賦給與契尾...照常細書業戶等姓名...司印以便稅務...字樣開前幅給業戶收...查核欽此欽遵察院行...特登項仍令業戶看...司查核轉報院部毋...計開...
A83: 31735066237417_001 | B83: 31735066237417 | C83: 1 | D83: 1849 | E83: 1849 | F83: =IF(D83="","?",IF(D83<1796,"pre-1796",IF(D83<1912,"1796-1911",IF(D83<1949,"1912-1948","1949+")))) -> 1796-1911 | G83: =IF(D83="","?",IF(D83<1912,"Qing",IF(D83<1949,"Republic","PRC"))) -> Qing | H83: 1849 | I83: 古田 | J83: 福建省古田縣 | K83: Government | L83: 林元鼎 | O83: Box 1, Folder 32 | P83: Other / fragment | AI83: 0 | AJ83: 0 | AK83: 0 | AL83: 0 | AM83: 0 | AN83: 0 | AO83: 0 | AP83: 0 | AQ83: 0 | AR83: 0 | AS83: 0 | AT83: 0 | AU83: 0 | AV83: 0 | AW83: 0 | AX83: 0 | AY83: 0 | AZ83: 0 | BA83: 0 | BB83: 0 | BC83: 1 | BD83: 0 | BE83: 0 | BF83: 0 | BG83: https://digital.library.pitt.edu/islandora/object/pitt:31735066237417 | BH83: 大
A84: 31735066237425_001 | B84: 31735066237425 | C84: 1 | D84: 1920 | E84: 1920 | F84: =IF(D84="","?",IF(D84<1796,"pre-1796",IF(D84<1912,"1796-1911",IF(D84<1949,"1912-1948","1949+")))) -> 1912-1948 | G84: =IF(D84="","?",IF(D84<1912,"Qing",IF(D84<1949,"Republic","PRC"))) -> Republic | H84: 1920 | I84: 閩侯（閩縣・侯官・林森） | J84: 福建省閩侯縣 | K84: Government | M84: 張氏 | N84: 林欽祥 | O84: Box 2, Folder 109 | P84: Private deed | Q84: 立賣新契 | R84: 民國九年 | S84: 林張氏 | U84: 價錢台伏叁拾貳元正 | V84: 台伏 | W84: 本洋 | X84: 后塢 | Y84: 田面 | AA84: 趙允坤 | AB84: 胞伯久水 | AI84: 1 | AJ84: 0 | AK84: 1 | AL84: 1 | AM84: 1 | AN84: 1 | AO84: 1 | AP84: 0 | AQ84: 1 | AR84: 0 | AS84: 1 | AT84: 0 | AU84: 0 | AV84: 1 | AW84: 0 | AX84: 0 | AY84: 0 | AZ84: 0 | BA84: 0 | BB84: 0 | BC84: 329 | BD84: 1 | BE84: 0 | BF84: 0 | BG84: https://digital.library.pitt.edu/islandora/object/pitt:31735066237425 | BH84: 立賣新契弟婦張氏原夫在日閩分下有民洋田面根全壹號坐產本洋土名后塢地方計丈拾分零東至長意桔樹西至長意桔樹南至長意桔樹北至乾茂田四至明白今因要用托中將此面根全田賣新兩夫伯欽祥震永遠為業三面言議今日賣新示價錢台伏叁拾貳元正其錢即日收足其田听買主前去翻犁耕作收掌子粒了納糧色听從通甲入戶但此面根全田係夫在日閩分下物業與親疎伯叔侄等無干並未曾重張典當他人財物以及未歷不明等情如有此情係夫弟婦云頭承當與夫伯無涉自賣新之汝係心愿承新萬藤向汝不得言湊言贖亦不得別生枝節之理兩相允愿各反恣恐口無憑立賣新契壹紙為照內標註大宇字樣照內標原契夾號不便繳付標照內標土埋長意西月坪下式柄鐸听買主挑土運回標照知契翁仕修謹民國九年九月吉日立賣新契林張氏在見胞伯久水謹久善仲人月生代筆趙允坤謹
A85: 31735066237433_001 | B85: 31735066237433 | C85: 1 | D85: 1928 | E85: 1928 | F85: =IF(D85="","?",IF(D85<1796,"pre-1796",IF(D85<1912,"1796-1911",IF(D85<1949,"1912-1948","1949+")))) -> 1912-1948 | G85: =IF(D85="","?",IF(D85<1912,"Qing",IF(D85<1949,"Republic","PRC"))) -> Republic | H85: 1928 | I85: 古田 | J85: 福建省古田縣 | K85: Government | L85: 盧亨雲 | O85: Box 3, Folder 137 | P85: Official form | Q85: 立之不動產舊契 | R85: 中華民國十七年 | U85: 價四十一元 | W85: 四至原契已載明白遵章呈驗應納紙價 | AE85: 驗 稅 契 證 | AF85: 福建財政廳 | AG85: 盧亨雲 | AI85: 0 | AJ85: 0 | AK85: 0 | AL85: 0 | AM85: 0 | AN85: 0 | AO85: 0 | AP85: 0 | AQ85: 0 | AR85: 0 | AS85: 1 | AT85: 1 | AU85: 0 | AV85: 0 | AW85: 1 | AX85: 1 | AY85: 1 | AZ85: 1 | BA85: 1 | BB85: 1 | BC85: 298 | BD85: 0 | BE85: 0 | BF85: 0 | BG85: https://digital.library.pitt.edu/islandora/object/pitt:31735066237433 | BH85: 驗稅契證福建財政廳為給發驗稅契證事案奉國民政府財政部訓令頒發驗契暫行條例及各省驗契章程凡在此次開辦驗契以前成立之不動產舊契無論已稅未稅均應一律限期呈驗換發新契紙倘逾限不呈驗遇有訴訟不能作為憑證如經人告發或官廳查出者並加以處罰業由財政部咨行司法部通飭遵辦以為匿驗有戒等因奉此當經擬具徵收方法電奉財政部核准照辦並已訂定本省驗契補充辦法分別通令布告遵照在案茲據業戶盧亨雲呈繳已稅田契壹紙產價四十一元坐落四至原契已載明白遵章呈驗應納紙價六元八角分註冊費一角附加教育費貳角業已如數收訖除註冊外另填驗稅契證粘連原契印給收執管業須至契證者恩增戶右給業戶盧亨雲准此每張收銀五文中華民國十七年五月日給下契登新字第號
A86: 31735066237433_002 | B86: 31735066237433 | C86: 2 | D86: 1928 | E86: 1928 | F86: =IF(D86="","?",IF(D86<1796,"pre-1796",IF(D86<1912,"1796-1911",IF(D86<1949,"1912-1948","1949+")))) -> 1912-1948 | G86: =IF(D86="","?",IF(D86<1912,"Qing",IF(D86<1949,"Republic","PRC"))) -> Republic | H86: 1928 | I86: 古田 | J86: 福建省古田縣 | K86: Government | L86: 盧亨雲 | O86: Box 3, Folder 137 | P86: Official form | Q86: 立契 | R86: 中華民國 年 | W86: 不動產面積四至東至南至西至北至畝 | AE86: (三) | 福建省政府財政廳頒發古田縣已稅契驗契證 | AF86: 福建省政府財政廳; 此處蓋縣政府 | AG86: 住址 | AI86: 0 | AJ86: 0 | AK86: 0 | AL86: 0 | AM86: 0 | AN86: 0 | AO86: 0 | AP86: 0 | AQ86: 0 | AR86: 0 | AS86: 0 | AT86: 0 | AU86: 0 | AV86: 0 | AW86: 0 | AX86: 0 | AY86: 0 | AZ86: 0 | BA86: 0 | BB86: 0 | BC86: 304 | BD86: 0 | BE86: 0 | BF86: 0 | BG86: https://digital.library.pitt.edu/islandora/object/pitt:31735066237433 | BH86: (三)福建省政府財政廳頒發古田縣已稅契驗契證茲為整理契稅，體卹人民，保障產權起見，特定驗契辦法，凡屬田園屋地各類不動產，已稅未稅契據，均應一律投驗，填給驗契證，已稅之紅契，不收驗費，未稅之白契，無論典賣及產價多寡，每張祇收驗契費銀壹元，經此驗契，粘有驗契證者，方為有效。非經買賣移轉，不再徵稅。業主姓名業主住址不動產種類不動產坐落不動產面積四至東至南至西至北至畝分畝分畝分畝分畝分等則賦額地丁糧米產價出典主姓名中證人姓名立契年月日其他此處粘連原契騎縫加蓋驗契鈐記此處蓋財政廳驗契證關防此處蓋縣政府印第區區長簽名蓋章中華民國年月日第號保保長或鄉長簽名蓋章此種已稅契驗契證不收驗費古田縣三此張填給業主粘連原契管業
A87: 31735066237441_001 | B87: 31735066237441 | C87: 1 | D87: 1915 | E87: 1915 | F87: =IF(D87="","?",IF(D87<1796,"pre-1796",IF(D87<1912,"1796-1911",IF(D87<1949,"1912-1948","1949+")))) -> 1912-1948 | G87: =IF(D87="","?",IF(D87<1912,"Qing",IF(D87<1949,"Republic","PRC"))) -> Republic | H87: 1915 | I87: 古田 | J87: 福建省古田縣 | K87: Government | L87: 雷汝知 | O87: Box 2, Folder 103 | P87: Official form | R87: 同治十二年; 中華民國 四年 | U87: 價銀肆拾貳兩 | W87: 古田縣本郡梅坪 | Z87: 于受 | AE87: 典 按 契 單 | 福建財政廳 | AF87: 福建財政廳 | AG87: 雷汝知 | AH87: 稅字第 貳萬零百柒 號 | AI87: 0 | AJ87: 0 | AK87: 0 | AL87: 0 | AM87: 0 | AN87: 0 | AO87: 0 | AP87: 0 | AQ87: 0 | AR87: 0 | AS87: 0 | AT87: 0 | AU87: 0 | AV87: 0 | AW87: 1 | AX87: 1 | AY87: 1 | AZ87: 1 | BA87: 0 | BB87: 0 | BC87: 401 | BD87: 0 | BE87: 0 | BF87: 0 | BG87: https://digital.library.pitt.edu/islandora/object/pitt:31735066237441 | BH87: 典按契單福建財政廳為給發契單事案查接管國稅廳籌備處卷內奉財政部飭開契稅條例於一月十一日經大總統公布並由本部按照本條例第十一條之規定訂定契稅條例施行細則於一月二十九日以部令公布在案查契稅條例第一條第二項前項契約用紙由財政部定式頒行等語除契稅條例第二條所規定之特別印花由部製備另行頒發外隨飭發去契稅條例暨契稅條例施行細則並契紙及各種收據清冊格式應即照式先行製備仰該處長遵照辦理可也等因奉此查契稅條例施行細則第二十條本條例公布後各徵稅官署未奉到部頒契紙特別印花出示曉諭以前所有田房稅契應仍照向章辦理等語合據古田縣業戶雷汝知於同治十二年十一月日典受雷上崎氏田由鄉坐落古田縣本郡梅坪地方東至南至北至西至大尺直坐向橫業已尺邀同中證于受議定價銀肆拾貳兩依限投稅應納稅銀貳元如數收訖合填契單粘連原契印給收執管業須至契單者右給業戶雷汝知准此清查証處字號中華民國四年十二月日給稅字第貳萬零百柒號嘉兌字第稅字第稅字第稅字第號
A88: 31735066237458_001 | B88: 31735066237458 | C88: 1 | D88: 1930 | E88: 1930 | F88: =IF(D88="","?",IF(D88<1796,"pre-1796",IF(D88<1912,"1796-1911",IF(D88<1949,"1912-1948","1949+")))) -> 1912-1948 | G88: =IF(D88="","?",IF(D88<1912,"Qing",IF(D88<1949,"Republic","PRC"))) -> Republic | H88: 1930 | I88: 古田 | J88: 福建省古田縣 | K88: Government | L88: 洪國慶 | O88: Box 3, Folder 141 | P88: Official form | AE88: 副 證 | 契 已 驗 稅 | AI88: 0 | AJ88: 0 | AK88: 0 | AL88: 0 | AM88: 0 | AN88: 0 | AO88: 0 | AP88: 0 | AQ88: 0 | AR88: 0 | AS88: 0 | AT88: 0 | AU88: 0 | AV88: 0 | AW88: 0 | AX88: 0 | AY88: 0 | AZ88: 0 | BA88: 0 | BB88: 0 | BC88: 42 | BD88: 0 | BE88: 0 | BF88: 0 | BG88: https://digital.library.pitt.edu/islandora/object/pitt:31735066237458 | BH88: 副證縣協地方門牌田畝畝分座號葉戶法國度契已驗稅契證新字第北丁號中華民國十九年四月日給
A89: 31735066237458_002 | B89: 31735066237458 | C89: 2 | D89: 1930 | E89: 1930 | F89: =IF(D89="","?",IF(D89<1796,"pre-1796",IF(D89<1912,"1796-1911",IF(D89<1949,"1912-1948","1949+")))) -> 1912-1948 | G89: =IF(D89="","?",IF(D89<1912,"Qing",IF(D89<1949,"Republic","PRC"))) -> Republic | H89: 1930 | I89: 古田 | J89: 福建省古田縣 | K89: Government | L89: 洪國慶 | O89: Box 3, Folder 141 | P89: Official form | Q89: 立之不動產舊契 | R89: 中華民國十九年 | U89: 價叁拾捌元 | W89: 四至原契已載明白遵章呈繳應納稅價 | AE89: 法潤章 | 驗 稅 契 證 | 福建財政廳 | AF89: 福建財政廳 | AG89: 洪國慶 | AH89: 新字第 卅一號 | AI89: 0 | AJ89: 0 | AK89: 0 | AL89: 0 | AM89: 0 | AN89: 0 | AO89: 0 | AP89: 0 | AQ89: 0 | AR89: 0 | AS89: 1 | AT89: 1 | AU89: 0 | AV89: 0 | AW89: 1 | AX89: 1 | AY89: 1 | AZ89: 1 | BA89: 1 | BB89: 1 | BC89: 309 | BD89: 0 | BE89: 0 | BF89: 0 | BG89: https://digital.library.pitt.edu/islandora/object/pitt:31735066237458 | BH89: 法潤章驗稅契證福建財政廳為給發驗稅契證事案奉國民政府財政部訓令頒發驗契暫行條例及各省驗契章程凡在此次開辦驗契以前成立之不動產舊契無論已稅未稅均應一律限期呈驗換發新契紙倘逾限不呈驗遇有訴訟不能作為憑證如經人告發或官廳查出者並加以處罰業由財政部咨行司法部通飭遵辦以為匿驗者戒等因奉此當經擬具徵收方法電奉財政部核准照辦並已訂定本省驗契補充辦法分別通令布告遵照在案茲據業戶洪國慶呈繳未稅契壹紙產價叁拾捌元坐落四至原契已載明白遵章呈繳應納稅價壹元貳角貳分註冊費壹角附加教育費貳角業已如數收訖除註冊外合填驗稅契證粘連原契印給收執管業須至契證者奉財政廳令定逾限按月遞加紙價十分之二右給業戶洪國慶准此中華民國十九年四月日給新字第卅一號
A90: 31735066237466_001 | B90: 31735066237466 | C90: 1 | F90: =IF(D90="","?",IF(D90<1796,"pre-1796",IF(D90<1912,"1796-1911",IF(D90<1949,"1912-1948","1949+")))) -> ? | G90: =IF(D90="","?",IF(D90<1912,"Qing",IF(D90<1949,"Republic","PRC"))) -> ? | I90: 古田 | J90: 福建省古田縣 | K90: Government | M90: 陳如良 | N90: 陈謀丁 | O90: Box 3, Folder 153 | P90: Official form | R90: 民國二十年; 中華民國二十四年 | U90: 銀番肆拾員正 | W90: 十二都 | X90: 利洋裡讓 | Y90: 田根 | Z90: 陳贈壽 | AA90: 陳炳星 | AB90: 胞兄如淋 | AE90: 民國二十年 續回作廢 | AI90: 1 | AJ90: 1 | AK90: 1 | AL90: 1 | AM90: 1 | AN90: 1 | AO90: 1 | AP90: 1 | AQ90: 0 | AR90: 0 | AS90: 1 | AT90: 1 | AU90: 0 | AV90: 0 | AW90: 0 | AX90: 0 | AY90: 0 | AZ90: 0 | BA90: 0 | BB90: 0 | BC90: 337 | BD90: 0 | BE90: 0 | BF90: 0 | BG90: https://digital.library.pitt.edu/islandora/object/pitt:31735066237466 | BH90: 立典佃田根勢陳如良承上手還有免分己份佃田重發坐址十二都地方土名利洋裡讓田八亩五分受種二斗五升年還林姓主租早米冬石捌斗應耕還租典異今因乏款應用自情愿託中將此佃田出典引向本保祖謀丁處為業三面言議特得典價划足重銀番肆拾員正其銀良全中親收足訖無少分文其佃田隨契即退與謀前去耕作還租當業中間允愿交關並無勒索亦未重張典當他人財物但此田是良已業與親堂伯叔兄弟侄與干倘有來歷不明良當出抵不涉謀之事自典之後年限言約三年限滿外任良倘辨典佃田根勢價以及稅耗一足取贖如限未滿不得言及盡贖等情兩允無悔今欲有憑托立典佃田根勢重紙并繳原根印稅批重紙共式總統為付照民國二十年續回作廢中華民國二十四年歲正月日立典佃田根勢陳如良在見胞兄如淋中人陳贈壽全見陳德銘代筆陳炳星田根勢陳如良此處粘連原契騎縫加蓋驗契鈐記
A91: 31735066237466_002 | B91: 31735066237466 | C91: 2 | F91: =IF(D91="","?",IF(D91<1796,"pre-1796",IF(D91<1912,"1796-1911",IF(D91<1949,"1912-1948","1949+")))) -> ? | G91: =IF(D91="","?",IF(D91<1912,"Qing",IF(D91<1949,"Republic","PRC"))) -> ? | I91: 古田 | J91: 福建省古田縣 | K91: Government | M91: 陳如良 | N91: 陈謀丁 | O91: Box 3, Folder 153 | P91: Official form | R91: 中華民國 年 | AF91: 此處蓋縣政府 | AI91: 0 | AJ91: 0 | AK91: 0 | AL91: 0 | AM91: 0 | AN91: 0 | AO91: 0 | AP91: 0 | AQ91: 0 | AR91: 0 | AS91: 0 | AT91: 0 | AU91: 0 | AV91: 0 | AW91: 0 | AX91: 0 | AY91: 0 | AZ91: 0 | BA91: 0 | BB91: 0 | BC91: 87 | BD91: 0 | BE91: 0 | BF91: 0 | BG91: https://digital.library.pitt.edu/islandora/object/pitt:31735066237466 | BH91: 此處蓋財政廳驗契證關防此處蓋縣政府印第一區長簽名蓋章中華民國年月日第24382號第保保長或鄉長簽名蓋章此種未稅契驗契證每張征收驗契費銀壹圓正古田縣三此張填給業主粘連原契據管業
A92: 31735066237474_001 | B92: 31735066237474 | C92: 1 | D92: 1925 | E92: 1925 | F92: =IF(D92="","?",IF(D92<1796,"pre-1796",IF(D92<1912,"1796-1911",IF(D92<1949,"1912-1948","1949+")))) -> 1912-1948 | G92: =IF(D92="","?",IF(D92<1912,"Qing",IF(D92<1949,"Republic","PRC"))) -> Republic | H92: 1925 | I92: 古田 | J92: 福建省古田縣 | K92: Government | M92: 林履同 | N92: 張炳源 | O92: Box 3, Folder 124 | P92: Private deed + state certificate | Q92: 立契 | R92: 光緒三十三年 | U92: 價伍拾元 | V92: 大洋 | W92: 玉源巷上面積廿號東至南至西至北至 | Z92: 鄭蔚如 | AE92: 例則摘要 | 要 | AI92: 0 | AJ92: 0 | AK92: 0 | AL92: 0 | AM92: 0 | AN92: 0 | AO92: 0 | AP92: 0 | AQ92: 0 | AR92: 0 | AS92: 1 | AT92: 1 | AU92: 0 | AV92: 0 | AW92: 0 | AX92: 1 | AY92: 0 | AZ92: 0 | BA92: 1 | BB92: 1 | BC92: 681 | BD92: 0 | BE92: 1 | BF92: 0 | BG92: https://digital.library.pitt.edu/islandora/object/pitt:31735066237474 | BH92: 古田契稅局本局為便利民起見凡將契印發給不登分文不稅限章納稅倘係不登分文不稅限章納稅倘係奉令自光緒三十三年拾月二十日起契紙加收善後附捐大洋壹元正新領契紙古田契稅局核准無效特此批明賣契立契年月日民國廿年正月買主姓名張炳源不動產種類祀田價伍拾元應納稅額叁元原契幾張壹張例則摘要要中華民國廿四年六月九日日賣主林履桐中人鄭蔚如坐落玉源巷上面積廿號東至南至西至北至一不動產之買主或承典人須於契紙成立後六個月以內赴該管徵收官署投稅一訂立不動產買契或典契時須由賣主或出典人赴該管徵收官署填具申請書請領契紙繳納契紙費大洋五角前項之契紙費五角由賣主與買主或出典人與承典人分擔一不動產之賣主或出典人請領契紙後已逾兩月其契約尚未成立者原領契紙失其効力但因有障礙致契約不能成立時得於限內赴徵收官署申明事由酌予寬限一原領契紙因遺失及其他事由須補領或更換時仍依第四條第一項之規定繳納契紙費一不動產之買主或承典人逾契約成立後六個月之期限不依本條例繳納契紙費者除納契稅外並處以應納稅額之十倍罰金一繳納契稅時匿稅契價者除另換契紙改正契約繳納稅額外並處以左列之罰金一匿報契價十分之二以上未滿十分之三者短納稅額之二倍一匿報契價十分之三以上未滿十分之四者短納稅額之四倍一匿報契價十分之四以上未滿十分之五者短納稅額之八倍一匿報契價十分之五以上者短納稅額之十六倍或由徵稅官署依所報契價收買之一契約成立後六個月之納稅期間限於遵領官契紙者適用之其私紙所書之契約若事後不換寫契紙以逾限論一賣主或出典人以私紙訂立契約者得由徵稅官署處以五元以上五十元以下之罰金一逾限未稅之契訴訟時無憑證之効力福建...虎...縣...
A93: 31735066237482_001 | B93: 31735066237482 | C93: 1 | D93: 1913 | E93: 1913 | F93: =IF(D93="","?",IF(D93<1796,"pre-1796",IF(D93<1912,"1796-1911",IF(D93<1949,"1912-1948","1949+")))) -> 1912-1948 | G93: =IF(D93="","?",IF(D93<1912,"Qing",IF(D93<1949,"Republic","PRC"))) -> Republic | H93: 1913 | I93: 屏南 | J93: 福建省屏南縣 | K93: Government | L93: 張傳珍 | O93: Box 2, Folder 100 | P93: Official form | Q93: 立之不動產舊契 | W93: 縣六家裡 | AE93: 契單 | 斷 | 福建國稅廳籌備處 | AF93: 福建國稅廳籌備處 | AG93: 張傳珍 | AH93: 驗字第七百伍六號 | AI93: 0 | AJ93: 0 | AK93: 0 | AL93: 0 | AM93: 0 | AN93: 0 | AO93: 0 | AP93: 0 | AQ93: 0 | AR93: 0 | AS93: 1 | AT93: 0 | AU93: 0 | AV93: 0 | AW93: 0 | AX93: 1 | AY93: 1 | AZ93: 1 | BA93: 1 | BB93: 1 | BC93: 356 | BD93: 0 | BE93: 0 | BF93: 0 | BG93: https://digital.library.pitt.edu/islandora/object/pitt:31735066237482 | BH93: 財政部令契單斷福建國稅廳籌備處給發契單事業奉財政部電行劃一契紙章程內開本章程施行以前成立之不動產舊契無論已稅契未稅契均應一律限期呈驗逾限不呈驗者於訴訟時不能作為憑據一併函知司法機關認真辦理以為憑驗者戒等因奉此當經擬定分別徵收方法已稅之舊契每張收紙價壹元未稅之舊契每產價百元收紙價壹元其光復後新契已稅者不收紙價酌定正限三個月餘限兩個月逾期呈驗者分別加徵嚴罰經已電奉財政部核准照辦並通飭遵照在案今據縣業戶張傳珍於年月西至原價銀北至坐向橫大尺直大尺中紙價壹元業已如數收訖合填契單粘連原契印給收執管業須至契單者兩中銀拾元原契未稅遵章依限呈驗應納受新張守斐地坪坐落縣六家裡地方東至南至驗字內錢糧處所至賣主中見姓名因限期緊迫填寫不及概憑原契及別底存根管業右給業戶張傳珍准此中華民國式年十一月日給驗字第七百伍六號給發契單事業奉
A94: 31735066237490_001 | B94: 31735066237490 | C94: 1 | D94: 1906 | E94: 1906 | F94: =IF(D94="","?",IF(D94<1796,"pre-1796",IF(D94<1912,"1796-1911",IF(D94<1949,"1912-1948","1949+")))) -> 1796-1911 | G94: =IF(D94="","?",IF(D94<1912,"Qing",IF(D94<1949,"Republic","PRC"))) -> Qing | H94: 1906 | K94: Personal | M94: 郭宗仲 | N94: 王齊發 | O94: Box 2, Folder 88 | P94: Private deed | Q94: 立賣斷契 | R94: 光緒三十二年 | S94: 郭宗仲 | W94: 閩邑文山鋪秋龍社 | Y94: 厝屋; 基地 | Z94: 高依賜 | AA94: 齊光波 | AB94: 曉弟宗階 | AI94: 1 | AJ94: 1 | AK94: 1 | AL94: 1 | AM94: 1 | AN94: 1 | AO94: 1 | AP94: 0 | AQ94: 1 | AR94: 1 | AS94: 1 | AT94: 0 | AU94: 0 | AV94: 1 | AW94: 0 | AX94: 0 | AY94: 0 | AZ94: 0 | BA94: 0 | BB94: 0 | BC94: 345 | BD94: 0 | BE94: 0 | BF94: 0 | BG94: https://digital.library.pitt.edu/islandora/object/pitt:31735066237490 | BH94: 立賣斷契郭宗仲原有自己手置式在厝屋旁欄左邊房屋壅堵右邊廊墘壅小堵共成叁堵坐產閩邑文山鋪秋龍社地方坐北向南其屋上至楊桁磚瓦天天下至梁石地其基地前至天井後至牆左至廊墘右至壅家屋此屋內門窓戶櫺廊石一切俱全其云至俱載明白出入門路水井係照舊通行通用今因急需需情願托中將此屋賣斷契王齊發處永遠管業本日三面言議賣斷屋價鏡銀書各西正其銀即日親手隨契收足其屋即聽主家太道管業奴折毀起蓋自今居住若他人請其便賣斷之後價足心願永斷萬萬膝不得言湊言至願言盡亦不得別生枝節但此屋仲自己手置與親陳房伯叔兄弟無干亦未曾重張典當他人財物以及來不明各等情如有此情係仲出頭承當不張王家之事兩相其愿各無反悔今欲有憑立賣斷契二紙郭宗仲老原契壹紙共成三紙統付為憑光緒三十二年三月吉日立賣斷契郭宗仲在見曉弟宗階中友高依賜林錫甫代筆齊光波
A95: 31735066237508_001 | B95: 31735066237508 | C95: 1 | D95: 1921 | E95: 1921 | F95: =IF(D95="","?",IF(D95<1796,"pre-1796",IF(D95<1912,"1796-1911",IF(D95<1949,"1912-1948","1949+")))) -> 1912-1948 | G95: =IF(D95="","?",IF(D95<1912,"Qing",IF(D95<1949,"Republic","PRC"))) -> Republic | H95: 1921 | I95: 古田 | J95: 福建省古田縣 | K95: Government | L95: 謝祀初 | O95: Box 3, Folder 115 | P95: Official form | R95: 民國拾年 | AE95: 給領 彙造 便民 兇枉 易知 卑 | AF95: 卑古田縣知事 | AI95: 0 | AJ95: 0 | AK95: 0 | AL95: 0 | AM95: 0 | AN95: 0 | AO95: 0 | AP95: 0 | AQ95: 0 | AR95: 0 | AS95: 0 | AT95: 0 | AU95: 0 | AV95: 0 | AW95: 0 | AX95: 0 | AY95: 0 | AZ95: 0 | BA95: 0 | BB95: 0 | BC95: 197 | BD95: 1 | BE95: 0 | BF95: 0 | BG95: https://digital.library.pitt.edu/islandora/object/pitt:31735066237508 | BH95: 給領彙造便民兇枉易知卑古田縣知事吳頒給帳單以便充賦事照得民間買賣田畝應即隨時推收止的戶證冊給單完納以杜訟案歷辦在案該民因成立奉發章程嚴重推收相應查照辦理除著令冊書將推收帳單按戶彙造照冊核對蓋印存檔以憑稽查其推收領單各費應遵照司領章程及縣辦理不准苛勒外合行給單為此仰縣戶收執照頒輸將以杜混冒毋違頒單舊管前屆冊造建邑新改謝祀初正五開除實查建邑以上各應徵銀戈錢捌分民國拾年五月日給賬戶謝祀初准此財政科
A96: 31735066237516_001 | B96: 31735066237516 | C96: 1 | D96: 1933 | E96: 1933 | F96: =IF(D96="","?",IF(D96<1796,"pre-1796",IF(D96<1912,"1796-1911",IF(D96<1949,"1912-1948","1949+")))) -> 1912-1948 | G96: =IF(D96="","?",IF(D96<1912,"Qing",IF(D96<1949,"Republic","PRC"))) -> Republic | H96: 1933 | I96: 古田 | J96: 福建省古田縣 | K96: Government | L96: 余興泉 | O96: Box 3, Folder 148 | P96: Official form | R96: 民國二十二年 | Y96: 民田 | AE96: 頒給彙造便民四柱易知單 | AF96: 單古田縣政府 | AI96: 0 | AJ96: 0 | AK96: 0 | AL96: 0 | AM96: 0 | AN96: 0 | AO96: 0 | AP96: 0 | AQ96: 0 | AR96: 0 | AS96: 0 | AT96: 0 | AU96: 0 | AV96: 0 | AW96: 1 | AX96: 1 | AY96: 0 | AZ96: 0 | BA96: 0 | BB96: 0 | BC96: 250 | BD96: 0 | BE96: 0 | BF96: 0 | BG96: https://digital.library.pitt.edu/islandora/object/pitt:31735066237516 | BH96: 頒給彙造便民四柱易知單古田縣政府縣長鄭為頒給易知由單以便完賦事照得民間買賣田畝應即隨時推收認立的戶註冊給單完納以杜詭寄歷辦有案民國成立奉發章程嚴重推收亦經照辦各在案茲奉財政廳轉奉財政部遵奉總理遺教訂定限制田畝加賦辦法飭即遵照辦理一面將田賦認真整頓毋任逋欠以裕稅收各等因除着令冊書將推收糧額認真查造征冊核對蓋印存擋以便稽查外合行給單為此單仰糧戶收執照額輸將以杜混冒毋違須單計開冊舊管都甲戶金興泉前屆冊載新收則民田伍畝伍分正開除實在田以上合應徵銀伍錢叁分貳厘民國二十二年伍月日給糧戶余興泉准此縣經管陳誠書
A97: 31735066237524_001 | B97: 31735066237524 | C97: 1 | D97: 1933 | E97: 1933 | F97: =IF(D97="","?",IF(D97<1796,"pre-1796",IF(D97<1912,"1796-1911",IF(D97<1949,"1912-1948","1949+")))) -> 1912-1948 | G97: =IF(D97="","?",IF(D97<1912,"Qing",IF(D97<1949,"Republic","PRC"))) -> Republic | H97: 1933 | I97: 古田 | J97: 福建省古田縣 | K97: Government | L97: 葉克培 | O97: Box 3, Folder 149 | P97: Official form | AE97: 頒給彙造便民四柱易知單 | AF97: 單古田縣政府 | AI97: 0 | AJ97: 0 | AK97: 0 | AL97: 0 | AM97: 0 | AN97: 0 | AO97: 0 | AP97: 0 | AQ97: 0 | AR97: 0 | AS97: 0 | AT97: 0 | AU97: 0 | AV97: 0 | AW97: 1 | AX97: 1 | AY97: 0 | AZ97: 0 | BA97: 0 | BB97: 0 | BC97: 198 | BD97: 0 | BE97: 0 | BF97: 0 | BG97: https://digital.library.pitt.edu/islandora/object/pitt:31735066237524 | BH97: 頒給彙造便民四柱易知單古田縣政府縣長為頒給易知由單以便完賦事照得民間買賣田畝應即隨時推收認立的戶註冊給單完納以杜詭寄歷辦有案民國成立奉發章程嚴重推收亦經照辦各在案茲奉財政廳轉奉財政部令總理遺教訂定限制田畝加賦辦法飭即遵照辦理一面將田賦認真整頓毋任逋欠以裕稅收各等因除着令冊書將推收糧額認真查造征冊核對蓋印存擋以便稽查外合行給單為此單仰糧戶收執照額輸將以杜混冒毋違須單計開冊舊管甲戶世示克培前屆冊載
A98: 31735066237532_001 | B98: 31735066237532 | C98: 1 | D98: 1904 | E98: 1943 | F98: =IF(D98="","?",IF(D98<1796,"pre-1796",IF(D98<1912,"1796-1911",IF(D98<1949,"1912-1948","1949+")))) -> 1796-1911 | G98: =IF(D98="","?",IF(D98<1912,"Qing",IF(D98<1949,"Republic","PRC"))) -> Qing | H98: 1904/1943 | I98: 閩侯（閩縣・侯官・林森） | J98: 福建省閩縣 | K98: Government | L98: 黃財業 | M98: 許春願 | N98: 黃財業 | O98: Box 2, Folder 86 | P98: Private deed | Q98: 立賣斷契 | R98: 光緒叁拾年 | S98: 許春願 | U98: 價大洋陸拾員正 | V98: 大洋 | W98: 潘亭洋 | X98: 祠堂門前墟岬 | Y98: 民田 | AA98: 陳經林 | AI98: 1 | AJ98: 1 | AK98: 0 | AL98: 1 | AM98: 1 | AN98: 1 | AO98: 1 | AP98: 0 | AQ98: 1 | AR98: 0 | AS98: 1 | AT98: 0 | AU98: 0 | AV98: 0 | AW98: 0 | AX98: 0 | AY98: 0 | AZ98: 0 | BA98: 0 | BB98: 0 | BC98: 249 | BD98: 1 | BE98: 0 | BF98: 0 | BG98: https://digital.library.pitt.edu/islandora/object/pitt:31735066237532 | BH98: 立賣斷契許春願承祖遺下有民田根面全壘號坐產潘亭洋地方土名祠堂門前墟岬等處受種柒升伍合正年載租米柒斗伍升正根立化冊許文相戶下今因乏用將此田賣斷與黃財業安永遠為業三面言議本日得訖田價大洋陸拾員正其銀隨契交足其田所黃另召到耕其根亦聽過割入戶理納糧色夫此田係願祖遺物業與別無干並未曾重張典當他財以及源流不清等情倘有發現此情願自頭支當不涉于黃之事自斷之後一筆千秋永不敢別生枝節之理今欲有憑立賣斷契垂中其原契夾帶多額未繳再照內記出字屋客再照光緒叁拾年十月日立賣斷契許春願竟元春岐中八黃振章代字陳經林此1539大
A99: 31735066237532_002 | B99: 31735066237532 | C99: 2 | D99: 1904 | E99: 1943 | F99: =IF(D99="","?",IF(D99<1796,"pre-1796",IF(D99<1912,"1796-1911",IF(D99<1949,"1912-1948","1949+")))) -> 1796-1911 | G99: =IF(D99="","?",IF(D99<1912,"Qing",IF(D99<1949,"Republic","PRC"))) -> Qing | H99: 1904/1943 | I99: 閩侯（閩縣・侯官・林森） | J99: 福建省閩縣 | K99: Government | L99: 黃財業 | M99: 許春願 | N99: 黃財業 | O99: Box 2, Folder 86 | P99: Other / fragment | AI99: 0 | AJ99: 0 | AK99: 0 | AL99: 0 | AM99: 0 | AN99: 0 | AO99: 0 | AP99: 0 | AQ99: 0 | AR99: 0 | AS99: 0 | AT99: 0 | AU99: 0 | AV99: 0 | AW99: 0 | AX99: 0 | AY99: 0 | AZ99: 0 | BA99: 0 | BB99: 0 | BC99: 0 | BD99: 0 | BE99: 0 | BF99: 0 | BG99: https://digital.library.pitt.edu/islandora/object/pitt:31735066237532
A100: 31735066237540_001 | B100: 31735066237540 | C100: 1 | D100: 1942 | E100: 1943 | F100: =IF(D100="","?",IF(D100<1796,"pre-1796",IF(D100<1912,"1796-1911",IF(D100<1949,"1912-1948","1949+")))) -> 1912-1948 | G100: =IF(D100="","?",IF(D100<1912,"Qing",IF(D100<1949,"Republic","PRC"))) -> Republic | H100: 1942/1943 | I100: 閩清 | J100: 福建省閩清縣 | K100: Government | L100: 張道興 | M100: 余傳荃 | N100: 張道興 | O100: Box 3, Folder 164 | P100: Private deed | Q100: 立賣契 | R100: 中華民國叁拾壹年 | S100: 余傳差 | U100: 價彈國幣貳佰伍拾元正 | V100: 國幣 | W100: 本鄉 | X100: 過頭洋上下截 | Y100: 民田; 田根 | AI100: 1 | AJ100: 1 | AK100: 1 | AL100: 1 | AM100: 1 | AN100: 0 | AO100: 1 | AP100: 0 | AQ100: 1 | AR100: 1 | AS100: 1 | AT100: 0 | AU100: 0 | AV100: 0 | AW100: 0 | AX100: 0 | AY100: 0 | AZ100: 0 | BA100: 0 | BB100: 0 | BC100: 305 | BD100: 1 | BE100: 0 | BF100: 0 | BG100: https://digital.library.pitt.edu/islandora/object/pitt:31735066237540 | BH100: 立賣契契係傳差承父手置有民田限在號坐址本鄉地方土名過頭洋上下截等處受種柴井伍合等載租未盡檢斗法看法合正倘立大帝會張處土地編查段別壹拾貳段地號伍佰壹拾柒號畝分貳畝叁分伍厘等則丁等其糧報立自己戶下今因要用自願托中州此民田根賣謝典張道興處永遠為業三面三像去日清訖賣謝田根價彈國幣貳佰伍拾元正其款即日交足其田張永遠離佃耕作倘租完課受業其糧亦听張過割入戶自賣斷之後係足心願一筆千秋向後余之子孫永不敢生端枝節等情但此田係自承父手置物業與別無干亦未曾借借他人財物倘有未由不清係余出首承當不涉張之事兩相查允各無反悔今款有憑立賣斷契壹紙付托永遠為照中華民國叁拾壹年拾壹月日立賣斷契余傳差謹立見恆世琛以子中蕭昭芬鑒不狀(宣縣處防)
...

Sheet Narrative_moves
A1: The 12 narrative moves of a private deed
A2: Counts = private-deed pages (incl. deed + certificate) where the move's search pattern appears in the OCR text. Lower bounds: OCR misreads hide some instances.
A4: # | B4: Move | C4: Typical formula | D4: Function | E4: Flag column in Documents | F4: Pages with move | G4: Private pages | H4: Share
A5: 1 | B5: Title & author | C5: 立〔賣斷〕契 + name | D5: Names the contract by legal type and its author | E5: (not auto-detected) | G5: =COUNTIF(Documents!$P$2:$P$408,"Private deed*") -> 118
A6: 2 | B6: Provenance | C6: 承祖 / 承父手置 / 鬮書份下 | D6: Ownership told as inheritance | E6: (not auto-detected) | G6: =COUNTIF(Documents!$P$2:$P$408,"Private deed*") -> 118
A7: 3 | B7: Description | C7: 坐落…土名… / 四至 / 受種 / 年載租 | D7: Land located by native place-name, measured by seed and rent | E7: (not auto-detected) | G7: =COUNTIF(Documents!$P$2:$P$408,"Private deed*") -> 118
A8: 4 | B8: Motive | C8: 今因要用 / 別置 / 無錢應用 | D8: Turning point; reason kept formulaic | E8: 今因 motive | F8: =COUNTIFS(Documents!$P$2:$P$408,"Private deed*",Documents!$AI$2:$AI$408,1) -> 83 | G8: =COUNTIF(Documents!$P$2:$P$408,"Private deed*") -> 118 | H8: =IFERROR(F8/G8,0) -> 0.70338983
A9: 5 | B9: Voluntariness | C9: 自願 | D9: Seller acts of own will | E9: 自願 voluntary | F9: =COUNTIFS(Documents!$P$2:$P$408,"Private deed*",Documents!$AJ$2:$AJ$408,1) -> 47 | G9: =COUNTIF(Documents!$P$2:$P$408,"Private deed*") -> 118 | H9: =IFERROR(F9/G9,0) -> 0.39830508
A10: 6 | B10: Mediation | C10: 託中 … 賣與 ⏎ X處為業 | D10: Middleman; buyer name often raised to a new line (抬頭) | E10: 託中 mediated | F10: =COUNTIFS(Documents!$P$2:$P$408,"Private deed*",Documents!$AK$2:$AK$408,1) -> 79 | G10: =COUNTIF(Documents!$P$2:$P$408,"Private deed*") -> 118 | H10: =IFERROR(F10/G10,0) -> 0.66949153
A11: 7 | B11: Agreement & price | C11: 三面言議 … 價銀…正 | D11: Three-party agreement; formal numerals closed by 正 | E11: 三面言議 | F11: =COUNTIFS(Documents!$P$2:$P$408,"Private deed*",Documents!$AL$2:$AL$408,1) -> 71 | G11: =COUNTIF(Documents!$P$2:$P$408,"Private deed*") -> 118 | H11: =IFERROR(F11/G11,0) -> 0.60169492
A12: 8 | B12: Payment | C12: 其銀即日隨契交足 | D12: Payment complete at writing | E12: 即日交足 paid | F12: =COUNTIFS(Documents!$P$2:$P$408,"Private deed*",Documents!$AM$2:$AM$408,1) -> 93 | G12: =COUNTIF(Documents!$P$2:$P$408,"Private deed*") -> 118 | H12: =IFERROR(F12/G12,0) -> 0.78813559
A13: 9 | B13: Warranty | C13: 未曾重張典當…來歷不明 | D13: Negates every possible prior claim | E13: 無重典/來歷 warranty | F13: =COUNTIFS(Documents!$P$2:$P$408,"Private deed*",Documents!$AN$2:$AN$408,1) -> 77 | G13: =COUNTIF(Documents!$P$2:$P$408,"Private deed*") -> 118 | H13: =IFERROR(F13/G13,0) -> 0.65254237
A14: 10 | B14: Liability | C14: 出頭承當，不涉X之事 | D14: Seller answers any claim | E14: 出頭承當 seller answers | F14: =COUNTIFS(Documents!$P$2:$P$408,"Private deed*",Documents!$AO$2:$AO$408,1) -> 71 | G14: =COUNTIF(Documents!$P$2:$P$408,"Private deed*") -> 118 | H14: =IFERROR(F14/G14,0) -> 0.60169492
A15: 11 | B15: Time clause | C15: 面約…年為限…取贖 / 永斷萬無 | D15: Redemption window or permanent closure | E15: 取贖 redemption | F15: =COUNTIFS(Documents!$P$2:$P$408,"Private deed*",Documents!$AP$2:$AP$408,1) -> 40 | G15: =COUNTIF(Documents!$P$2:$P$408,"Private deed*") -> 118 | H15: =IFERROR(F15/G15,0) -> 0.33898305
A16: 12 | B16: Closing | C16: 兩相允願，各無反悔。今欲有憑，立…壹紙為照 | D16: The paper itself as proof | E16: 今欲有憑 closing | F16: =COUNTIFS(Documents!$P$2:$P$408,"Private deed*",Documents!$AS$2:$AS$408,1) -> 112 | G16: =COUNTIF(Documents!$P$2:$P$408,"Private deed*") -> 118 | H16: =IFERROR(F16/G16,0) -> 0.94915254

Sheet Formulae_by_period
A1: Private-deed formulae by period
A2: Each cell: number of private-deed pages in that period whose OCR text contains the formula. Period = catalogue start year.
A4: Formula | B4: pre-1796 | C4: 1796-1911 | D4: 1912-1948 | E4: 1949+ | F4: ? | G4: Total | H4: pre-1796 % | I4: 1796-1911 % | J4: 1912-1948 %
A5: Private pages (base) | B5: =COUNTIFS(Documents!$P$2:$P$408,"Private deed*",Documents!$F$2:$F$408,"pre-1796") -> 9 | C5: =COUNTIFS(Documents!$P$2:$P$408,"Private deed*",Documents!$F$2:$F$408,"1796-1911") -> 58 | D5: =COUNTIFS(Documents!$P$2:$P$408,"Private deed*",Documents!$F$2:$F$408,"1912-1948") -> 43 | E5: =COUNTIFS(Documents!$P$2:$P$408,"Private deed*",Documents!$F$2:$F$408,"1949+") -> 5 | F5: =COUNTIFS(Documents!$P$2:$P$408,"Private deed*",Documents!$F$2:$F$408,"?") -> 3 | G5: =SUM(B5:F5) -> 118
A6: 今因 motive | B6: =COUNTIFS(Documents!$P$2:$P$408,"Private deed*",Documents!$F$2:$F$408,"pre-1796",Documents!$AI$2:$AI$408,1) -> 4 | C6: =COUNTIFS(Documents!$P$2:$P$408,"Private deed*",Documents!$F$2:$F$408,"1796-1911",Documents!$AI$2:$AI$408,1) -> 46 | D6: =COUNTIFS(Documents!$P$2:$P$408,"Private deed*",Documents!$F$2:$F$408,"1912-1948",Documents!$AI$2:$AI$408,1) -> 29 | E6: =COUNTIFS(Documents!$P$2:$P$408,"Private deed*",Documents!$F$2:$F$408,"1949+",Documents!$AI$2:$AI$408,1) -> 1 | F6: =COUNTIFS(Documents!$P$2:$P$408,"Private deed*",Documents!$F$2:$F$408,"?",Documents!$AI$2:$AI$408,1) -> 3 | G6: =SUM(B6:F6) -> 83 | H6: =IFERROR(B6/B$5,0) -> 0.44444444 | I6: =IFERROR(C6/C$5,0) -> 0.79310345 | J6: =IFERROR(D6/D$5,0) -> 0.6744186
A7: 自願 voluntary | B7: =COUNTIFS(Documents!$P$2:$P$408,"Private deed*",Documents!$F$2:$F$408,"pre-1796",Documents!$AJ$2:$AJ$408,1) -> 3 | C7: =COUNTIFS(Documents!$P$2:$P$408,"Private deed*",Documents!$F$2:$F$408,"1796-1911",Documents!$AJ$2:$AJ$408,1) -> 27 | D7: =COUNTIFS(Documents!$P$2:$P$408,"Private deed*",Documents!$F$2:$F$408,"1912-1948",Documents!$AJ$2:$AJ$408,1) -> 15 | E7: =COUNTIFS(Documents!$P$2:$P$408,"Private deed*",Documents!$F$2:$F$408,"1949+",Documents!$AJ$2:$AJ$408,1) -> 1 | F7: =COUNTIFS(Documents!$P$2:$P$408,"Private deed*",Documents!$F$2:$F$408,"?",Documents!$AJ$2:$AJ$408,1) -> 1 | G7: =SUM(B7:F7) -> 47 | H7: =IFERROR(B7/B$5,0) -> 0.33333333 | I7: =IFERROR(C7/C$5,0) -> 0.46551724 | J7: =IFERROR(D7/D$5,0) -> 0.34883721
A8: 託中 mediated | B8: =COUNTIFS(Documents!$P$2:$P$408,"Private deed*",Documents!$F$2:$F$408,"pre-1796",Documents!$AK$2:$AK$408,1) -> 4 | C8: =COUNTIFS(Documents!$P$2:$P$408,"Private deed*",Documents!$F$2:$F$408,"1796-1911",Documents!$AK$2:$AK$408,1) -> 45 | D8: =COUNTIFS(Documents!$P$2:$P$408,"Private deed*",Documents!$F$2:$F$408,"1912-1948",Documents!$AK$2:$AK$408,1) -> 26 | E8: =COUNTIFS(Documents!$P$2:$P$408,"Private deed*",Documents!$F$2:$F$408,"1949+",Documents!$AK$2:$AK$408,1) -> 2 | F8: =COUNTIFS(Documents!$P$2:$P$408,"Private deed*",Documents!$F$2:$F$408,"?",Documents!$AK$2:$AK$408,1) -> 2 | G8: =SUM(B8:F8) -> 79 | H8: =IFERROR(B8/B$5,0) -> 0.44444444 | I8: =IFERROR(C8/C$5,0) -> 0.77586207 | J8: =IFERROR(D8/D$5,0) -> 0.60465116
A9: 三面言議 | B9: =COUNTIFS(Documents!$P$2:$P$408,"Private deed*",Documents!$F$2:$F$408,"pre-1796",Documents!$AL$2:$AL$408,1) -> 3 | C9: =COUNTIFS(Documents!$P$2:$P$408,"Private deed*",Documents!$F$2:$F$408,"1796-1911",Documents!$AL$2:$AL$408,1) -> 40 | D9: =COUNTIFS(Documents!$P$2:$P$408,"Private deed*",Documents!$F$2:$F$408,"1912-1948",Documents!$AL$2:$AL$408,1) -> 25 | E9: =COUNTIFS(Documents!$P$2:$P$408,"Private deed*",Documents!$F$2:$F$408,"1949+",Documents!$AL$2:$AL$408,1) -> 3 | F9: =COUNTIFS(Documents!$P$2:$P$408,"Private deed*",Documents!$F$2:$F$408,"?",Documents!$AL$2:$AL$408,1) -> 0 | G9: =SUM(B9:F9) -> 71 | H9: =IFERROR(B9/B$5,0) -> 0.33333333 | I9: =IFERROR(C9/C$5,0) -> 0.68965517 | J9: =IFERROR(D9/D$5,0) -> 0.58139535
A10: 即日交足 paid | B10: =COUNTIFS(Documents!$P$2:$P$408,"Private deed*",Documents!$F$2:$F$408,"pre-1796",Documents!$AM$2:$AM$408,1) -> 6 | C10: =COUNTIFS(Documents!$P$2:$P$408,"Private deed*",Documents!$F$2:$F$408,"1796-1911",Documents!$AM$2:$AM$408,1) -> 47 | D10: =COUNTIFS(Documents!$P$2:$P$408,"Private deed*",Documents!$F$2:$F$408,"1912-1948",Documents!$AM$2:$AM$408,1) -> 33 | E10: =COUNTIFS(Documents!$P$2:$P$408,"Private deed*",Documents!$F$2:$F$408,"1949+",Documents!$AM$2:$AM$408,1) -> 4 | F10: =COUNTIFS(Documents!$P$2:$P$408,"Private deed*",Documents!$F$2:$F$408,"?",Documents!$AM$2:$AM$408,1) -> 3 | G10: =SUM(B10:F10) -> 93 | H10: =IFERROR(B10/B$5,0) -> 0.66666667 | I10: =IFERROR(C10/C$5,0) -> 0.81034483 | J10: =IFERROR(D10/D$5,0) -> 0.76744186
A11: 無重典/來歷 warranty | B11: =COUNTIFS(Documents!$P$2:$P$408,"Private deed*",Documents!$F$2:$F$408,"pre-1796",Documents!$AN$2:$AN$408,1) -> 5 | C11: =COUNTIFS(Documents!$P$2:$P$408,"Private deed*",Documents!$F$2:$F$408,"1796-1911",Documents!$AN$2:$AN$408,1) -> 39 | D11: =COUNTIFS(Documents!$P$2:$P$408,"Private deed*",Documents!$F$2:$F$408,"1912-1948",Documents!$AN$2:$AN$408,1) -> 29 | E11: =COUNTIFS(Documents!$P$2:$P$408,"Private deed*",Documents!$F$2:$F$408,"1949+",Documents!$AN$2:$AN$408,1) -> 1 | F11: =COUNTIFS(Documents!$P$2:$P$408,"Private deed*",Documents!$F$2:$F$408,"?",Documents!$AN$2:$AN$408,1) -> 3 | G11: =SUM(B11:F11) -> 77 | H11: =IFERROR(B11/B$5,0) -> 0.55555556 | I11: =IFERROR(C11/C$5,0) -> 0.67241379 | J11: =IFERROR(D11/D$5,0) -> 0.6744186
A12: 出頭承當 seller answers | B12: =COUNTIFS(Documents!$P$2:$P$408,"Private deed*",Documents!$F$2:$F$408,"pre-1796",Documents!$AO$2:$AO$408,1) -> 4 | C12: =COUNTIFS(Documents!$P$2:$P$408,"Private deed*",Documents!$F$2:$F$408,"1796-1911",Documents!$AO$2:$AO$408,1) -> 34 | D12: =COUNTIFS(Documents!$P$2:$P$408,"Private deed*",Documents!$F$2:$F$408,"1912-1948",Documents!$AO$2:$AO$408,1) -> 29 | E12: =COUNTIFS(Documents!$P$2:$P$408,"Private deed*",Documents!$F$2:$F$408,"1949+",Documents!$AO$2:$AO$408,1) -> 1 | F12: =COUNTIFS(Documents!$P$2:$P$408,"Private deed*",Documents!$F$2:$F$408,"?",Documents!$AO$2:$AO$408,1) -> 3 | G12: =SUM(B12:F12) -> 71 | H12: =IFERROR(B12/B$5,0) -> 0.44444444 | I12: =IFERROR(C12/C$5,0) -> 0.5862069 | J12: =IFERROR(D12/D$5,0) -> 0.6744186
A13: 取贖 redemption | B13: =COUNTIFS(Documents!$P$2:$P$408,"Private deed*",Documents!$F$2:$F$408,"pre-1796",Documents!$AP$2:$AP$408,1) -> 3 | C13: =COUNTIFS(Documents!$P$2:$P$408,"Private deed*",Documents!$F$2:$F$408,"1796-1911",Documents!$AP$2:$AP$408,1) -> 20 | D13: =COUNTIFS(Documents!$P$2:$P$408,"Private deed*",Documents!$F$2:$F$408,"1912-1948",Documents!$AP$2:$AP$408,1) -> 14 | E13: =COUNTIFS(Documents!$P$2:$P$408,"Private deed*",Documents!$F$2:$F$408,"1949+",Documents!$AP$2:$AP$408,1) -> 0 | F13: =COUNTIFS(Documents!$P$2:$P$408,"Private deed*",Documents!$F$2:$F$408,"?",Documents!$AP$2:$AP$408,1) -> 3 | G13: =SUM(B13:F13) -> 40 | H13: =IFERROR(B13/B$5,0) -> 0.33333333 | I13: =IFERROR(C13/C$5,0) -> 0.34482759 | J13: =IFERROR(D13/D$5,0) -> 0.3255814
A14: 永遠 perpetual | B14: =COUNTIFS(Documents!$P$2:$P$408,"Private deed*",Documents!$F$2:$F$408,"pre-1796",Documents!$AQ$2:$AQ$408,1) -> 2 | C14: =COUNTIFS(Documents!$P$2:$P$408,"Private deed*",Documents!$F$2:$F$408,"1796-1911",Documents!$AQ$2:$AQ$408,1) -> 28 | D14: =COUNTIFS(Documents!$P$2:$P$408,"Private deed*",Documents!$F$2:$F$408,"1912-1948",Documents!$AQ$2:$AQ$408,1) -> 23 | E14: =COUNTIFS(Documents!$P$2:$P$408,"Private deed*",Documents!$F$2:$F$408,"1949+",Documents!$AQ$2:$AQ$408,1) -> 0 | F14: =COUNTIFS(Documents!$P$2:$P$408,"Private deed*",Documents!$F$2:$F$408,"?",Documents!$AQ$2:$AQ$408,1) -> 0 | G14: =SUM(B14:F14) -> 53 | H14: =IFERROR(B14/B$5,0) -> 0.22222222 | I14: =IFERROR(C14/C$5,0) -> 0.48275862 | J14: =IFERROR(D14/D$5,0) -> 0.53488372
A15: 無反悔/異言 | B15: =COUNTIFS(Documents!$P$2:$P$408,"Private deed*",Documents!$F$2:$F$408,"pre-1796",Documents!$AR$2:$AR$408,1) -> 3 | C15: =COUNTIFS(Documents!$P$2:$P$408,"Private deed*",Documents!$F$2:$F$408,"1796-1911",Documents!$AR$2:$AR$408,1) -> 32 | D15: =COUNTIFS(Documents!$P$2:$P$408,"Private deed*",Documents!$F$2:$F$408,"1912-1948",Documents!$AR$2:$AR$408,1) -> 24 | E15: =COUNTIFS(Documents!$P$2:$P$408,"Private deed*",Documents!$F$2:$F$408,"1949+",Documents!$AR$2:$AR$408,1) -> 1 | F15: =COUNTIFS(Documents!$P$2:$P$408,"Private deed*",Documents!$F$2:$F$408,"?",Documents!$AR$2:$AR$408,1) -> 2 | G15: =SUM(B15:F15) -> 62 | H15: =IFERROR(B15/B$5,0) -> 0.33333333 | I15: =IFERROR(C15/C$5,0) -> 0.55172414 | J15: =IFERROR(D15/D$5,0) -> 0.55813953
A16: 今欲有憑 closing | B16: =COUNTIFS(Documents!$P$2:$P$408,"Private deed*",Documents!$F$2:$F$408,"pre-1796",Documents!$AS$2:$AS$408,1) -> 8 | C16: =COUNTIFS(Documents!$P$2:$P$408,"Private deed*",Documents!$F$2:$F$408,"1796-1911",Documents!$AS$2:$AS$408,1) -> 55 | D16: =COUNTIFS(Documents!$P$2:$P$408,"Private deed*",Documents!$F$2:$F$408,"1912-1948",Documents!$AS$2:$AS$408,1) -> 42 | E16: =COUNTIFS(Documents!$P$2:$P$408,"Private deed*",Documents!$F$2:$F$408,"1949+",Documents!$AS$2:$AS$408,1) -> 4 | F16: =COUNTIFS(Documents!$P$2:$P$408,"Private deed*",Documents!$F$2:$F$408,"?",Documents!$AS$2:$AS$408,1) -> 3 | G16: =SUM(B16:F16) -> 112 | H16: =IFERROR(B16/B$5,0) -> 0.88888889 | I16: =IFERROR(C16/C$5,0) -> 0.94827586 | J16: =IFERROR(D16/D$5,0) -> 0.97674419
A17: 併繳 prior deeds | B17: =COUNTIFS(Documents!$P$2:$P$408,"Private deed*",Documents!$F$2:$F$408,"pre-1796",Documents!$AT$2:$AT$408,1) -> 1 | C17: =COUNTIFS(Documents!$P$2:$P$408,"Private deed*",Documents!$F$2:$F$408,"1796-1911",Documents!$AT$2:$AT$408,1) -> 17 | D17: =COUNTIFS(Documents!$P$2:$P$408,"Private deed*",Documents!$F$2:$F$408,"1912-1948",Documents!$AT$2:$AT$408,1) -> 15 | E17: =COUNTIFS(Documents!$P$2:$P$408,"Private deed*",Documents!$F$2:$F$408,"1949+",Documents!$AT$2:$AT$408,1) -> 0 | F17: =COUNTIFS(Documents!$P$2:$P$408,"Private deed*",Documents!$F$2:$F$408,"?",Documents!$AT$2:$AT$408,1) -> 1 | G17: =SUM(B17:F17) -> 34 | H17: =IFERROR(B17/B$5,0) -> 0.11111111 | I17: =IFERROR(C17/C$5,0) -> 0.29310345 | J17: =IFERROR(D17/D$5,0) -> 0.34883721
A18: 內改 correction | B18: =COUNTIFS(Documents!$P$2:$P$408,"Private deed*",Documents!$F$2:$F$408,"pre-1796",Documents!$AU$2:$AU$408,1) -> 0 | C18: =COUNTIFS(Documents!$P$2:$P$408,"Private deed*",Documents!$F$2:$F$408,"1796-1911",Documents!$AU$2:$AU$408,1) -> 9 | D18: =COUNTIFS(Documents!$P$2:$P$408,"Private deed*",Documents!$F$2:$F$408,"1912-1948",Documents!$AU$2:$AU$408,1) -> 6 | E18: =COUNTIFS(Documents!$P$2:$P$408,"Private deed*",Documents!$F$2:$F$408,"1949+",Documents!$AU$2:$AU$408,1) -> 0 | F18: =COUNTIFS(Documents!$P$2:$P$408,"Private deed*",Documents!$F$2:$F$408,"?",Documents!$AU$2:$AU$408,1) -> 1 | G18: =SUM(B18:F18) -> 16 | H18: =IFERROR(B18/B$5,0) -> 0 | I18: =IFERROR(C18/C$5,0) -> 0.15517241 | J18: =IFERROR(D18/D$5,0) -> 0.13953488
A19: 吉日 | B19: =COUNTIFS(Documents!$P$2:$P$408,"Private deed*",Documents!$F$2:$F$408,"pre-1796",Documents!$AV$2:$AV$408,1) -> 0 | C19: =COUNTIFS(Documents!$P$2:$P$408,"Private deed*",Documents!$F$2:$F$408,"1796-1911",Documents!$AV$2:$AV$408,1) -> 24 | D19: =COUNTIFS(Documents!$P$2:$P$408,"Private deed*",Documents!$F$2:$F$408,"1912-1948",Documents!$AV$2:$AV$408,1) -> 4 | E19: =COUNTIFS(Documents!$P$2:$P$408,"Private deed*",Documents!$F$2:$F$408,"1949+",Documents!$AV$2:$AV$408,1) -> 0 | F19: =COUNTIFS(Documents!$P$2:$P$408,"Private deed*",Documents!$F$2:$F$408,"?",Documents!$AV$2:$AV$408,1) -> 0 | G19: =SUM(B19:F19) -> 28 | H19: =IFERROR(B19/B$5,0) -> 0 | I19: =IFERROR(C19/C$5,0) -> 0.4137931 | J19: =IFERROR(D19/D$5,0) -> 0.093023256

Sheet Official_formulae
A1: Bureaucratic formulae by regime
A2: Pages typed "Official form" or "Private deed + state certificate". Regime = catalogue start year (<1912 Qing, <1949 Republic, else PRC).
A4: Step | B4: Formula | C4: Function | D4: Qing | E4: Republic | F4: PRC | G4: Total
A5: 1 | B5: 為…事 | C5: Purpose heading | D5: =COUNTIFS(Documents!$P$2:$P$408,"Official form",Documents!$G$2:$G$408,"Qing",Documents!$AW$2:$AW$408,1)+COUNTIFS(Documents!$P$2:$P$408,"Private deed + state certificate",Documents!$G$2:$G$408,"Qing",Documents!$AW$2:$AW$408,1) -> 21 | E5: =COUNTIFS(Documents!$P$2:$P$408,"Official form",Documents!$G$2:$G$408,"Republic",Documents!$AW$2:$AW$408,1)+COUNTIFS(Documents!$P$2:$P$408,"Private deed + state certificate",Documents!$G$2:$G$408,"Republic",Documents!$AW$2:$AW$408,1) -> 51 | F5: =COUNTIFS(Documents!$P$2:$P$408,"Official form",Documents!$G$2:$G$408,"PRC",Documents!$AW$2:$AW$408,1)+COUNTIFS(Documents!$P$2:$P$408,"Private deed + state certificate",Documents!$G$2:$G$408,"PRC",Documents!$AW$2:$AW$408,1) -> 0 | G5: =SUM(D5:F5) -> 72
A6: 2 | B6: 案奉 / 等因奉此 | C6: Quotes higher authority | D6: =COUNTIFS(Documents!$P$2:$P$408,"Official form",Documents!$G$2:$G$408,"Qing",Documents!$AX$2:$AX$408,1)+COUNTIFS(Documents!$P$2:$P$408,"Private deed + state certificate",Documents!$G$2:$G$408,"Qing",Documents!$AX$2:$AX$408,1) -> 16 | E6: =COUNTIFS(Documents!$P$2:$P$408,"Official form",Documents!$G$2:$G$408,"Republic",Documents!$AX$2:$AX$408,1)+COUNTIFS(Documents!$P$2:$P$408,"Private deed + state certificate",Documents!$G$2:$G$408,"Republic",Documents!$AX$2:$AX$408,1) -> 38 | F6: =COUNTIFS(Documents!$P$2:$P$408,"Official form",Documents!$G$2:$G$408,"PRC",Documents!$AX$2:$AX$408,1)+COUNTIFS(Documents!$P$2:$P$408,"Private deed + state certificate",Documents!$G$2:$G$408,"PRC",Documents!$AX$2:$AX$408,1) -> 0 | G6: =SUM(D6:F6) -> 54
A7: 3 | B7: 須至…者 | C7: Performative act of issuing | D7: =COUNTIFS(Documents!$P$2:$P$408,"Official form",Documents!$G$2:$G$408,"Qing",Documents!$AY$2:$AY$408,1)+COUNTIFS(Documents!$P$2:$P$408,"Private deed + state certificate",Documents!$G$2:$G$408,"Qing",Documents!$AY$2:$AY$408,1) -> 11 | E7: =COUNTIFS(Documents!$P$2:$P$408,"Official form",Documents!$G$2:$G$408,"Republic",Documents!$AY$2:$AY$408,1)+COUNTIFS(Documents!$P$2:$P$408,"Private deed + state certificate",Documents!$G$2:$G$408,"Republic",Documents!$AY$2:$AY$408,1) -> 46 | F7: =COUNTIFS(Documents!$P$2:$P$408,"Official form",Documents!$G$2:$G$408,"PRC",Documents!$AY$2:$AY$408,1)+COUNTIFS(Documents!$P$2:$P$408,"Private deed + state certificate",Documents!$G$2:$G$408,"PRC",Documents!$AY$2:$AY$408,1) -> 0 | G7: =SUM(D7:F7) -> 57
A8: 4 | B8: 右給…准此 | C8: Address and close | D8: =COUNTIFS(Documents!$P$2:$P$408,"Official form",Documents!$G$2:$G$408,"Qing",Documents!$AZ$2:$AZ$408,1)+COUNTIFS(Documents!$P$2:$P$408,"Private deed + state certificate",Documents!$G$2:$G$408,"Qing",Documents!$AZ$2:$AZ$408,1) -> 11 | E8: =COUNTIFS(Documents!$P$2:$P$408,"Official form",Documents!$G$2:$G$408,"Republic",Documents!$AZ$2:$AZ$408,1)+COUNTIFS(Documents!$P$2:$P$408,"Private deed + state certificate",Documents!$G$2:$G$408,"Republic",Documents!$AZ$2:$AZ$408,1) -> 37 | F8: =COUNTIFS(Documents!$P$2:$P$408,"Official form",Documents!$G$2:$G$408,"PRC",Documents!$AZ$2:$AZ$408,1)+COUNTIFS(Documents!$P$2:$P$408,"Private deed + state certificate",Documents!$G$2:$G$408,"PRC",Documents!$AZ$2:$AZ$408,1) -> 0 | G8: =SUM(D8:F8) -> 48
A9: – | B9: 罰 / 逾限 | C9: Penalties, deadlines | D9: =COUNTIFS(Documents!$P$2:$P$408,"Official form",Documents!$G$2:$G$408,"Qing",Documents!$BA$2:$BA$408,1)+COUNTIFS(Documents!$P$2:$P$408,"Private deed + state certificate",Documents!$G$2:$G$408,"Qing",Documents!$BA$2:$BA$408,1) -> 9 | E9: =COUNTIFS(Documents!$P$2:$P$408,"Official form",Documents!$G$2:$G$408,"Republic",Documents!$BA$2:$BA$408,1)+COUNTIFS(Documents!$P$2:$P$408,"Private deed + state certificate",Documents!$G$2:$G$408,"Republic",Documents!$BA$2:$BA$408,1) -> 38 | F9: =COUNTIFS(Documents!$P$2:$P$408,"Official form",Documents!$G$2:$G$408,"PRC",Documents!$BA$2:$BA$408,1)+COUNTIFS(Documents!$P$2:$P$408,"Private deed + state certificate",Documents!$G$2:$G$408,"PRC",Documents!$BA$2:$BA$408,1) -> 3 | G9: =SUM(D9:F9) -> 50
A10: – | B10: 訴訟 / 憑證 | C10: Validity as evidence in court | D10: =COUNTIFS(Documents!$P$2:$P$408,"Official form",Documents!$G$2:$G$408,"Qing",Documents!$BB$2:$BB$408,1)+COUNTIFS(Documents!$P$2:$P$408,"Private deed + state certificate",Documents!$G$2:$G$408,"Qing",Documents!$BB$2:$BB$408,1) -> 5 | E10: =COUNTIFS(Documents!$P$2:$P$408,"Official form",Documents!$G$2:$G$408,"Republic",Documents!$BB$2:$BB$408,1)+COUNTIFS(Documents!$P$2:$P$408,"Private deed + state certificate",Documents!$G$2:$G$408,"Republic",Documents!$BB$2:$BB$408,1) -> 27 | F10: =COUNTIFS(Documents!$P$2:$P$408,"Official form",Documents!$G$2:$G$408,"PRC",Documents!$BB$2:$BB$408,1)+COUNTIFS(Documents!$P$2:$P$408,"Private deed + state certificate",Documents!$G$2:$G$408,"PRC",Documents!$BB$2:$BB$408,1) -> 2 | G10: =SUM(D10:F10) -> 34
A12: Official pages (base) | D12: =COUNTIFS(Documents!$P$2:$P$408,"Official form",Documents!$G$2:$G$408,"Qing")+COUNTIFS(Documents!$P$2:$P$408,"Private deed + state certificate",Documents!$G$2:$G$408,"Qing") -> 66 | E12: =COUNTIFS(Documents!$P$2:$P$408,"Official form",Documents!$G$2:$G$408,"Republic")+COUNTIFS(Documents!$P$2:$P$408,"Private deed + state certificate",Documents!$G$2:$G$408,"Republic") -> 135 | F12: =COUNTIFS(Documents!$P$2:$P$408,"Official form",Documents!$G$2:$G$408,"PRC")+COUNTIFS(Documents!$P$2:$P$408,"Private deed + state certificate",Documents!$G$2:$G$408,"PRC") -> 25 | G12: =SUM(D12:F12) -> 226

Sheet Deed_types
A1: Deed titles (立…契/字/約) found in the OCR
A2: Title as recognised. 畫 is often an OCR misreading of 盡; 我 of 找. Stage is a manual grouping.
A4: Deed title | B4: Stage | C4: Pages | E4: Stage | F4: Pages
A5: 立典契 | B5: Conditional sale / pledge | C5: =COUNTIFS(Documents!$Q$2:$Q$408,A5,Documents!$P$2:$P$408,"Private deed*") -> 17 | E5: Conditional sale / pledge | F5: =SUMIF($B$5:$B$52,E5,$C$5:$C$52) -> 32
A6: 立賣斷契 | B6: Outright sale | C6: =COUNTIFS(Documents!$Q$2:$Q$408,A6,Documents!$P$2:$P$408,"Private deed*") -> 15 | E6: Top-up | F6: =SUMIF($B$5:$B$52,E6,$C$5:$C$52) -> 8
A7: 立賣契 | B7: Sale | C7: =COUNTIFS(Documents!$Q$2:$Q$408,A7,Documents!$P$2:$P$408,"Private deed*") -> 13 | E7: Final sale | F7: =SUMIF($B$5:$B$52,E7,$C$5:$C$52) -> 12
A8: 立契 | B8: Other | C8: =COUNTIFS(Documents!$Q$2:$Q$408,A8,Documents!$P$2:$P$408,"Private deed*") -> 10 | E8: Outright sale | F8: =SUMIF($B$5:$B$52,E8,$C$5:$C$52) -> 29
A9: 立賣斷根面全田契 | B9: Outright sale | C9: =COUNTIFS(Documents!$Q$2:$Q$408,A9,Documents!$P$2:$P$408,"Private deed*") -> 5 | E9: Sale | F9: =SUMIF($B$5:$B$52,E9,$C$5:$C$52) -> 21
A10: 立盡根斷賣契 | B10: Final sale | C10: =COUNTIFS(Documents!$Q$2:$Q$408,A10,Documents!$P$2:$P$408,"Private deed*") -> 4 | E10: Tenancy | F10: =SUMIF($B$5:$B$52,E10,$C$5:$C$52) -> 1
A11: 立轉典契 | B11: Conditional sale / pledge | C11: =COUNTIFS(Documents!$Q$2:$Q$408,A11,Documents!$P$2:$P$408,"Private deed*") -> 3 | E11: Family division | F11: =SUMIF($B$5:$B$52,E11,$C$5:$C$52) -> 0
A12: 立畫根斷賣契 | B12: Final sale | C12: =COUNTIFS(Documents!$Q$2:$Q$408,A12,Documents!$P$2:$P$408,"Private deed*") -> 3 | E12: Agreement | F12: =SUMIF($B$5:$B$52,E12,$C$5:$C$52) -> 3
A13: 立賣斷山契 | B13: Outright sale | C13: =COUNTIFS(Documents!$Q$2:$Q$408,A13,Documents!$P$2:$P$408,"Private deed*") -> 2 | E13: Other | F13: =SUMIF($B$5:$B$52,E13,$C$5:$C$52) -> 12
A14: 立湊字 | B14: Top-up | C14: =COUNTIFS(Documents!$Q$2:$Q$408,A14,Documents!$P$2:$P$408,"Private deed*") -> 2
A15: 立賣新契 | B15: Sale | C15: =COUNTIFS(Documents!$Q$2:$Q$408,A15,Documents!$P$2:$P$408,"Private deed*") -> 2
A16: 立典田根契 | B16: Conditional sale / pledge | C16: =COUNTIFS(Documents!$Q$2:$Q$408,A16,Documents!$P$2:$P$408,"Private deed*") -> 2
A17: 立典田面契 | B17: Conditional sale / pledge | C17: =COUNTIFS(Documents!$Q$2:$Q$408,A17,Documents!$P$2:$P$408,"Private deed*") -> 2
A18: 立合約 | B18: Agreement | C18: =COUNTIFS(Documents!$Q$2:$Q$408,A18,Documents!$P$2:$P$408,"Private deed*") -> 2
A19: 立湊斷契 | B19: Top-up | C19: =COUNTIFS(Documents!$Q$2:$Q$408,A19,Documents!$P$2:$P$408,"Private deed*") -> 2
A20: 立繳典契 | B20: Conditional sale / pledge | C20: =COUNTIFS(Documents!$Q$2:$Q$408,A20,Documents!$P$2:$P$408,"Private deed*") -> 2
A21: 立送字 | B21: Other | C21: =COUNTIFS(Documents!$Q$2:$Q$408,A21,Documents!$P$2:$P$408,"Private deed*") -> 1
A22: 立典屋契 | B22: Conditional sale / pledge | C22: =COUNTIFS(Documents!$Q$2:$Q$408,A22,Documents!$P$2:$P$408,"Private deed*") -> 1
A23: 立杜賣田皮骨契 | B23: Final sale | C23: =COUNTIFS(Documents!$Q$2:$Q$408,A23,Documents!$P$2:$P$408,"Private deed*") -> 1
A24: 立令賣契 | B24: Sale | C24: =COUNTIFS(Documents!$Q$2:$Q$408,A24,Documents!$P$2:$P$408,"Private deed*") -> 1
A25: 立賣與契 | B25: Sale | C25: =COUNTIFS(Documents!$Q$2:$Q$408,A25,Documents!$P$2:$P$408,"Private deed*") -> 1
... A52: 立白契 | B52: Other | C52: =COUNTIFS(Documents!$Q$2:$Q$408,A52,Documents!$P$2:$P$408,"Private deed*") -> 1

Sheet Land_and_money
A1: Land and currency vocabulary
A2: Pages whose extracted land-term / currency field contains the term (all page types).
A4: Term | B4: Meaning | C4: Pages
A5: 田根 | B5: Root layer: the subsoil right, carries the land tax | C5: =COUNTIF(Documents!$Y$2:$Y$408,"*田根*") -> 12
A6: 田面 | B6: Surface layer: the right to farm or collect rent | C6: =COUNTIF(Documents!$Y$2:$Y$408,"*田面*") -> 14
A7: 根面全田 | B7: Both layers together (full ownership) | C7: =COUNTIF(Documents!$Y$2:$Y$408,"*根面全田*") -> 11
A8: 皮骨 | B8: Skin and bone: surface plus root (mountain land) | C8: =COUNTIF(Documents!$Y$2:$Y$408,"*皮骨*") -> 6
A9: 苗米 | B9: Grain levy attached to the field | C9: =COUNTIF(Documents!$Y$2:$Y$408,"*苗米*") -> 7
A10: 民田 | B10: Commoner (taxable) field | C10: =COUNTIF(Documents!$Y$2:$Y$408,"*民田*") -> 40
A11: 山場 | B11: Hill land | C11: =COUNTIF(Documents!$Y$2:$Y$408,"*山場*") -> 5
A12: 山埔 | B12: Hill land / slope | C12: =COUNTIF(Documents!$Y$2:$Y$408,"*山埔*") -> 1
A13: 厝屋 | B13: House (Min dialect 厝) | C13: =COUNTIF(Documents!$Y$2:$Y$408,"*厝屋*") -> 19
A14: 店屋 | B14: Shop-house | C14: =COUNTIF(Documents!$Y$2:$Y$408,"*店屋*") -> 7
A15: 基地 | B15: House plot | C15: =COUNTIF(Documents!$Y$2:$Y$408,"*基地*") -> 8
A16: 茶山 | B16: Tea hill | C16: =COUNTIF(Documents!$Y$2:$Y$408,"*茶山*") -> 3
A17: 墳 | B17: Grave site | C17: =COUNTIF(Documents!$Y$2:$Y$408,"*墳*") -> 7
A20: Currency | B20: Meaning | C20: Pages
A21: 紋銀 | B21: Sycee silver (taels) | C21: =COUNTIF(Documents!$V$2:$V$408,"*紋銀*") -> 4
A22: 番銀 | B22: Foreign silver dollars | C22: =COUNTIF(Documents!$V$2:$V$408,"*番銀*") -> 2
A23: 先番 | B23: Foreign silver dollars (older style) | C23: =COUNTIF(Documents!$V$2:$V$408,"*先番*") -> 1
A24: 洋銀 | B24: Foreign silver dollars | C24: =COUNTIF(Documents!$V$2:$V$408,"*洋銀*") -> 8
A25: 佛銀 | B25: "Buddha" silver dollars (Spanish/Carolus) | C25: =COUNTIF(Documents!$V$2:$V$408,"*佛銀*") -> 1
A26: 台伏 | B26: Fuzhou local banknote / account dollar | C26: =COUNTIF(Documents!$V$2:$V$408,"*台伏*") -> 4
A27: 大洋 | B27: Silver yuan (large coin) | C27: =COUNTIF(Documents!$V$2:$V$408,"*大洋*") -> 22
A28: 小洋 | B28: Subsidiary coin | C28: =COUNTIF(Documents!$V$2:$V$408,"*小洋*") -> 1
A29: 錢文 | B29: Copper cash | C29: =COUNTIF(Documents!$V$2:$V$408,"*錢文*") -> 6
A30: 國幣 | B30: Republican national currency | C30: =COUNTIF(Documents!$V$2:$V$408,"*國幣*") -> 15
A31: 法幣 | B31: Fabi (1935+ legal tender) | C31: =COUNTIF(Documents!$V$2:$V$408,"*法幣*") -> 4
A32: 銀元 | B32: Silver yuan | C32: =COUNTIF(Documents!$V$2:$V$408,"*銀元*") -> 5
A33: 人民幣 | B33: Renminbi (PRC) | C33: =COUNTIF(Documents!$V$2:$V$408,"*人民幣*") -> 6

Sheet Deed_chains
A1: Documents that cite each other
A3: Chain | B3: Page ID | C3: Date | D3: Document | E3: Party | F3: Place | G3: Price | H3: Middleman | I3: Note
A4: A | B4: 31735064607843_001 | C4: 1805 | D4: 立轉典契 (re-pledge deed) | E4: 趙守藻 | F4: 侯官縣草市都馬坑 | G4: 銀壹拾肆兩 | H4: 楊海武 | I4: Re-pledges rented-out surface rights 田面
A5: A | B5: 31735064607884_001 | C5: 1922 | D5: 福建國稅廳籌備處 典按契單 (deed certificate) | E5: 林有柱 (holder); 趙華藻 (pledgor) | F5: 閩侯縣草市都馬坑 | G5: 原價銀拾肆兩 | H5: 楊海武 | I5: Certificate quotes 嘉慶拾年 pledge; 華/守 likely OCR or copy variant
A6: B | B6: 31735064607488_001 | C6: 1870 | D6: 立賣斷契 (outright sale) | E6: 吳開成 et al. → 陳 | F6: 閩邑橫街舖 | G6: 銀陸拾捌兩 | H6: 李懷鏡 | I6: Hands over 25 papers: redemption deeds, loan note, conditional-sale deeds, 14 old taxed deeds

Sheet OCR_issues
A1: OCR problems to fix before quantitative work
A3: Issue | B3: OCR reads | C3: Should be | D3: Effect
A4: Similar-character misread | B4: 閩書 / 閩分 | C4: 鬮書 / 鬮分 | D4: Family-division provenance hidden
A5: Similar-character misread | B5: 增我杜新契 | C5: 增找杜新契 | D5: Top-up deeds mislabelled
A6: Similar-character misread | B6: 托牛 | C6: 托中 | D6: Mediation under-counted
A7: Similar-character misread | B7: 畫契 / 畫紙 | C7: 盡契 / 壹紙 (check image) | D7: Deed-type labels wrong
A8: Similar-character misread | B8: 市政使司 | C8: 布政使司 | D8: Office name wrong
A9: Similar-character misread | B9: 卦色 | C9: 糧色 (probable) | D9: Tax clause unreadable
A10: Reversed reading order | B10: 處理管食糧賦田 | C10: 田賦糧食管理處 | D10: 1940s tax forms scrambled
A11: Repetition / hallucination | B11: 福建等處承宣市政使司也 ×15 | C11: — | D11: Inflates counts
A12: English descriptions | B12: "Vertical columns of text…" | C12: — | D12: Remove before text mining
A13: Flattened columns | B13: Signature block in one line | C13: — | D13: Roles attached to wrong names
A15: Pages with truncated blocks | B15: =COUNTIF(Documents!$BE$2:$BE$408,">0") -> 43
A16: Pages with English mixed in | B16: =COUNTIF(Documents!$BF$2:$BF$408,">0") -> 12
A17: Total truncated blocks | B17: =SUM(Documents!$BE$2:$BE$408) -> 155
